Workbook

Sheet 管理表
A1: 区 | B1: No | C1: 勤務地 | D1: 国籍 | E1: 社員コード | F1: 写真 | G1: フリガナ | H1: 氏名 | I1: 呼名 | J1: 性別 | K1: 生年月日 | L1: 年齢 | M1: 配偶者 | N1: 登録支援機関 | O1: 入社日 | P1: 帰国予定 | Q1: 実習区分 | R1: 住所 | S1: 個・相部屋 | T1: 家賃負担 | U1: 雇用条件書 | V1: カード期限 | W1: 在留カード番号 | X1: 雇用保険番号 | Y1: 自転車渡日 | Z1: 自転車No-防犯 | AA1: 自転車回収日 | AB1: 日本語検定 | AC1: 試験資格 | AD1: 一時退職日 | AE1: 一時帰国From | AF1: 一時帰国To | AG1: 再入社 | AH1: 退職区分 | AI1: 退職日 | AJ1: 帰国費用 | AK1: 部署長 | AL1: 特定1号 保険加入 | AM1: 特定1号 入国日 | AN1: 特定1号保険期間 | AO1: 給与口座 | AP1: 備考 | AQ1: 在留カード表裏 | AR1: パスポート | AS1: 特定保険証券 | AT1: 通帳 | AU1: 保険証 | AV1: 日本語合格 | AW1: 特定２号合格 | AX1: 免許関係 | AY1: その他１（写真） | AZ1: その他２（写真） | BA1: その他１（ファイル） | BB1: その他２（ファイル）
B2: 1 | C2: 津吉 | D2: ベトナム | E2: 07011401 | G2: ホアン ティ フォン | H2: HOANG THI HUONG | I2: ホアンフォン | J2: 女 | K2: 31861 | L2: =DATEDIF(K2,TODAY(),"Y") -> 39 | N2: 中四国 | O2: 43040 | P2: 2022/11 | Q2: 技能実習3号 | R2: 松山市津吉町535-1コーポ津吉1-2 | V2: 44893 | W2: ＤＸ30707722ＰＣ | X2: 5100-318356-1 | AH2: 退職 | AI2: 44831
B3: 2 | C3: 津吉 | D3: ベトナム | E3: 07011502 | G3: ドー ティ ミー ハイン | H3: DO THI MI HANH | I3: ハイン | J3: 女 | K3: 32774 | L3: =DATEDIF(K3,TODAY(),"Y") -> 36 | N3: 中四国 | O3: 43040 | P3: 2022/11 | Q3: 技能実習3号 | R3: 松山市津吉町535-1コーポ津吉1-2 | V3: 44893 | W3: ＤＸ89886995ＰＣ | X3: 5100-318488-1 | AH3: 退職 | AI3: 44879
A4: =_xludf.IMAGE("F96",1) -> #NAME? | B4: 3 | C4: 津吉 | D4: ベトナム | E4: 07011602 | F4: /appsheet/photograph/3.写真.030343.jpg | G4: グエン ビック フーン | H4: NGUYEN BICH PHUONG | I4: フーン | J4: 女 | K4: 31664 | L4: =DATEDIF(K4,TODAY(),"Y") -> 39 | M4: 有 | N4: 中四国 | O4: 43040 | P4: 2027/01 | Q4: 特定技能１号 | R4: 松山市津吉町535-1コーポ津吉1-2 | S4: 個 | T4: 20000 | U4: 45887 | V4: 46327 | W4: UH17492757PC | X4: 5100-318256-3 | Z4: 通勤は自転車B-0128657 白26ｲﾝﾁABELIA 買い物と外出時は ｱｼｽﾄ自転車（知人から貰った） | AA4: 2026/02/13 | AE4: 45711 | AF4: 45732 | AH4: 退職 | AI4: 46066 | AJ4: 広島→ハノイ 79,500- 空港までは自己で行くが荷物２個は空港まで会社負担 | AK4: 帰国 飛行機代会社負担 | AL4: 〇 | AM4: 44866 | AN4: 2025/8/1～2026/7/31 ※2026年に帰国予定の 為、本人より1年間の契約希望 | AO4: ひめぎん 末広町支店 | AP4: 2/20まで出勤・3/17より出勤 2026/2月に退職して帰国したい申し出。 新開工場長へ連絡済み。帰りの飛行機代を確認依頼。 帰りの飛行機代は会社負担（専務了承済） 2026/2/13退職 最終出勤日1/22（1/23～有給消化） 2/14退寮 2/13 給料現金払い 1/23～夫のところへ行くため、1/23～2/14までの光熱費 は￥1000請求（尾崎さんより1/14） 2/9口座解約、転出届予定。
B5: 4 | C5: 津吉 | D5: ベトナム | E5: 07011603 | G5: ヴー ティ アイン | H5: VU THI ANH | I5: アイン | J5: 女 | K5: 35781 | L5: =DATEDIF(K5,TODAY(),"Y") -> 28 | N5: 中四国 | O5: 43040 | P5: 2027/10 | Q5: 特定技能１号 | R5: 松山市津吉町535-1コーポ津吉1-2 | V5: 45231 | W5: TJ66354580PA | X5: 5100-318538-2 | AH5: 退職 | AI5: 45127
B6: 5 | C6: 本社 | D6: ベトナム | E6: 07001701 | G6: ブイ ティ チン | H6: BUI THI CHINH | I6: チン | J6: 女 | K6: 34817 | L6: =DATEDIF(K6,TODAY(),"Y") -> 30 | N6: 中四国 | O6: 43162 | P6: 2029/06 | Q6: 特定技能１号 | R6: 和泉北1-20-28アトムスカイマンション401 | S6: 個 | T6: 20000 | V6: 45483 | W6: NP48961811PA | X6: 特定技能 23.7/10～ | Z6: 番号なし 福岡47－え5316 | AA6: 2024/04/21 小栗工場裏 | AB6: N3:2021.7月 | AE6: 44958 | AF6: 45000 | AH6: 退職 | AI6: 45402 | AJ6: 2024.4月完全帰国 帰国費用会社負担 | AP6: 24.4.20退職決定（4/17最終出勤日、4/18～4/20は有休） 4/22退寮
B7: 6 | C7: 本社 | D7: ベトナム | E7: 07001502 | G7: チャン ティ ガー | H7: TRAN THI NGA | I7: ガー | J7: 女 | K7: 32727 | L7: =DATEDIF(K7,TODAY(),"Y") -> 36 | N7: 中四国 | O7: 43435 | P7: 2023/11 | Q7: 技能実習3号 | R7: 小栗1丁目3-30ﾋﾟｯｺﾛｶｽﾀｰﾆｬ308 | V7: 45273 | W7: TJ69040729PC | X7: 5103-260930-7 | AH7: 退職 | AI7: 45198
B8: 7 | C8: 本社 | D8: ベトナム | E8: 07001509 | F8: =_xludf.IMAGE(F9) -> #NAME? | G8: ブイ ティ ヴィエトザン | H8: BUI THI VIET GIANG | I8: ザン | J8: 女 | K8: 35832 | L8: =DATEDIF(K8,TODAY(),"Y") -> 28 | N8: 中四国 | O8: 43435 | P8: 2023/11 | Q8: 技能実習3号 | R8: 雄郡1丁目6-2ｱﾙﾄ雄郡西405 | V8: 45273 | W8: TJ53898721PC | X8: 5103-260928-3 | AH8: 退職 | AI8: 45259
B9: 8 | C9: 本社 | D9: ベトナム | E9: 07001612 | F9: /appsheet/photograph/小栗_タム_20240424.jpg | G9: グエン ティ タム | H9: NGUYEN THI TAM | I9: タム | J9: 女 | K9: 33800 | L9: =DATEDIF(K9,TODAY(),"Y") -> 33 | M9: 無 | N9: 中四国 | O9: 43435 | P9: 2025/09 | Q9: 特定技能１号 | R9: 和泉北1-20-28アトムスカイマンション304 | S9: 相1 | T9: 10000 | U9: 45383 | V9: 45912 | W9: SA28686623PA | X9: 5103-260925-5 | Z9: 1966ーB-0091966 | AB9: N4 2024/07/07 | AD9: 45311 | AE9: 45311 | AF9: 45342 | AG9: 45343 | AH9: 退職 | AI9: 45646 | AJ9: 実習終了後完全帰国 12/23 松山→成田15,000 宿泊 12/24 成田→ハノイ80,000 | AP9: 2024.6.12～社員コード変わる済（特定活動になるため） 2024.6.12～9/152実習3号→特定活動 9/12～特定技能へ
B10: 9 | C10: 本社 | D10: ベトナム | E10: 07001611 | F10: /appsheet/photograph/小栗_ミン_20240424.jpg | G10: ブイ ティ ミン | H10: BUI THI MINH | I10: ミン | J10: 女 | K10: 36245 | L10: =DATEDIF(K10,TODAY(),"Y") -> 27 | M10: 夫婦 | N10: 中四国 | O10: 43435 | P10: 2025/09 | Q10: 特定技能１号 | R10: 和泉北1-20-28アトムスカイマンション305 | S10: 夫婦 | T10: 20000 | U10: 45870 | V10: 46294 | W10: UH54552117PC | X10: 5103-260929-6 | Z10: 返却済 宮内工場長の自転車を乗っている | AB10: N4 2024/07/07 | AE10: 45271 | AF10: 45311 | AL10: 〇 | AM10: ２018/10/30 | AN10: 2025/8/1～2029/9/30 | AO10: 伊予銀 | AP10: ※特定技能申請の為、ﾊﾟｽﾎﾟｰﾄと在留ｶｰﾄﾞは中四国預かり（6/13朴さんより） 2024.6.12～社員コード変わる済（特定活動になるため） 2024.6.12～9.12実習3号→特定活動 9/12～特定技能へ ※特定活動（6ヵ月）申請しその期間に特定技能へ変更予定。 2026/5/4出産予定日 一時帰国し出産予定。2026/3/24～6/29産休 6/30～2027/5/3育休
B11: 10 | C11: 本社 | D11: ベトナム | E11: 07001613 | F11: /appsheet/photograph/10.写真.032947.jpg | G11: グエン ティ ロアン | H11: NGUYEN THI LOAN | I11: ロアン | J11: 女 | K11: 31701 | L11: =DATEDIF(K11,TODAY(),"Y") -> 39 | M11: 有 | N11: 中四国 | O11: 43435 | P11: 2025/09 | Q11: 特定技能１号 | R11: 和泉北1-20-28アトムスカイマンション403 | S11: 個1 | T11: 20000 | U11: 45870 | V11: 46294 | W11: UH51964624PC | X11: 5103-260926-8 | Z11: 1968-B-0091968 2024/08/27自転車変更 7912(1596)赤へ 2025/08/27変更 B-0246665-1008 | AD11: 45317 | AE11: 2024/01/27 2026/5月頃 | AF11: 2024/02/27 2026/7月頃 | AG11: 45350 | AL11: 〇 | AM11: 43403 | AN11: 2025/8/1～2029/5/31 | AO11: 伊予銀 湊町支店 | AP11: ※特定技能申請の為、ﾊﾟｽﾎﾟｰﾄと在留ｶｰﾄﾞは中四国預かり（6/13朴さんより） 2024.6.12～社員コード変わる済（特定活動になるため） 2024.6.12～9/152実習3号→特定活動 9/12～特定技能へ ※特定活動（6ヵ月）申請しその期間に特定技能へ変更予定。 2022.7.18一時退職8/9～一時帰国 2024.1.26一時退職 2025/10/4 2～3年前から週に5日程下痢が続いているため、窪田クリニックを受診。便検査の結果、病原性大腸菌O-18が見つかり、ベロ毒素の検査結果は陰性。（陽性であれば保健所に届け出が必要とのこと）。除菌のため、抗生物質の薬を5日服用し、5日後に再度便検査を病院でする予定。 | AT11: /appsheet/photograph/07001613.通帳.040920.jpg
B12: 11 | C12: 協同本社 | D12: ベトナム | E12: 17001003 | G12: チャン ティ トゥー ヒエン転籍 | H12: TRAN THI THU HIEN | I12: ヒエン | J12: 女 | K12: 33673 | L12: =DATEDIF(K12,TODAY(),"Y") -> 34 | N12: 中四国 | O12: 43627 | P12: 2024/06 | Q12: 技能実習3号 | R12: 和泉北1-20-28アトムスカイマンション403 | V12: 45116 | W12: TJ09931713PC | X12: 5105-142066-5 | Z12: 1905-1056 | AA12: 小栗工場裏 | AH12: 退職 | AI12: 45066 | AP12: 2025年頃日本に戻って技能実習を再開したいとの希望あり
B13: 12 | C13: 本社 | D13: ベトナム | E13: 07001614 | F13: /appsheet/photograph/12.写真.224547.jpg | G13: ホアン ティ チャン | H13: HOANG THI TRANG | I13: チャン | J13: 女 | K13: 34922 | L13: =DATEDIF(K13,TODAY(),"Y") -> 30 | N13: 中四国 | O13: 43627 | P13: 2025/09 | Q13: 特定技能１号 | R13: 和泉北1-20-28アトムスカイマンション403 | S13: 個2 | T13: 20000 | U13: 45870 | V13: 46294 | W13: UH80838380PC | X13: 5105-142112-5 | Z13: 2021/01購入 なし-B-0188562 | AE13: 44760 | AF13: 44803 | AL13: 〇 | AM13: 43594 | AN13: 2025/8/1～2029/5/31 | AO13: 伊予銀 | AP13: ※特定技能申請の為、ﾊﾟｽﾎﾟｰﾄと在留ｶｰﾄﾞは中四国預かり（6/13朴さんより） 2024.6.12～9/12 実習3号→特定活動 9/12～特定技能へ ※特定活動（6ヵ月）申請しその期間に特定技能へ変更予定。 2024.6.12～（協同→中温へ転籍）
B14: 13 | C14: 協同本社 | D14: ベトナム | G14: チャン ティ フォン | H14: TRAN THI HUONG | I14: チャンフォン | J14: 女 | K14: 32356 | L14: =DATEDIF(K14,TODAY(),"Y") -> 37 | N14: 中四国 | O14: 43627 | Q14: 技能実習2号 | R14: 和泉北1-20-28アトムスカイマンション402 | V14: 44327 | W14: LD29267624PC | X14: 5105-141994-8 | AH14: 退職 | AI14: 44679
B15: 14 | C15: 本社 | D15: ベトナム | E15: 07001404 | G15: チャン ティ フォン | H15: TRAN THI HUONG | I15: フォン | J15: 女 | K15: 36187 | L15: =DATEDIF(K15,TODAY(),"Y") -> 27 | N15: 中四国 | O15: 43879 | P15: 2023/01 | Q15: 技能実習2号 | R15: 和泉北1-20-28アトムスカイマンション305 | V15: 44984 | W15: TJ51126887PC | X15: 5106-445108-4 | AH15: 退職 | AI15: 44941
B16: 15 | C16: 津吉 | D16: ベトナム | E16: 07011405 | G16: グエン ティ ゴック タオ | H16: NGUYEN THI NGOC THAO | I16: タオ | J16: 女 | K16: 34452 | L16: =DATEDIF(K16,TODAY(),"Y") -> 31 | N16: 中四国 | O16: 43729 | P16: 2022/08 | Q16: 技能実習2号 | R16: 松山市津吉町535-1コーポ津吉1-6 | V16: 44794 | W16: DX17958926PC | X16: 5105-743699-4 | AH16: 退職 | AI16: 44793
B17: 16 | C17: 津吉 | D17: ベトナム | E17: 07011504 | G17: ファム ティ ヒエン | H17: PHAM THI HIEN | I17: ファムヒエン | J17: 女 | K17: 36585 | L17: =DATEDIF(K17,TODAY(),"Y") -> 26 | N17: 中四国 | O17: 43729 | P17: 2024/08 | Q17: 技能実習3号 | R17: 松山市津吉町535-1コーポ津吉1-6 | T17: 20000 | U17: 44690 | V17: 45587 | W17: NP60084115PC | X17: 5105-743702-4 | Z17: 自身で購入 会社支給 管理番号なし B-0128655 買い物等は自転車使用 | AA17: 45394 | AC17: 缶詰巻締上級 2024/09/12 | AE17: 44958 | AF17: 45000 | AH17: 退職 | AI17: 45568 | AJ17: 実習終了帰国 松山→ベトナム ６３，６００円 | AP17: 2024.10.3実習3号終了が正しい 実習終了にて帰国予定 有給１６日在留カード期限10/22だが、10/3が実習終了のため9/9最終出勤、10/3退職 10/4退寮 現金支払い
B18: 17 | C18: 津吉 | D18: ベトナム | E18: 07011402 | G18: グエン ティ トゥー | H18: NGUYEN THI THU | I18: トゥー | J18: 女 | K18: 31954 | L18: =DATEDIF(K18,TODAY(),"Y") -> 38 | N18: 中四国 | O18: 43729 | P18: 2022/08 | Q18: 技能実習2号 | R18: 松山市津吉町535-1コーポ津吉1-6 | V18: 44794 | W18: DX99865766PC | X18: 5105-743700-9 | AH18: 退職 | AI18: 44793
B19: 18 | C19: 本社 | D19: ベトナム | E19: 07001403 | G19: グエン ティ トゥー | H19: NGUYEN THI THU | I19: トゥー | J19: 女 | K19: 33508 | L19: =DATEDIF(K19,TODAY(),"Y") -> 34 | N19: 中四国 | O19: 43879 | P19: 2023/01 | Q19: 特定技能１号 | R19: 和泉北1-20-28アトムスカイマンション305 | V19: 45332 | W19: NP29436386PA | X19: 5106-445109-7 | AH19: 退職 | AI19: 45066
B20: 19 | C20: 津吉 | D20: ベトナム | E20: 07011613 | F20: /appsheet/photograph/19.写真.032434.jpg | G20: ファム ティ チン | H20: PHAM THI CHINH | I20: チン | J20: 女 | K20: 33243 | L20: =DATEDIF(K20,TODAY(),"Y") -> 35 | M20: 夫婦 | N20: 中四国 | O20: 43729 | P20: 2029/08 | Q20: 特定技能１号 | R20: 松山市上野町774番地ビレッジハウス松山上野1-303 | S20: 夫婦 | T20: 0 | U20: 45912 | V20: 46360 | W20: UH90854712PC | X20: 5105-743701-1 | Z20: ご主人のバイクで通勤 会社支給 管理番号なし B-0128654 白26ｲﾝﾁ | AA20: 通勤方法確認書 には通勤、買い物も 会社の自転車使用 と記載あり | AE20: 45707 | AF20: 45707 | AH20: 育児休暇中 | AJ20: 2025/03/11帰国費用 広島⇔ハノイ74,300円 半額負担し、特定終了後は 負担しない | AL20: × | AN20: 自転車保険 2026/09/15 | AP20: ビレッジハウス 個人で契約するとのこと 妊娠のため2025.9月末頃？～産休（予定日11/7）2025.5.30出産で9月頃退職後一時帰国予定。（子供が1才になるまで）再度中温へ戻りたいとの希望あり。→中四国朴さんより、日本で出産すると本人が言っているとのこと。寮は次が確定しているため、再度確認依頼済。 2024/12/04～特定技能 2024/10/04～特定活動 2024.10.20 実習3号終了予定 130ズオンデタオが夫 2024/09/18 特定技能へ申請手続き 2024/09/25コーポ津吉1-6よりビレッジ2-503へ引越→通勤届済 2025.9.5引越 ビレッジ1-303へ（チン名義で借りる） 2025.9.27～育児休暇 2026/10/20までは確定 2025.11.4帝王切開予定 2025.10/31出産 | AQ20: /appsheet/photograph/07011613.在留カード表裏.072221.pdf
B21: 20 | C21: 津吉 | D21: ベトナム | E21: 07011506 | G21: カオ ティ トム | H21: CAO THI THOM | I21: トム | J21: 女 | K21: 36177 | L21: =DATEDIF(K21,TODAY(),"Y") -> 27 | N21: 中四国 | O21: 43762 | P21: 2024/09 | Q21: 技能実習3号 | R21: 松山市津吉町535-1コーポ津吉1-6 | V21: 45221 | W21: TJ09914475PC | X21: 5105-880527-2 | AH21: 退職 | AI21: 45158
B22: 20 | D22: ベトナム | G22: ズオン トアン タン （チン、タオの赤ちゃん） | H22: DUONG TOAN THANG | J22: 男 | K22: 45961 | L22: 0 | Q22: 特定活動 | R22: 松山市上野町774番地ビレッジハウス松山上野1-303 | S22: チン、タオの子供 | V22: 46373 | W22: UH90942141PC | AL22: ― | AM22: ― | AN22: ― | AP22: こちらでチンの更新と一緒に在留カード更新する｡
B23: 21 | C23: 津吉 | D23: ベトナム | E23: 07011764 | G23: グエン ヴァン ハオ | H23: NGUYEN VAN HAO | I23: ハオ | J23: 男 | K23: 34732 | L23: =DATEDIF(K23,TODAY(),"Y") -> 31 | N23: 中四国 | O23: 44616 | P23: ? | Q23: 特定活動 | R23: 松山市上野町774番地ビレッジハウス松山上野2-508 | V23: 44964 | W23: TJ88198592RA | X23: 5098-636935-8 | AH23: 退職 | AI23: 44956
B24: 22 | C24: 津吉 | D24: ベトナム | E24: 07011601 | G24: ビー ティー ジェム フォン | H24: VI THI DIEM HUONG | I24: ビーフォン | J24: 女 | K24: 34241 | L24: =DATEDIF(K24,TODAY(),"Y") -> 32 | N24: 中四国 | O24: 42655 | P24: 2024/09 | Q24: 特定技能１号 | R24: 松山市津吉町535-1コーポ津吉1-2 | V24: 45207 | W24: TJ92560142PA | X24: 5097-085709-2 | AH24: 退職 | AI24: 45005
B25: 23 | C25: 津吉 | D25: ベトナム | G25: グエン ティ チャム フェン | H25: NGUYEN THI TRAM HUYEN | I25: チャムフェン | J25: 女 | K25: 33824 | L25: =DATEDIF(K25,TODAY(),"Y") -> 33 | N25: ポエム | O25: 44013 | P25: ? | Q25: 特定活動 | R25: 津吉町535-1コーポ津吉2-4 | V25: 44735 | W25: DX99566980PC | X25: 5105-699781-1 | AH25: 退職 | AI25: 44712
B26: 24 | C26: 津吉 | D26: ベトナム | E26: 07011761 | G26: ホアン ティ ハン★ | H26: HOANG THI HAN | I26: ハン | J26: 女 | K26: 32890 | L26: =DATEDIF(K26,TODAY(),"Y") -> 36 | N26: ポエム | O26: 44013 | Q26: 特定活動 | R26: 津吉町535-1コーポ津吉2-4 | V26: 44857 | W26: ＴＪ04286685PC | X26: 5105-385457-3 | AH26: 退職 | AI26: 44854
B27: 25 | C27: 津吉 | D27: ベトナム | E27: 07011762 | G27: ヴー ティ・ホアン★ | H27: VU THI HOAN | I27: ホアン | J27: 女 | K27: 32353 | L27: =DATEDIF(K27,TODAY(),"Y") -> 37 | N27: ポエム | O27: 44013 | P27: ? | Q27: 特定活動 | R27: 津吉町535-1コーポ津吉2-4 | V27: 44857 | W27: ＴＪ39383067PC | X27: 5105-385458-6 | Z27: 2104? | AH27: 退職 | AI27: 44854
B28: 26 | C28: 津吉 | D28: ベトナム | E28: 07011606 | F28: /appsheet/photograph/26.写真.001347.jpg | G28: ヴー ティ ホアン | H28: VU THI HOAN | I28: ホアン | J28: 女 | K28: 32353 | L28: =DATEDIF(K28,TODAY(),"Y") -> 37 | M28: 有 | N28: 中四国 | O28: 45111 | P28: 2028/06 | Q28: 特定技能１号 | R28: 松山市津吉町535-1コーポ津吉1-2 | S28: 個 | T28: 20000 | U28: 45734 | V28: 46206 | W28: UH16081560PA | Z28: 2104 通勤、買い物も会社 支給の自転車使用 | AC28: 2026/1月２号試験希望_統括より | AD28: 46101 | AE28: 2024/07/01 2026/01/24 | AF28: 2024/08/01 2026/03/21 | AH28: 一時退職 | AL28: 〇 | AM28: 45110 | AN28: 2025/8/1～2028/6/30 | AP28: 24.7/3頃～8/5頃一時帰国 新開工場長へ申請あり4/24 →中四国 からの日程の連絡待ち。→6/30～7/31確定（6/19中四国より） 本人からの休暇届けは7/1～8/1一時帰国（全て有給申請）となって いるため、中四国廣瀬さんへ確認依頼済（6/28中に） 一時帰国後8/6以降順風会で健診予定 24.4月分～ﾎｱﾝﾃｨﾊﾝが入寮したら家賃2万→1万へ 2026.1月 特定2号受験予定 2025/11/7特定2号試験終了後、２月初めから、２ヶ月一時帰国したい申し出あり。水沼さん了承。 | AW28: /appsheet/photograph/07011606.特定２号合格.011012.pdf
B29: 27 | C29: 津吉 | D29: ベトナム | E29: 07011763 | G29: チャン ティ ホアン リェン | H29: TRAN THI HOANG LIEN | I29: リエン | J29: 女 | K29: 30163 | L29: =DATEDIF(K29,TODAY(),"Y") -> 43 | N29: ポエム | O29: 44013 | P29: ? | Q29: 特定活動 | R29: 松山市津吉町535-1コーポ津吉1-6 | V29: 44857 | W29: ＴＪ53602521PC | X29: 5105-385461-2 | AH29: 退職 | AI29: 44854
B30: 28 | C30: 本社 | D30: ベトナム | E30: 07001609 | F30: /appsheet/photograph/IDPhoto_20240711_マイン.jpg | G30: トー マイン トゥ | H30: TO MANH TU | I30: マイン | J30: 男 | K30: 34747 | L30: =DATEDIF(K30,TODAY(),"Y") -> 31 | N30: 中四国 | O30: 44119 | P30: 2028/08 | Q30: 特定技能１号 | R30: 小栗1丁目3-30ﾋﾟｯｺﾛｶｽﾀｰﾆｬ308 | S30: 個 | T30: 20000 | U30: 45484 | V30: 45912 | W30: SA48074257PA | X30: 5109-022627-2 | Z30: 2020/10購入 B-0177518-1040 | AD30: 45306 | AE30: 45306 | AF30: 45341 | AG30: 45343 | AH30: 退職 | AI30: 45904 | AJ30: 帰国 | AL30: ― | AN30: ― | AO30: ― | AP30: 特定技能1号期間更新中 24.7.11 2025.8月か9月頃に帰国希望（工場長より） 2025/08/31ピッコロ解約し、9/5退職9/9頃帰国 9/1～9/5アトム504 9/4退職、9/5退寮 有給残10日あり ※最終出勤日8/27 9/5現金払い
B31: 29 | C31: 本社 | D31: ベトナム | E31: 07001629 | F31: /appsheet/photograph/IDPhoto_20240711_ヴィエット.jpg | G31: チャン ヴァン ヴィエット | H31: TRAN VAN VIET | I31: ヴィエット | J31: 男 | K31: 32955 | L31: =DATEDIF(K31,TODAY(),"Y") -> 36 | N31: 中四国 | O31: 44119 | P31: 2028/08 | Q31: 特定技能１号 | R31: 和泉北1-20-28アトムスカイマンション504 | S31: 相1 | T31: 20000 | U31: 2025/08/01 2026/01/31 | V31: 46294 | W31: UH63950753PC | X31: 5109-022666-1 | Z31: 2020/10購入 紛失17000002-B-0177519 新888-B-0143840-1653 | AA31: 5/30立花駅にて盗難 6/3市駅前交番届出 | AD31: 46015 | AE31: 46016 | AF31: 46055 | AG31: 46056 | AJ31: 2025/12/25-2026/2/2 関西国際空港⇔ハノイ 115,800円 | AL31: ― | AN31: 自転車保険 2026/09/15 | AO31: 伊予銀 三津浜支店 | AP31: 特定技能1号期間更新中 24.7.11 6/3 10:01受理 市駅前交番にて 5/30自転車盗難の申出。鍵が故障により施錠しておらずとの申し出。6/3組合に5,000円徴収依頼 6/4￥5000支払済 2025/10/8伊予銀 三津浜支店 ワタナベさんより連絡あり。在留ｶｰﾄﾞ更新後のコピーの提出がまだ。10/17 2025/12/25～2026/02/02一時帰国希望（宮内工場長より） 2025/12/24一時退職 12/25～2026/2/2一時帰国 2026/2/3再入社 社員ｺｰﾄﾞ変更済 | AQ31: /appsheet/photograph/07001605.在留カード表裏.003116.pdf
B32: 30 | C32: 本社 | D32: ベトナム | E32: 07001610 | F32: /appsheet/photograph/IDPhoto_20240711_ダット.jpg | G32: グエン ヒュー タイン ダット | H32: NGUYEN HUU THANH DAT | I32: ダット | J32: 男 | K32: 37255 | L32: =DATEDIF(K32,TODAY(),"Y") -> 24 | M32: 夫婦 | N32: 中四国 | O32: 44119 | P32: 2028/08 | Q32: 特定技能１号 | R32: 松山市末広町5-14三和ﾏﾝｼｮﾝ末広201 | S32: 夫婦 | T32: 21500 | U32: 46082 | V32: 46294 | W32: UH42724630PC | X32: 5109-022610-8 | Z32: 2020/10購入 17000003 B-0177520 | AB32: N3 2024/12/01 | AD32: 45306 | AE32: 45306 | AF32: 45352 | AG32: 45355 | AL32: 〇 | AM32: 45181 | AN32: 2025/8/1～2028/8/31 | AO32: 伊予銀 | AP32: 特定技能1号期間更新中 24.7.11 2024.6.21～ｱﾄﾑ504→三和ﾏﾝｼｮﾝ末広201へ引越 6/26住所変更済（中四国で） 家賃￥21500/人。家具家電は会社負担 奥さんｱｲﾝと一緒に住む 2025/7/24一時帰国から戻ってから在留ｶｰﾄﾞ更新予定⇒済9/29 2026.1月 特定2号受験予定 | AT32: /appsheet/photograph/07001610.通帳.042824.pdf | AW32: /appsheet/photograph/07001610.特定２号合格.010117.pdf
B33: 31 | C33: 本社 | D33: ベトナム | E33: 07001406 | G33: ダン ティ タイン トゥイ | H33: DANG THI THANH THUY | I33: ダン | J33: 女 | K33: 36097 | L33: =DATEDIF(K33,TODAY(),"Y") -> 27 | N33: 中四国 | O33: 43879 | P33: 2023/01 | Q33: 技能実習2号 | R33: 和泉北1-20-28アトムスカイマンション305 | V33: 44953 | W33: TJ41491013PC | X33: 5106-445113-6 | AH33: 退職 | AI33: 44941
B34: 32 | C34: 本社 | D34: ベトナム | E34: 07001407 | G34: ダオ ティ トゥー フエン | H34: DAO THI THU HUYEN | I34: ダオ | J34: 女 | K34: 34487 | L34: =DATEDIF(K34,TODAY(),"Y") -> 31 | N34: 中四国 | O34: 43879 | P34: 2023/01 | Q34: 技能実習2号 | R34: 和泉北1-20-28アトムスカイマンション304 | V34: 44953 | W34: TJ48438123PC | X34: 5106-445107-1 | AH34: 退職 | AI34: 44915 | AP34: 22.12/20 退職 12/23 帰国
B35: 33 | C35: 本社 | D35: ベトナム | E35: 07001402 | G35: ハー ティ ソン | H35: HA THI SON | I35: ソン | J35: 女 | K35: 33354 | L35: =DATEDIF(K35,TODAY(),"Y") -> 34 | N35: 中四国 | O35: 43879 | P35: 2023/01 | Q35: 技能実習2号 | R35: 和泉北1-20-28アトムスカイマンション304 | V35: 44953 | W35: TJ44753516PC | X35: 5106-445112-3 | AH35: 退職 | AI35: 44941
B36: 34 | C36: 本社 | D36: ベトナム | E36: 07001401 | G36: グエンティ ミン フォン | H36: NGUYEN THI MINH HUONG | I36: グエン | J36: 女 | K36: 35901 | L36: =DATEDIF(K36,TODAY(),"Y") -> 28 | N36: 中四国 | O36: 43879 | P36: 2023/01 | Q36: 技能実習2号 | R36: 和泉北1-20-28アトムスカイマンション305 | V36: 44953 | W36: TJ57789188PC | X36: 5106-445110-8 | AH36: 退職 | AI36: 44941
B37: 35 | C37: 津吉 | D37: ベトナム | E37: 07011605 | G37: ファム ティ リン | H37: PHAM THI LINH | I37: リン | J37: 女 | K37: 36662 | L37: =DATEDIF(K37,TODAY(),"Y") -> 25 | N37: 中四国 | O37: 43879 | P37: 2028/02 | Q37: 特定技能１号 | R37: 松山市津吉町535-1コーポ津吉1-6 | T37: 20000 | V37: 45716 | W37: SA26542494PA | X37: 5106-445114-9 | Z37: 自身で購入（ｱｼｽﾄ自転車）通勤使用 ﾀﾞｲｷで購入 書類紛失の為 防犯登録等不明 会社支給 管理番号なし B-0128657会社の自転車は時々使用 | AE37: 45324 | AF37: 45346 | AH37: 退職 | AI37: 45513 | AP37: 2024.8.14退職希望とのことで新開工場長より（7/1）2024.2/2～2/24一時帰国 特定技能23.2/28～ 23.3/21～津吉へ 最終8/9退職 8/15退寮
B38: 36 | C38: 本社 | D38: ベトナム | E38: 07001617 | F38: /appsheet/photograph/36.写真.225148.jpg | G38: グエン タイン ド― | H38: NGUYEN THANH DO | I38: ドー | J38: 男 | K38: 33529 | L38: =DATEDIF(K38,TODAY(),"Y") -> 34 | M38: 有 | N38: 中四国 | O38: 44221 | P38: 2028/12 | Q38: 特定技能１号 | R38: 和泉北1-20-28アトムスカイマンション504 | S38: 相2 | T38: 20000 | U38: 45912 | V38: 46377 | W38: UH64477231PC | X38: 5109-504178-2 | Z38: 2021/01購入 8561 B-0188561-1188 | AE38: 45677 | AF38: 45721 | AG38: 45723 | AJ38: 関空⇔ハノイ 98,300-会社負担 | AL38: ― | AN38: ― 自転車保険加入済 2026/2/1～2027/2/1 1年間 | AQ38: /appsheet/photograph/07001617.在留カード表裏.072440.pdf | AR38: 管理表_Files_/07001617.パスポート.003113.pdf
B39: 37 | C39: 本社 | D39: ベトナム | E39: 07001409 | G39: ハー ティ タイン ハン | H39: HA THI THANH HANG | I39: ハン | J39: 女 | K39: 36747 | L39: =DATEDIF(K39,TODAY(),"Y") -> 25 | N39: 中四国 | O39: 44221 | P39: 2028/12 | Q39: 技能実習2号 | R39: 和泉北1-20-28アトムスカイマンション304 | V39: 45281 | W39: TJ53670164PC | X39: 5109-504268-5 | AH39: 退職 | AI39: 45275
B40: 38 | C40: 津吉 | D40: ベトナム | E40: 07011611 | G40: レー ティ ニュン | H40: LE THI NHUNG | I40: ニュン | J40: 女 | K40: 36713 | L40: =DATEDIF(K40,TODAY(),"Y") -> 25 | N40: 中四国 | O40: 44221 | P40: 2028/12 | Q40: 特定技能１号 | R40: 津吉町535-1コーポ津吉2-4 | T40: 20000 | V40: 45647 | W40: NP14928533PA | X40: 5109-504384-3 | Z40: ｱｲｽﾄ自転車 B-0266737 青 ﾀｹﾀﾞ403 SUISUI 車体番号CFS22060439 | AA40: 会社支給の自転車 は使用していない | AD40: 45324 | AE40: 45324 | AF40: 45371 | AG40: 45372 | AH40: 退職 | AI40: 45513 | AP40: 2024.8.14退職希望とのこと新開工場長より（7/1） 一時退職の為社員コード変わる2023.3/21～済 24.3.21～1人へ（家賃2万へ） 3/21再入社 3/21は欠勤 最終8/9退職 8/15退寮
B41: 39 | C41: 津吉 | D41: ベトナム | E41: 07011408 | G41: レー カイン ヴァン | H41: LE KHANH VAN | I41: ヴァン | J41: 女 | K41: 36056 | L41: =DATEDIF(K41,TODAY(),"Y") -> 27 | N41: 中四国 | O41: 44221 | P41: 2023/02 | Q41: 技能実習2号 | R41: 津吉町535-1コーポ津吉2-4 | V41: 45281 | W41: TJ64941730PC | X41: 5109-504323-8 | AH41: 退職 | AI41: 45275
B42: 40 | C42: 本社 | D42: ベトナム | E42: 07001501 | G42: ヴー ティ・ホア | H42: VU THI HOA | I42: ホア | J42: 女 | K42: 33200 | L42: =DATEDIF(K42,TODAY(),"Y") -> 35 | N42: 中四国 | O42: 43162 | P42: 2023/02 | Q42: 技能実習3号 | R42: 和泉北1-20-28アトムスカイマンション401 | V42: 45017 | W42: TJ17412123PC | X42: 5100-954995-4 | AH42: 退職 | AI42: 45003
B43: 41 | C43: 本社 | D43: ベトナム | E43: 07001507 | G43: クック ティ・トアン | H43: KHUC THI THOAN | I43: トアン | J43: 女 | K43: 36016 | L43: =DATEDIF(K43,TODAY(),"Y") -> 27 | N43: 中四国 | O43: 43162 | P43: 2023/02 | Q43: 技能実習3号 | R43: 和泉北1-20-28アトムスカイマンション401 | V43: 45017 | W43: TJ92668730PC | X43: 5100-954998-2 | AH43: 退職 | AI43: 45003
B44: 42 | C44: 津吉 | D44: ベトナム | E44: 07012701 | G44: ドゥ ティ フォン ザン | H44: DO THI HUONG GIANG | J44: 女 | K44: 35597 | L44: =DATEDIF(K44,TODAY(),"Y") -> 28 | N44: キュービック | O44: 44523 | P44: ? | Q44: 特定活動 | R44: 松山市上野町774番地ビレッジハウス松山上野2-506 | V44: 44884 | W44: TJ15016868PC | X44: 5097-420160-4 | AH44: 退職 | AI44: 44863 | AP44: 2024.4.20令和4年の源泉徴収票依頼あり。
B45: 43 | C45: 津吉 | D45: ベトナム | G45: グエン ホン ニュン | H45: NGUYEN HONG NHUNG | J45: 女 | K45: 32935 | L45: =DATEDIF(K45,TODAY(),"Y") -> 36 | N45: キュービック | O45: 44523 | P45: 2026/10 | Q45: 特定技能１号 | R45: 松山市上野町774番地ビレッジハウス松山上野2-506 | V45: 44884 | W45: DX39572747PA | X45: 5100-218012-7 | AH45: 退職 | AI45: 44701
B46: 44 | C46: 津吉 | D46: ベトナム | G46: ファム ティ ハイ イエン | H46: PHAM THI HAI YEN | J46: 女 | K46: 35731 | L46: =DATEDIF(K46,TODAY(),"Y") -> 28 | N46: キュービック | O46: 44546 | P46: 2026/11 | Q46: 特定技能１号 | R46: 松山市上野町774番地ビレッジハウス松山上野2-503 | V46: 44910 | W46: DX97008497PA | X46: 5103-439764-5 | AH46: 退職 | AI46: 44701
B47: 45 | C47: 津吉 | D47: ベトナム | G47: ディン ティ トウイ | H47: DINH THI THUY | J47: 女 | K47: 36437 | L47: =DATEDIF(K47,TODAY(),"Y") -> 26 | N47: キュービック | O47: 44599 | P47: 2027/01 | Q47: 特定技能１号 | R47: 松山市上野町774番地ビレッジハウス松山上野2-503 | V47: 44595 | W47: TJ016/82361PC | X47: 5103-763436-4 | AH47: 退職 | AI47: 44701
B48: 46 | C48: 津吉 | D48: ベトナム | G48: グエン チョン マイン | H48: NGUYEN TRONG MANH | J48: 男 | K48: 35463 | L48: =DATEDIF(K48,TODAY(),"Y") -> 29 | N48: キュービック | O48: 44531 | P48: ? | Q48: 特定活動 | R48: 松山市上野町774番地ビレッジハウス松山上野2-503 | V48: 44707 | W48: DX20614267PA | X48: 5103-340669-1 | AH48: 退職 | AI48: 44701
B49: 47 | C49: 津吉 | D49: ベトナム | E49: 07012607 | G49: グエン クアン アィン | H49: NGUYEN QUANG ANH | J49: 男 | K49: 36369 | L49: =DATEDIF(K49,TODAY(),"Y") -> 26 | N49: デルタ四国 | O49: 44539 | P49: 2026/11 | Q49: 特定技能１号 | R49: 松山市上野町774番地ビレッジハウス松山上野2-504 | V49: 45679 | W49: SA96273864PC | X49: 5103-404967-7 | AH49: 退職 | AI49: 45330 | AP49: 24.2.8退寮
B50: 48 | C50: 津吉 | D50: ベトナム | E50: 07012603 | G50: グエン スアン ヒエップ | H50: NGUYEN XUAN HIEP | J50: 男 | K50: 34108 | L50: =DATEDIF(K50,TODAY(),"Y") -> 32 | N50: キュービック | O50: 44566 | P50: 2026/12 | Q50: 特定技能１号 | R50: 松山市上野町774番地ビレッジハウス松山上野2-504 | V50: 44930 | W50: TJ50818345PA | X50: 5103-540391-6 | AH50: 退職 | AI50: 44803
B51: 49 | C51: 津吉 | D51: ベトナム | G51: グエン アン トゥー | H51: NGUYEN ANH TU | J51: 男 | K51: 31776 | L51: =DATEDIF(K51,TODAY(),"Y") -> 39 | N51: キュービック | O51: 44643 | P51: 2026/12 | Q51: 特定活動 | R51: 松山市上野町774番地ビレッジハウス松山上野2-504 | V51: 44826 | W51: TJ55410419PC | X51: まだ | AH51: 退職 | AI51: 44680
B52: 50 | C52: 津吉 | D52: ベトナム | E52: 07012625 07017701 | F52: /appsheet/photograph/50.写真.031439.jpg | G52: チャン ティー トゥータオ | H52: TRAN THI THU THAO | I52: タオ | J52: 女 | K52: 35807 | L52: =DATEDIF(K52,TODAY(),"Y") -> 28 | M52: 夫婦 | N52: デルタ四国 | O52: 44566 | P52: 2026/12 | Q52: 特定技能２号 | R52: 松山市上野町774番地ビレッジハウス松山上野2-507 | S52: 個 | T52: 20000 | U52: 45962 | V52: 47102 | W52: UH79100289PC | X52: 5099-602786-1 | AD52: 45756 | AE52: 45756 | AF52: 45794 | AG52: 45796 | AL52: ― | AO52: ひめぎん 末広町支店 | AP52: 自身の結婚の為一時帰国 勤務再開2025/5/19 一時退職のため、社員ｺｰﾄﾞ変更予定 2025.7.24給与口座を伊予銀行→ひめぎんへ変更したいとのこと。中温経由であれば一時的なことではなく、給与振込口座として作成するのであれば可能とのひめぎんより回答あり。 9月分の給料よりひめぎんへ変更。 在留ｶｰﾄﾞ更新申請中。更新後の在留ｶｰﾄﾞをひめぎんへ提出（ﾃﾞﾙﾀ・松岡さんへ伝え済8月末～9月頃予定） 伊予銀口座解約⇒仕事が忙しく休みが取れない為、年末までには銀行へ行く予定 2025/10 特定2号試験合格。早急に2号に移行したいとの回答。2号移行後は弊社の自社支援となる（ﾃﾞﾙﾀ松岡さんより10/27） 2025/12/21～特定2号へ移行予定 2025/11/12昨日、病院へ行って妊娠４週ぐらい。まだ小さいため、安定したら再度話す。新開工場長へは連絡済み 2025/12/15 特定2号へ移行完了 ブイよりタオが妊娠。出産予定9月。西条工場へ夫婦で行く予定のため、病院で迷っている。現在つばきウィメンズクリニック。後日相談 | AQ52: /appsheet/photograph/07012625.在留カード表裏.082059.pdf | AR52: 管理表_Files_/07012625.パスポート.070534.pdf | BA52: /appsheet/photograph/07012625-07017701.その他１（ファイル）.055702.pdf
B53: 51 | C53: 津吉 | D53: ベトナム | E53: 07012624 07017700 | F53: /appsheet/photograph/51.写真.031458.jpg | G53: ブイ ヒウ フン | H53: BUI HUU HUNG | I53: ブイ | J53: 男 | K53: 35127 | L53: =DATEDIF(K53,TODAY(),"Y") -> 30 | M53: 夫婦 | N53: デルタ四国 | O53: 44566 | P53: 2026/12 | Q53: 特定技能２号 | R53: 松山市上野町774番地ビレッジハウス松山上野2-507 | S53: 個 | T53: 20000 | U53: 45962 | V53: 47102 | W53: UH13080122PC | X53: 5097-305748-7 | Z53: ﾊﾞｲｸ通勤 2024.3.21～ | AD53: 45756 | AE53: 45756 | AF53: 45794 | AG53: 45796 | AL53: ― | AO53: ひめぎん 末広町支店 | AP53: 24.3.8頃～原付通勤 通勤届書類提出済3/17 4月分の給料から通勤手当変更 自身の結婚の為一時帰国 勤務再開2025/5/19 一時退職のため、社員ｺｰﾄﾞ変更予定 2025.7.24給与口座を伊予銀行→ひめぎんへ変更したいとのこと。中温経由であれば一時的なことではなく、給与振込口座として作成するのであれば可能とのひめぎんより回答あり。 9月分の給料よりひめぎんへ変更。 在留ｶｰﾄﾞ更新申請中。更新後の在留ｶｰﾄﾞをひめぎんへ提出（ﾃﾞﾙﾀ・松岡さんへ伝え済8月末～9月頃予定） 伊予銀口座解約⇒仕事が忙しく休みが取れない為、年末までには銀行へ行く予定 2025/10 特定2号試験合格。早急に2号に移行したいとの回答。2号移行後は弊社の自社支援となる（ﾃﾞﾙﾀ松岡さんより10/27） 2025/12/21～特定2号へ移行予定 2025/12/15 特定2号へ移行完了 | AQ53: /appsheet/photograph/07012624.在留カード表裏.082233.pdf | AR53: 管理表_Files_/07012624.パスポート.070709.pdf
B54: 52 | C54: 津吉 | D54: ベトナム | E54: 07012604 | G54: ブイ ティ レー | H54: BUI THI LE | I54: レー | J54: 女 | K54: 34797 | L54: =DATEDIF(K54,TODAY(),"Y") -> 31 | N54: デルタ四国 | O54: 44692 | P54: 2027/04 | Q54: 特定技能１号 | R54: 松山市上野町774番地ビレッジハウス松山上野2-506 | S54: 個 | T54: 15000 | V54: 45856 | W54: SA19114543EA | Z54: 7912 (1596)赤 | AA54: 2024.2.13鍵（7912赤） 返却済 自転車は小栗へ回収 2024-827小栗のロアンへ | AH54: 退職 | AI54: 45524 | AP54: 24.6/13～7/12傷病手当申請予定・早めに提出いただくよう伝え済。 8/20退職の為入金があるまで口座を残してもらう等ﾃﾞﾙﾀへ依頼済（7/5） 在留ｶｰﾄﾞ更新中。（伊予銀へ 更新後のコピー提出要。1ヵ月延長済。6/26過ぎること了承済。更新 後の在留ｶｰﾄﾞを届きし速やかに本人が窓口へ提出） 24.8/9最終出勤日、8/21退寮 本人より妊娠の疑いあり。4/20に病院で 検査し妊娠。お相手：マイヴァンサン（MAI VAN SANG）/1995.9.9生/ 実習生2号/勤務先：浦田建設㈲→緊急連絡先 勤務先089-924-8685 代表者：浦田一幸 入籍はしてない 24.8月中旬まで勤務し退職。帰国し出産、子供が1才まで育児予定。その後 再入社希望。（ﾃﾞﾙﾀ松岡さんより2024.4.20）新開工場長、専務了承済4/22"
B55: 53 | C55: 津吉 | D55: ベトナム | E55: 07012605 | G55: グエン バン ホー | H55: NGUYEN VAN HO | I55: ホー | J55: 男 | K55: 36038 | L55: =DATEDIF(K55,TODAY(),"Y") -> 27 | N55: デルタ四国 | O55: 44782 | P55: 2027/07 | Q55: 特定技能１号 | R55: 松山市上野町774番地ビレッジハウス松山上野2-504 | S55: 個 | T55: 15000 | V55: 45522 | W55: NP75209824PC | X55: 5103-422049-3 | Z55: 電動アシスト 会社支給の自転車返却済 | AA55: 2023.1月 自転車・鍵回収済 | AH55: 退職 | AI55: 45409 | AP55: 2024.4/30退寮。本人より会社支給の自転車は本人が電動ｱｼｽﾄ購入時に返却済。 鍵は2023.1.23に返却済とのこと。（ﾃﾞﾙﾀより4/20）24.5/1一時退職5/3～6/18一時 帰国予定⇒家族より一時帰国ではなく、退職してほしいとの希望。4/15ﾃﾞﾙﾀ松岡さん より 妻レー カイン ヴァン 22.12/25～1/10 帰国
B56: 54 | C56: 津吉 | D56: ベトナム | E56: 07012703 | G56: キエン ミン トゥアン | H56: KIEU MINH TUAN | J56: 男 | K56: 32835 | L56: =DATEDIF(K56,TODAY(),"Y") -> 36 | N56: キュービック | O56: 44855 | P56: 2027/09 | Q56: 特定活動 | R56: 松山市上野町774番地ビレッジハウス松山上野2-504 | V56: 45217 | W56: TJ84866671PC | Z56: 3815 (1593) | AH56: 退職 | AI56: 45066
B57: 55 | C57: 津吉 | D57: ベトナム | E57: 07012606 | G57: チャン クアン トゥアン | H57: TRAN QUANG TUAN | J57: 男 | K57: 36224 | L57: =DATEDIF(K57,TODAY(),"Y") -> 27 | M57: 夫婦 | N57: デルタ四国 | O57: 44890 | P57: 2027/10 | Q57: 特定技能１号 | R57: 松山市上野町774番地ビレッジハウス松山上野2-504 | S57: 個 | T57: 15000 | U57: 45616 | V57: 45654 | W57: NP42358626EA | X57: 寮23.10/11～ | Z57: 3816新鍵 B-0233816 | AA57: 自転車返却希望 鍵と防犯登録を 津吉の事務所へ（6/13） | AE57: 2024/01/23 2024/12/20 | AF57: 2024/02/26 2025/02/20 | AH57: 退職 | AI57: 45646 | AP57: 支給の自転車返却予定。鍵が壊れているため、修理して新しい 鍵と防犯登録番号を分かるようにして6/26鍵を返却予定（6/13ﾃﾞﾙﾀへ） 2024/9/22に引越済2-508→2-504妻ハーティヴァン 24.1/23～2/26一時帰国 24/12/19最終出勤12/20退職退寮、 再入寮25/2/20再入社2/21歳入社
B58: 56 | C58: 津吉 | D58: ベトナム | E58: 07012608 | G58: フィン ゴック ガン | H58: HUYNH NGOC NGAN | J58: 女 | K58: 30635 | L58: =DATEDIF(K58,TODAY(),"Y") -> 42 | N58: ｅ-人財 | O58: 44939 | P58: 2027/12 | Q58: 特定技能１号 | R58: 松山市上野町774番地ビレッジハウス松山上野2-506 | V58: 45302 | W58: NP83766353MA | Z58: 2201 | AH58: 退職 | AI58: 45241
B59: 57 | C59: 津吉 | D59: ベトナム | E59: 07012609 | G59: ホー ティ ガー | H59: HO THI NGA | J59: 女 | K59: 35423 | L59: =DATEDIF(K59,TODAY(),"Y") -> 29 | N59: デルタ四国 | O59: 44939 | P59: 2027/12 | Q59: 特定技能１号 | R59: 松山市上野町774番地ビレッジハウス松山上野4-501 | V59: 45694 | W59: SA11529932EA | Z59: 2203→ホアンティハンへ | AB59: N3 | AH59: 退職 | AI59: 45369 | AP59: 24.3/18退職、退寮 自転車の鍵（2203）、寮の鍵返却済3/21
B60: 58 | C60: 津吉 | D60: ベトナム | E60: 07012610 | G60: グエン ティ クイン ガー | H60: NGUYEN THI QUYNH NGA | J60: 女 | K60: 35124 | L60: =DATEDIF(K60,TODAY(),"Y") -> 30 | N60: デルタ四国 | O60: 44939 | P60: 2027/12 | Q60: 特定技能１号 | R60: 松山市上野町774番地ビレッジハウス松山上野4-501 | V60: 45302 | W60: NP63447264MA | Z60: 2203 | AH60: 退職 | AI60: 45296
B61: 59 | C61: 津吉 | D61: ベトナム | E61: 07012611 | G61: チン ディン フン | H61: TRINH DINH HUNG | J61: 男 | K61: 36162 | L61: =DATEDIF(K61,TODAY(),"Y") -> 27 | N61: デルタ四国 | O61: 44949 | P61: 2027/12 | Q61: 特定技能１号 | R61: 松山市上野町774番地ビレッジハウス松山上野2-503 | V61: 45311 | W61: NP30657628PC | X61: 3815(1593)が返却 | Z61: 3780 (1098)青 | AH61: 退職 | AI61: 45307
B62: 60 | C62: 津吉 | D62: ベトナム | E62: 07012612 | G62: グエン ゴック ガー | H62: NGUYEN NGOC NGA | J62: 女 | K62: 35570 | L62: =DATEDIF(K62,TODAY(),"Y") -> 28 | N62: デルタ四国 | O62: 44998 | P62: 2028/02 | Q62: 特定技能１号 | R62: 松山市上野町774番地ビレッジハウス松山上野2-506 | S62: 個 | T62: 15000 | U62: 44860 | V62: 45818 | W62: SA76079571EA | Z62: バイク通勤（原付） 2024.4.15～ | AA62: 自転車返却希望 240322鍵回収現物2号棟前 3779(1062)赤-B-9233779-㉔ | AB62: N3 2024/07/07 | AH62: 退職 | AI62: 45616 | AJ62: 完全帰国 | AP62: 支給の自転車返却予定。6/26鍵をﾃﾞﾙﾀより返却予定 一時帰国 2024.6.26～8.5（結婚式） 2024.4.15～ﾊﾞｲｸ通勤 通勤届提出済4/15 4/21～通勤手当変更。自転車紛失2024.3/21⇒自転車、鍵あり。
B63: 61 | C63: 津吉 | D63: ベトナム | E63: 07012613 | G63: チャン ヴァン ヒエン | H63: TRAN VAN HIEN | I63: ヒエン | J63: 男 | K63: 35692 | L63: =DATEDIF(K63,TODAY(),"Y") -> 28 | N63: デルタ四国 | O63: 45057 | P63: 2028/04 | Q63: 特定技能１号 | R63: 松山市上野町774番地ビレッジハウス松山上野2-503 | S63: 個 | T63: 15000 | V63: 45576 | W63: SA08839739EA | Z63: バイク通勤の為返却2024/3/26 （7931 2024.3.26迄） | AA63: 2024.3.26鍵久保さんへ 返却済 自転車はﾋﾞﾚｯｼﾞﾊｳｽ有 | AH63: 退職 | AI63: 45544 | AP63: 2024.3.21～ﾊﾞｲｸ通勤 通勤届書類済3/25 4月分の給与～通勤手当変更 24.3.29 バイク対車の事故 8/5 ９月上旬に退職したい申し出 9/9退職 9/12退寮
B64: 62 | C64: 津吉 | D64: ベトナム | E64: 07012614 | G64: ハー ティ ヴァン | H64: HA THI VAN | J64: 女 | K64: 35545 | L64: =DATEDIF(K64,TODAY(),"Y") -> 28 | M64: 夫婦 | N64: デルタ四国 | O64: 45212 | P64: 2028/09 | Q64: 特定技能１号 | R64: 松山市上野町774番地ビレッジハウス松山上野2-508 | S64: 個 | T64: 15000 | U64: 45166 | V64: 45602 | W64: NP85143709PC | Z64: 6666 B-0246666 | AA64: 45584 | AE64: 45314 | AF64: 45348 | AH64: 退職 | AI64: 45569 | AJ64: 妊娠完全帰国 | AP64: 2024.10.4退職。10/4最終出勤日、10/10退寮 10/10給与は現金準備出来しﾃﾞﾙﾀへ支払予定 5/17病院で検査し妊娠7週目。 出産予定日2025年1月 24.1/23～2/26一時帰国 夫ﾁｬﾝｸｱﾝﾄｩｱﾝ
B65: 63 | C65: 津吉 | D65: ベトナム | E65: 07012615 | G65: グエン ホアン マン | H65: NGUYEN HOANG MAN | J65: 男 | K65: 34305 | L65: =DATEDIF(K65,TODAY(),"Y") -> 32 | N65: デルタ四国 | O65: 45238 | P65: 2028/10 | Q65: 特定技能１号 | R65: 松山市上野町774番地ビレッジハウス松山上野2-504 | S65: 個 | T65: 15000 | U65: 45087 | V65: 46002 | W65: SA60944681EA | Z65: 2207 Ｂ－0274811-V067 | AA65: 45770 | AB65: N3 2024.11月入社時あり | AH65: 退職 | AI65: 45765 | AJ65: 転職 | AP65: 4/18退職 4/21退寮
B66: 64 | C66: 津吉 | D66: ベトナム | E66: 07012616 | G66: グエン ヴァン ズオン | H66: NGUYEN VAN DUONG | J66: 男 | K66: 33470 | L66: =DATEDIF(K66,TODAY(),"Y") -> 34 | N66: デルタ四国 | O66: 45343 | P66: 2029/01 | Q66: 特定技能１号 | R66: 松山市上野町774番地ビレッジハウス松山上野2-503 | S66: 個 | T66: 15000 | V66: 45708 | W66: SA59269635PC | Z66: 2201ーB-0274805 | AA66: 2024/08/22 コーポ津吉よりヴィレッジに 移動後回収し小栗へ 中野住宅へ | AE66: 45469 | AF66: 45509 | AH66: 退職 | AI66: 45469 | AP66: 7/30 デルタ四国より帰国を8/15にとの話があり最終6/26付け退職6 /26～8/5一時帰国の予定が6/19～欠勤のため、確認した ところ同部屋の実習生から6/24～帰国しているとのこと（新開工場長より6/24）（6/19～欠勤）ﾃﾞﾙﾀ確認（6/24）帰国は予定どおり8/5 24.2.19～入寮 2024.11.23～2025.1.6 一時帰国（土地の契約更新の為） 一時帰国 2024.6.24～8.5
A67: 出荷 | B67: 65 | C67: 津吉 | D67: インドネシア | E67: 07013629 | F67: /appsheet/photograph/65.写真.033201.jpg | G67: ククー ヌル ハンドヨ | H67: KUKUH NUR HANDOYO | I67: クク | J67: 男 | K67: 35333 | L67: =DATEDIF(K67,TODAY(),"Y") -> 29 | M67: 有 | N67: H&C | O67: 45027 | P67: 2028/03 | Q67: 特定技能１号 | R67: 松山市上野町774番地ビレッジハウス松山上野3-508 | S67: 個 | T67: 15000 | U67: 46082 | V67: 46172 | W67: UH69112519PC | Z67: 2301-V065 | AE67: 45506 | AF67: 45525 | AK67: 垂水主任 | AL67: 〇 | AM67: 45024 | AN67: 2025/6/１～2028/4/30 | AP67: 24.7/10保険証紛失（H&Cへ伝え済） 8/5～8/9有給使用予定（7/5H＆C古谷さんより） 2024.8月に3週間程一時帰国希望。（6/14H&C三好さんより）新開工場長了承済。 有休残日数と次回の付与日で時季を再検討とのこと （24.4.23H&C三好さんより） 2025.10.24奥さんが中温で働きたいとのこと。特定1号取得、食料品の資格も取得済。（尾崎さんから新開工場長へ伝えるとのこと）
B68: 66 | C68: 津吉 | D68: インドネシア | E68: 07013602 | G68: フィフィ オリフィヤティ | H68: VIVI OLVIYATI | I68: 帰国（結婚） | J68: 女 | K68: 35554 | L68: =DATEDIF(K68,TODAY(),"Y") -> 28 | N68: H&C | O68: 44669 | P68: 2027/03 | Q68: 特定技能１号 | R68: 東温市牛渕170-3 | V68: 45026 | W68: TJ79903994FA | AH68: 退職 | AI68: 45023
B69: 67 | C69: 津吉 | D69: インドネシア | E69: 07013603 | G69: リダ ドゥイ アマリア | H69: RIDA DWI AMALIA | J69: 女 | K69: 35381 | L69: =DATEDIF(K69,TODAY(),"Y") -> 29 | N69: H&C | O69: 44669 | P69: 2027/03 | Q69: 特定技能１号 | R69: 松山市上野町774番地ビレッジハウス松山上野4-502 | V69: 45408 | W69: NP41864952PC | AH69: 退職 | AI69: 45342 | AP69: 2/22退寮 ・雇用契約書2/20受領 保険証回収2/21
B70: 68 | C70: 津吉 | D70: インドネシア | E70: 07013604 | G70: サフリダ ユリアンティ | H70: SAFRIDA YULIANTI | I70: 大学院 | J70: 女 | K70: 34177 | L70: =DATEDIF(K70,TODAY(),"Y") -> 32 | N70: H&C | O70: 44669 | P70: 2027/03 | Q70: 特定技能１号 | R70: 東温市牛渕170-3 | V70: 45026 | W70: TJ59788198FA | AH70: 退職 | AI70: 45005
A71: 四課 | B71: 69 | C71: 津吉 | D71: インドネシア | E71: 07013630 | F71: /appsheet/photograph/69.写真.025352.jpg | G71: ムハマッド ヒダヤット ヌロフマン | H71: MUHAMMAD HIDAYAT NUROHMAN | J71: 男 | K71: 36053 | L71: =DATEDIF(K71,TODAY(),"Y") -> 27 | M71: 無 | N71: H&C | O71: 45027 | P71: 2028/03 | Q71: 特定技能１号 | R71: 松山市上野町774番地ビレッジハウス松山上野3-508 | S71: 個 | T71: 15000 | U71: 46082 | V71: 46172 | W71: UH67756555PC | Z71: 自身で購入 元2302 シルバー B-0287298-V208 | AK71: 大西係長 | AL71: ― | AM71: 45024 | AN71: ― | AP71: 2024.5.8引越ﾋﾞﾚｯｼﾞﾊｳｽ3-508→ﾋﾞﾚｯｼﾞﾊｳｽ4-507へ 2026.1.14寮の契約終了の為、引越予定 2026/1/21ﾋﾞﾚｯｼﾞ4-507→3-508へ引越（契約終了の為） | AQ71: /appsheet/photograph/07013630.在留カード表裏.042704.pdf
A72: 四課 | B72: 70 | C72: 津吉 | D72: インドネシア | E72: 07013631 | F72: /appsheet/photograph/70.写真.025447.jpg | G72: レザ アルヤ ヌグラハ | H72: REZA ARYA NUGRAHA | I72: レザ | J72: 男 | K72: 37958 | L72: =DATEDIF(K72,TODAY(),"Y") -> 22 | M72: 無 | N72: H&C | O72: 45027 | P72: 2028/03 | Q72: 特定技能１号 | R72: 松山市上野町774番地ビレッジハウス松山上野3-507 | S72: 個 | T72: 15000 | U72: 46082 | V72: 46172 | W72: UH91062732PC | X72: 寮23.5/21～ | Z72: 2303 鍵付き B-0287297-V138 | AA72: 46085 | AK72: 大西係長 | AL72: 〇 | AM72: 45024 | AN72: 2025/6/１～2028/4/30 | AP72: 2025/5/9 11:30自宅にて休みがちのため指導訪問 2025/6/24 2週間前から喉の痛みあり、1、2日目は38度の熱あり。よしおか内科へ⇒特定技能保険請求予定 | AU72: /appsheet/photograph/07013631.保険証.064740.pdf
A73: 一課 | B73: 71 | C73: 津吉 | D73: インドネシア | E73: 07013632 | F73: /appsheet/photograph/71.写真.020439.jpg | G73: ファルハン ファティ ラマダンシャー | H73: FARHAN FATHI RAMADHANSYAH | J73: 男 | K73: 37928 | L73: =DATEDIF(K73,TODAY(),"Y") -> 22 | M73: 無 | N73: H&C | O73: 45027 | P73: 2028/03 | Q73: 特定技能１号 | R73: 松山市上野町774番地ビレッジハウス松山上野4-501 | S73: 個 | T73: 15000 | U73: 46082 | V73: 46172 | W73: UH58397878PC | Z73: 2304 B-0287295-V088 | AA73: 45715 | AE73: 46091 | AF73: 46164 | AK73: 小林主任 | AL73: ― | AM73: 45024 | AN73: ― | AP73: 自転車改造中で放置のため、管理人さんよりｸﾚｰﾑ H&Cより本人へ伝えてもらう現状復帰もしくは￥5000 3/27 2025/04/14処分 2025/2/21V2-405→V4-501へ引越 2025/5/9 11:00自宅にてGWに入り休んでいるので指導 2025/7/25中野クリニック受診予定 腰痛、眠れないので欠勤が続いているため
A74: 箱入れ | B74: 72 | C74: 津吉 | D74: インドネシア | E74: 07013633 | F74: /appsheet/photograph/72.写真.031751.jpg | G74: ナナ マルディアナ | H74: NANA MARDIANA | J74: 男 | K74: 37994 | L74: =DATEDIF(K74,TODAY(),"Y") -> 22 | M74: 無 | N74: H&C | O74: 45027 | P74: 2028/03 | Q74: 特定技能１号 | R74: 松山市上野町774番地ビレッジハウス松山上野3-507 | S74: 個 | T74: 15000 | U74: 46082 | V74: 46172 | W74: UH92389157PC | Z74: 自身で購入 元2305-V084 | AE74: 46221 | AF74: 46269 | AH74: 一時帰国予定 | AK74: 水沼主任 | AL74: 〇 | AM74: 45024 | AN74: 2025/6/１～2028/4/30 | AP74: 2024/11/09 ビレッジハウス上野2-405⇒3-507へ移動 2025/11/25ナナより、デウィマシトと来年結婚する。 2026/7/18～9/4まで帰国結婚、中温で２人で住居したい申出。 日程については、新開工場長と相談済。
A75: 四課 | B75: 73 | C75: 津吉 | D75: インドネシア | E75: 07013634 | F75: /appsheet/photograph/73.写真.031810.jpg | G75: シャールル ムアリフ | H75: SYAHRUL MUARIF | I75: アルル | J75: 男 | K75: 38053 | L75: =DATEDIF(K75,TODAY(),"Y") -> 22 | N75: H&C | O75: 45027 | P75: 2028/03 | Q75: 特定技能１号 | R75: 松山市上野町774番地ビレッジハウス松山上野3-103 | S75: 個 | T75: 15000 | U75: 46082 | V75: 46172 | W75: UH07197758PC | Z75: 2306 鍵付き B-0287299-V054 | AK75: 大西係長 | AL75: 〇 | AM75: 45024 | AN75: 2025/6/１～2028/4/30 | AP75: 自転車故障で欠勤24.7？ 2025/2/21V2-405→V3-103へ引越
B76: 74 | C76: 津吉 | D76: インドネシア | E76: 07013610 | G76: ラニ ヒダヤー | H76: RANI HIDAYAH | J76: 女 | K76: 35359 | L76: =DATEDIF(K76,TODAY(),"Y") -> 29 | N76: H&C | O76: 44669 | P76: 2027/03 | Q76: 特定技能１号 | R76: 東温市牛渕170-3（母屋1F） | V76: 45408 | W76: NP14098347PC | AH76: 退職 | AI76: 45189
A77: 四課 | B77: 75 | C77: 津吉 | D77: インドネシア | E77: 07013635 | F77: /appsheet/photograph/75.写真.031619.jpg | G77: レイハン アリ サハシカ ザカリ | H77: REYHAN ALI SAHASIKA ZACKARY | I77: レイハン | J77: 男 | K77: 37989 | L77: =DATEDIF(K77,TODAY(),"Y") -> 22 | N77: H&C | O77: 45027 | P77: 2028/03 | Q77: 特定技能１号 | R77: 松山市上野町774番地ビレッジハウス松山上野3-103 | S77: 個 | T77: 15000 | U77: 46082 | V77: 46172 | W77: UH59875474PC | Z77: 2307 鍵付き B-0287293-V053 | AK77: 大西係長 | AL77: 〇 | AM77: 45024 | AN77: 2025/6/１～2028/4/30 | AO77: ひめぎん 末広町支店 | AP77: 2024.7.24労災 手を切って5針縫った。しばらく休み
A78: 一課 | B78: 76 | C78: 津吉 | D78: インドネシア | E78: 07013692 | F78: /appsheet/photograph/76.写真.030513.jpg | G78: ヨヴィト チャトゥル ヌグラハ | H78: YOVITO CATUR NUGRAHA | J78: 男 | K78: 37719 | L78: =DATEDIF(K78,TODAY(),"Y") -> 23 | N78: H&C | O78: 45027 | P78: 2028/03 | Q78: 特定技能１号 | R78: 松山市上野町774番地ビレッジハウス松山上野3-103 | S78: 個 | T78: 15000 | U78: 44940 | V78: 45756 | W78: SA24363882PC | Z78: 自身で購入 元2308 B-0287294-V175 | AD78: 45653 | AG78: 45726 | AH78: 退職 | AI78: 45775 | AJ78: 本人負担 | AK78: 小林主任 | AP78: 2024/12に入り体調不良にて休み。12/21心療診療内科内科受診し一時帰国を進められる。一時退職し帰国を打診。12/20締有給すべて消化処理。体調復帰すれば再度入社する 1/19退寮 2025/3/7面接し、3/10再入社する 2025/4/30退職 5/28退寮。退職届預かり。現在、H&Cにて在留ｶｰﾄﾞの更新のためﾊﾟｽﾎﾟｰﾄと預けている。更新間に合えば更新後に帰国希望。 帰国のﾁｹｯﾄは本人手配。4万円預かりの内 手数料￥6,000+家賃計算し返金予定
A79: 一課 | B79: 77 | C79: 津吉 | D79: インドネシア | E79: 07013637 | F79: /appsheet/photograph/77.写真.033328.jpg | G79: カデック アデリア ウィディアニタ レスタリ | H79: KADEK ADELIA WIDYANITA LESTARI | J79: 女 | K79: 35772 | L79: =DATEDIF(K79,TODAY(),"Y") -> 28 | N79: H&C | O79: 45027 | P79: 2028/03 | Q79: 特定技能１号 | R79: 松山市上野町774番地ビレッジハウス松山上野4-505 | S79: 個 | T79: 15000 | U79: 46082 | V79: 46172 | W79: UH41395173PC | Z79: 自身で購入 | AE79: 45542 | AF79: 45563 | AK79: 小林主任 | AL79: ― | AM79: 45024 | AN79: ― | AP79: 2024.8月末からもしくは9月初めから2～3週間程 お姉さんの結婚式で一時帰国希望（6/17H&C三好さんより） 新開工場長了承済6/28
A80: 四課 | B80: 78 | C80: 津吉 | D80: インドネシア | E80: 07013601 | F80: /appsheet/photograph/IDPhoto_20250328_78_トリ ユニ.jpg | G80: トリ ユニ | H80: TRI YUNI | I80: ユニ | J80: 女 | K80: 36257 | L80: =DATEDIF(K80,TODAY(),"Y") -> 27 | N80: H&C | O80: 44669 | P80: 2027/03 | Q80: 特定技能１号 | R80: 松山市上野町774番地ビレッジハウス松山上野4-505 | S80: 個 | T80: 15000 | U80: 46106 | V80: 46184 | W80: UH33566452PC | Z80: 自身で購入 | AE80: 45853 | AF80: 45890 | AK80: 大西係長 | AL80: 〇 | AM80: 44661 | AN80: 2025/6/１～2027/4/30 | AP80: 2025.3/5親の調子が悪いため一時帰国予定 2025.7.15～8/21 8/24より勤務
A81: 四課 | B81: 79 | C81: 津吉 | D81: インドネシア | E81: 07013605 07018700 | F81: /appsheet/photograph/IDPhoto_20250328_79_エヴィ ラハユ.jpg | G81: エヴィ ラハユ | H81: EVI RAHAYU | I81: エヴィ | J81: 女 | K81: 36638 | L81: =DATEDIF(K81,TODAY(),"Y") -> 25 | M81: 有 | N81: H&C | O81: 44669 | P81: 2027/03 | Q81: 特定技能２号 | R81: 松山市上野町774番地ビレッジハウス松山上野4-205 | S81: 個 | T81: 15000 | U81: 45962 | V81: 47102 | W81: UH82099732PC | X81: 寮23.5/21～ | Z81: 6668-故障のため Ｂ－0246668-1635 2333代替 Ｂ－0304388-V212 | AB81: N3 2025/07 | AE81: 45623 | AF81: 45660 | AK81: 大西係長 | AL81: ― | AM81: 2022/04/10 （雇用契約書確認） | AN81: 2025/6/１～2027/4/30 2号移行時解約済 | AP81: 2024/11/27～2025/01/03自身の結婚の為一時帰国 2025.8.18自転車故障。（自転車は津吉工場の自転車置き場に有り）代替自転車渡す 2025/12/21～特定2号へ資格変更予定 2025/12/15 特定2号へ移行完了 | AQ81: /appsheet/photograph/07013605.在留カード表裏.081406.pdf | AR81: 管理表_Files_/07013605.パスポート.071830.pdf
A82: 一課 | B82: 80 | C82: 津吉 | D82: インドネシア | E82: 07013606 | F82: /appsheet/photograph/IDPhoto_20250328_80_アユサ ヌル フィトリヤニ.jpg | G82: アユサ ヌル フィトリヤニ | H82: AYUSA NUR FITRIYANI | J82: 女 | K82: 36870 | L82: =DATEDIF(K82,TODAY(),"Y") -> 25 | N82: H&C | O82: 44669 | P82: 2027/03 | Q82: 特定技能１号 | R82: 松山市上野町774番地ビレッジハウス松山上野2-405 | S82: 個 | T82: 15000 | U82: 46106 | V82: 46184 | W82: UH11298219PC | Z82: 6671 Ｂ－0246671-1146 | AK82: 小林主任 | AL82: 〇 | AN82: 2025/6/１～2027/4/30 | AP82: 2025/3/8牛渕1号館→ビレッジ4-502へ引越 | AT82: /appsheet/photograph/07013606.通帳.000822.jpg
B83: 81 | C83: 津吉 | D83: インドネシア | E83: 07013607 | G83: ユリ アニ | H83: YULIANI | I83: ユリ | J83: 女 | K83: 35718 | L83: =DATEDIF(K83,TODAY(),"Y") -> 28 | N83: H&C | O83: 44669 | P83: 2027/03 | Q83: 特定技能１号 | R83: 東温市牛渕170-3 | S83: 母1F-4-相2 | T83: 10000 | U83: 44788 | V83: 45785 | W83: SA20104549PC | Z83: 自身で購入 | AE83: 45383 | AF83: 45414 | AH83: 退職 | AI83: 45677 | AJ83: 転職 （福岡スイーツ） | AP83: 2024.4.1～5/2一時帰国 2025/1に退職し、福岡の会社に転職申出(内定) 1/25退寮
B84: 82 | C84: 津吉 | D84: インドネシア | E84: 07013608 | G84: アウィツ ドゥンヌライン | H84: AWIT DUNNURAIN | J84: 女 | K84: 36056 | L84: =DATEDIF(K84,TODAY(),"Y") -> 27 | N84: H&C | O84: 44669 | P84: 2027/03 | Q84: 特定技能１号 | R84: 東温市牛渕170-3 | S84: 母1F-1-相2 | T84: 10000 | U84: 44788 | V84: 45785 | W84: SA63755763PC | Z84: 6672 Ｂ－0246672-1595 | AA84: 45997 | AE84: 45383 | AF84: 45414 | AH84: 退職 | AI84: 45736 | AJ84: 転職 | AP84: 2024.4.1～5/2一時帰国
B85: 83 | C85: 津吉 | D85: インドネシア | E85: 07013609 | G85: ノヴィアナ ラティー | H85: NOVIANA RATIH | J85: 女 | K85: 35762 | L85: =DATEDIF(K85,TODAY(),"Y") -> 28 | N85: H&C | O85: 44669 | P85: 2027/03 | Q85: 特定技能１号 | R85: 東温市牛渕170-3 | S85: 母1F-3-相2 | T85: 10000 | U85: 44788 | V85: 45785 | W85: SA68067686PC | Z85: 自身で購入 元2311-V141 | AE85: 45383 | AF85: 45414 | AH85: 退職 | AI85: 45677 | AJ85: 転職 （福岡スイーツ） | AP85: 2024.4.1～5/2一時 2024.5月 労災申請 2025/1に退職し、福岡の会社に転職申出(内定） 1/25退寮
B86: 84 | C86: 津吉 | D86: インドネシア | E86: 07013612 | G86: リンダ ヌルハリザ | H86: LINDA NURHALIZA | I86: リンダ | J86: 女 | K86: 35762 | L86: =DATEDIF(K86,TODAY(),"Y") -> 28 | M86: 夫婦 | N86: H&C | O86: 44669 | P86: 2027/03 | Q86: 特定技能１号 | R86: 松山市上野町774番地ビレッジハウス松山上野4-501 | S86: 夫婦 | T86: 20000 | U86: 44788 | V86: 45808 | W86: SA03276157PC | X86: 寮23.5/21～ | Z86: 自身で購入 | AE86: 45459 | AF86: 45504 | AH86: 退職 | AI86: 45677 | AJ86: 妊娠-出産 | AM86: 44661 | AP86: 一時帰国後8/1以降順風会で健診予定 2024.6月一時帰国予定（結婚）→夫が8月入社予定。 4-205よりハクと4-501へ2024/08/10引越家賃15,000→20,000へ 8/29 H&C三好さんより妊娠6週と連絡あり 2025/1/20退職 1/30退寮 1/30帰国 2025年11月頃中温へ戻りたいとのこと（ﾊｸより）
A87: 四課 | B87: 85 | C87: 津吉 | D87: インドネシア | E87: 07013614 | F87: /appsheet/photograph/IDPhoto_20250328_85_コフィファー ヌル コエリヤー.jpg | G87: コフィファー ヌル コエリヤー | H87: KHOFIFAH NUR KHOERIYAH | I87: コフィ | J87: 女 | K87: 36874 | L87: =DATEDIF(K87,TODAY(),"Y") -> 25 | M87: 無 | N87: H&C | O87: 44669 | P87: 2027/03 | Q87: 特定技能１号 | R87: 松山市上野町774番地ビレッジハウス松山上野4-502 | S87: 個 | T87: 15000 | U87: 46093 | V87: 46184 | W87: UH31691579PC一時帰国前、申請済 | Z87: 自身で購入 | AE87: 2025/01/31 2026/04/20 | AF87: 2025/03/03 2026/06/03 | AH87: 一時帰国予定 | AK87: 大西係長 | AM87: 44661 | AN87: 2022/04/10-2027/04/09 | AP87: 最終出勤日1/30 2025/1/31～3/3一時帰国 1/21～1/30まで勤務の為控除無し及びH&C管理住宅 自身の結婚のため、2026/04/20～6/3まで一時帰国希望 （新開工場長より2025/12/23） ※在留カード（6/11期限）帰国前に更新申請 2026年5月もしくは6月の特定2号の試験も申し出ありとのこと
B88: 86 | C88: 津吉 | D88: インドネシア | E88: 07013622 | G88: ヴァニ アフリリアニ ファディラ | H88: VANNY AFRILIANI FADILAH | I88: ヴァ二 | J88: 女 | K88: 37732 | L88: =DATEDIF(K88,TODAY(),"Y") -> 23 | N88: H&C | O88: 44937 | P88: 2027/12 | Q88: 特定技能１号 | R88: 東温市牛渕170-3（母屋2F） | V88: 45287 | W88: TJ55804897RD | Z88: 2205 | AH88: 退職 | AI88: 45240
B89: 87 | C89: 津吉 | D89: インドネシア | E89: 07013623 | G89: ユリンドラ アウリア プトリ | H89: YULINDRA AULIA PUTRI | I89: ユリ | J89: 女 | K89: 37447 | L89: =DATEDIF(K89,TODAY(),"Y") -> 23 | N89: H&C | O89: 44937 | P89: 2027/12 | Q89: 特定技能１号 | R89: 東温市牛渕170-3（母屋2F） | V89: 45287 | W89: TJ49633205RD | Z89: 2206 | AH89: 退職 | AI89: 45280
B90: 88 | C90: 津吉 | D90: インドネシア | E90: 07013615 | F90: /appsheet/photograph/IDPhoto_20250328_88_ウフィク ルフィアナ.jpg | G90: ウフィク ルフィアナ | H90: UFIK LUFIANA | J90: 女 | K90: 36553 | L90: =DATEDIF(K90,TODAY(),"Y") -> 26 | M90: 有 | N90: H&C | O90: 44669 | P90: 2027/03 | Q90: 特定技能１号 | R90: 松山市上野町774番地ビレッジハウス松山上野2-508 | S90: 夫婦 | T90: 20000 | U90: 46106 | V90: 46184 | W90: UH25074774PC | Z90: 6662 Ｂ－0246662-1767 | AE90: 45855 | AF90: 45893 | AK90: 小林主任 | AL90: 〇 | AM90: 44661 | AN90: 2025/6/１～2027/4/30 | AP90: 2024/09/21より１人部屋の為家賃15.000-変更 2025/7/17～8/24一時帰国 8/26～出勤 | AQ90: /appsheet/photograph/07013615.在留カード表裏.062020.pdf
B91: 89 | C91: 津吉 | D91: インドネシア | E91: 07013616 | G91: エルサ プルナマ セプティア プトリ | H91: ERSA PURNAMA SEPTIA PUTRI | I91: エルサ | J91: 女 | K91: 36770 | L91: =DATEDIF(K91,TODAY(),"Y") -> 25 | N91: H&C | O91: 44669 | P91: 2027/03 | Q91: 特定技能１号 | R91: 松山市上野町774番地ビレッジハウス松山上野4-205 | S91: 個 | T91: 15000 | U91: 44788 | V91: 45808 | W91: SA25435720PC | Z91: 自身で購入 | AH91: 退職 | AI91: 45677 | AJ91: 転職 （福岡スイーツ） | AP91: ２０２４/11月一時帰国したい申し出 ⇒取り下げ 12/4～1/3一時帰国したい→変更 2025/1に退職し、福岡の会社に転職申出(内定） 1/25退寮
B92: 90 | C92: 津吉 | D92: インドネシア | E92: 07013617 | G92: アルバシタ アマリア | H92: AL BASITA AMALIA | I92: アルバ | J92: 女 | K92: 37462 | L92: =DATEDIF(K92,TODAY(),"Y") -> 23 | N92: H&C | O92: 44669 | P92: 2027/03 | Q92: 特定技能１号 | R92: 東温市牛渕170-3 | T92: 15000 | U92: 44788 | V92: 45808 | W92: SA94653239PC | Z92: 2205 B-0274808-V213 | AB92: N3 2024/12/01 | AH92: 退職 | AI92: 45677 | AJ92: 転職 （福岡スイーツ） | AM92: 44661 | AP92: 12/3古谷さんより退職の意向の話。詳細は後日 1/31退寮 福岡の会社へ転職
B93: 91 | C93: 津吉 | D93: インドネシア | E93: 07013618 | G93: イスティコマー | H93: ISTIKOMAH | I93: イスティ | J93: 女 | K93: 37174 | L93: =DATEDIF(K93,TODAY(),"Y") -> 24 | N93: H&C | O93: 44669 | P93: 2027/03 | Q93: 特定技能１号 | R93: 東温市牛渕170-3 | S93: 離1F-2-個1 | T93: 15000 | U93: 44788 | V93: 45808 | W93: SA22913091PC | Z93: 6659 Ｂ－0246659-1645 | AA93: 45997 | AH93: 退職 | AI93: 45736 | AJ93: 転職 | AP93: 23.8/11～9/10一時帰国 2/28まで勤務 3/1～3/20まで有給 3/20退職
B94: 92 | C94: 津吉 | D94: インドネシア | E94: 07013611 | G94: ロチ アンジェリ ルイタン | H94: ROCHI ANJELI RUITANG | I94: ロチ | J94: 女 | K94: 37494 | L94: =DATEDIF(K94,TODAY(),"Y") -> 23 | N94: H&C | O94: 44669 | P94: 2027/03 | Q94: 特定技能１号 | R94: 松山市上野町774番地ビレッジハウス松山上野4-502 | S94: 個 | T94: 15000 | U94: 44788 | V94: 45808 | W94: SA25451122PC | Z94: 自身で購入 | AH94: 退職 | AI94: 45677 | AJ94: 結婚 帰国後転職 | AP94: 1/21退寮 結婚のため、退職。帰国後結婚式を行い、旦那の勤務する大阪に転職予定
B95: 93 | C95: 津吉 | D95: インドネシア | E95: 07013613 | G95: エガ アユ ドウィプラウェティ | H95: EGA AYU DWI PRAWESTI | J95: 女 | K95: 37511 | L95: =DATEDIF(K95,TODAY(),"Y") -> 23 | N95: H&C | O95: 44669 | P95: 2027/03 | Q95: 特定技能１号 | R95: 東温市牛渕170-3 | S95: 母1F-1-相2 | T95: 10000 | U95: 44788 | V95: 45808 | W95: SA93545760PC | Z95: 6667 Ｂ－0246667-1173 | AE95: 45253 | AF95: 45293 | AH95: 退職 | AI95: 45736 | AJ95: 転職 | AP95: 23.11/23～1/2一時帰国 1/5出社
A96: 二課 | B96: 94 | C96: 津吉 | D96: インドネシア | E96: 07013619 07018701 | F96: /appsheet/photograph/IDPhoto_20250328_94_ミフタフル アリフ.jpg | G96: ミフタフル アリフ | H96: MIFTAKHUL ARIF | I96: アリフ | J96: 男 | K96: 34331 | L96: =DATEDIF(K96,TODAY(),"Y") -> 32 | M96: 有 | N96: H&C | O96: 44669 | P96: 2027/03 | Q96: 特定技能２号 | R96: 松山市上野町774番地ビレッジハウス松山上野3-507 | S96: 個 | T96: 15000 | U96: 45962 | V96: 47102 | W96: UH86875702PC | Z96: 6660 B-0246660-1194 ｼﾙﾊﾞｰ26ｲﾝﾁ | AB96: N4 | AK96: 佐伯主任 | AL96: ― | AM96: 44661 | AN96: 2025/6/１～2027/4/30 2号移行時解約済 | AP96: 24.5/1～6/28一時帰国 7/8新開工場長より一時帰国に有給を使いたい申出あるも、事前申請ないため不可(専務相談済) 2025/12/21～特定2号へ資格変更予定 2025/12/15 特定2号へ移行完了 | AQ96: /appsheet/photograph/07013619.在留カード表裏.081828.pdf | AR96: 管理表_Files_/07013619.パスポート.070451.pdf
B97: 95 | C97: 津吉 | D97: インドネシア | E97: 07013620 | G97: レストゥ グメラー | H97: RESTU GUMELAR | J97: 男 | K97: 35416 | L97: =DATEDIF(K97,TODAY(),"Y") -> 29 | N97: H&C | O97: 44669 | P97: 2027/03 | Q97: 特定技能１号 | R97: 松山市上野町774番地ビレッジハウス松山上野3-507 | S97: 個 | T97: 15000 | U97: 44788 | V97: 45808 | W97: SA83962817PC | Z97: 6670 Ｂ－0246670-1763 | AB97: N4 2017/01/22 | AH97: 退職 | AI97: 45585 | AP97: 2024/10/09三好さんより退職の連絡。新開工場長へ連絡済。兵庫の冷凍食品11/1より時給1,200-平均して残業があるため、指導しても時給が大差ないため
A98: 四課 | B98: 96 | C98: 津吉 | D98: インドネシア | E98: 07013638 | F98: /appsheet/photograph/IDPhoto_20250328_96_ニマトゥル マウリダ.jpg | G98: ニマトゥル マウリダ | H98: NIMATUL MAULIDA | J98: 女 | K98: 35621 | L98: =DATEDIF(K98,TODAY(),"Y") -> 28 | M98: 夫婦 | N98: H&C | O98: 45075 | P98: 2028/04 | Q98: 特定技能１号 | R98: 松山市上野町774番地ビレッジハウス松山上野4-504 | S98: 夫婦 | T98: 20000 | U98: 46106 | V98: 46184 | W98: UH01039353PC | Z98: 自身で購入 元2309 中野住宅で使用 | AA98: 45555 | AB98: N3 2024/07/07 | AE98: 45783 | AF98: 45817 | AH98: 育児休暇中 | AK98: 大西係長 | AL98: 〇 | AM98: 45071 | AN98: 2025/6/25-2028/5/24 | AP98: N3：2024/07/07 10/15連絡あり→10/31振込分より手当 2025/5/6～6/10一時帰国 帰国後 6/9～ﾋﾞﾚｯｼﾞ4-504へ夫エカと住む 2025/11/2エカより、ニマが妊娠13週との連絡あり。今後について、相談すると伝える エカと３人で津吉社長室にて話す。出産予定2026/5/5、つばきウイメンズで出産予定、日本にて産みたい。エカも特定２号受けたい。入社が2025/6/17、転職のため、特定１号の機嫌が2027/3までのため、入官へ確認。
A99: 四課 | B99: 97 | C99: 津吉 | D99: インドネシア | E99: 07013639 | F99: /appsheet/photograph/IDPhoto_20250328_97_ハビバ プリヤンティ.jpg | G99: ハビバ プリヤンティ | H99: HABIBAH PRIYANTI | J99: 女 | K99: 38039 | L99: =DATEDIF(K99,TODAY(),"Y") -> 22 | N99: H&C | O99: 45075 | P99: 2028/04 | Q99: 特定技能１号 | R99: 松山市上野町774番地ビレッジハウス松山上野4-505 | S99: 個 | T99: 15000 | U99: 46106 | V99: 46184 | W99: UH53265164PC | Z99: ｱｼｽﾄ（自身で購入） 2310-B-0287449 9/6中野住宅へ移動 | AA99: 45373 | AK99: 大西係長 | AL99: 〇 | AM99: 45071 | AN99: 2025/6/１～2028/5/31
A100: 一課 | B100: 98 | C100: 津吉 | D100: インドネシア | E100: 07013640 | F100: /appsheet/photograph/IDPhoto_20250328_98_ノヴィ ノヴィタ.jpg | G100: ノヴィ ノヴィタ | H100: NOVI NOVITA | J100: 女 | K100: 38073 | L100: =DATEDIF(K100,TODAY(),"Y") -> 22 | M100: 無 | N100: H&C | O100: 45075 | P100: 2028/04 | Q100: 特定技能１号 | R100: 松山市上野町774番地ビレッジハウス松山上野4-502 | S100: 個 | T100: 15000 | U100: 46106 | V100: 46184 | W100: UH31391623PC一時帰国後、申請 | X100: 寮23.10/21～ | Z100: 自身で購入 | AE100: 46093 | AF100: 46122 | AH100: 一時帰国予定 | AK100: 小林主任 | AL100: 〇 | AM100: 45071 | AN100: 2025/6/１～2028/5/31" | AP100: 2025/3/29～1号館1人部屋→ビレッジ4-502へ 家賃同額 | AQ100: /appsheet/photograph/07013640.在留カード表裏.062206.pdf | AR100: /appsheet/photograph/07013640.パスポート.062206.pdf
...

Sheet 履歴
A1: 連番 | B1: 日付 | C1: 時間 | D1: 登録者 | E1: 実習生 | F1: 場所 | G1: 申請区分 | H1: 完了区分 | I1: 登録画像１－１ | J1: 登録画像１－２ | K1: 登録記事 | L1: 対応１日付 | M1: 対応１時間 | N1: 対応者１ | O1: 対応画像１ー１ | P1: 対応画像１－２ | Q1: 対応１記事 | R1: 対応２日付 | S1: 対応２時間 | T1: 対応者２ | U1: 対応画像２ー１ | V1: 対応画像２－２ | W1: 対応２記事 | X1: 対応３日付 | Y1: 対応３時間 | Z1: 対応者３ | AA1: 対応画像３ー１ | AB1: 対応画像３－２ | AC1: 対応３記事 | AD1: 対応４日付 | AE1: 対応４時間 | AF1: 対応者４ | AG1: 対応画像４ー１ | AH1: 対応画像４－２ | AI1: 対応４記事 | AJ1: 対応５日付 | AK1: 対応５時間 | AL1: 対応者５ | AM1: 対応画像５ー１ | AN1: 対応画像５－２ | AO1: 対応５記事 | AP1: 備考
A2: 1 | B2: 45958 | C2: 0.37100694 | D2: 池内 | E2: 07013662 | F2: ビレッジ4-502 | G2: 病院 | H2: 完了 | L2: 45958 | N2: 池内 | O2: 履歴_Images/1.対応画像１ー２.015505.jpg | Q2: 10.26から体調不良 10.28かどた内科にて受診でコロナ陽性 金曜日まで自宅療養
A3: 2 | B3: 45959 | C3: 0.63690972 | D3: 池内 | E3: 07013675 | F3: ビレッジ3-501 | G3: 病院 | H3: 対応中 | K3: 10/29にチンティアから、11/12にどい心療内科へ連れてってほしいと相談。（最近眠れない、涙が出る。などの症状）本人が11：50診察予約している。チンティアのおばが通訳として病院に同行予定。 | L3: 45961 | M3: 0.51388889 | N3: 尾崎 | Q3: 新開工場長より、昨日、タブレット入力ミスを他の実習生に指摘され更衣室で泣いてた。その時に精神科受診の話を聞いた。本日、休み。明日も休むようなら様子を確認すると伝える。11.1_10時自宅にて池内さん尾崎で話し、落ち着いた様子。とりあえず、月曜日から仕事にはいく。ブイにも話しなくていいとのこと。また何かあれば、連絡依頼。11/4に11/3,11/4出勤確認。 | R3: 45973 | T3: 池内 | W3: 11/12どい心療内科受診。3か月ほど前から不安症状あり。他人からどう見られているのかとても気にしてしまい過剰に不安になる。失敗するのが怖く、色々考えて集中できない。10日分の薬をもらい11/22に再度受診予定。11月頭の実習生に怒られた件も少しトラウマになっているので、今後のチーム組むときにできれば配慮をしてほしいと工場長に相談した。 | AC3: 11/22経過観察。インドネシアにいるときにも心療内科かかってたらしい。合う薬模索中。次回12/5 10:00~ | AP3: 12/22済・次回1/23 9:50～
A4: 3 | B4: 45960 | C4: 0.4099537 | D4: 尾崎 | E4: 07013641 | G4: 帰国 | H4: 完了 | K4: 新開工場長より、2026/3/13より2ヶ月ぐらい、自身の結婚のため帰国の申し出。日程の調整確認依頼 | L4: 45960 | M4: 0.45362269 | N4: 尾崎 | Q4: 10/30現在有休残３日、11/29付与12日、合計15日新開工場長へline済み | R4: 45971 | S4: 0.52361111 | T4: 尾崎 | U4: /appsheet/rireki_photo/3.対応画像２ー１.231248.jpg | V4: /appsheet/rireki_photo/3.対応画像２－２.231248.jpg | W4: 3/13結婚のため、一時帰国。5/10頃帰国し在留カード更新手続きを行うと話す。 | AA4: /appsheet/rireki_photo/3.対応画像３ー１.060848.jpg | AB4: /appsheet/rireki_photo/3.対応画像３－２.060848.jpg | AD4: 46092 | AE4: 0.37976852 | AF4: 尾崎 | AG4: /appsheet/rireki_photo/3.対応画像４ー１.000907.jpg | AI4: 3/12松山発17:40に変更。インドネシアへはノヴィと一緒
A5: 4 | B5: 45960 | C5: 0.41168981 | D5: 尾崎 | E5: 07013685 | G5: 退職 | H5: 完了 | K5: ザーラより、LINEにて、12/20を最終出勤日として翌1/5の飛行機で大学に行くため帰国したい申し出。新開工場長へ電話にて報告 | L5: 45960 | M5: 0.45572917 | N5: 尾崎 | Q5: 10/30現在有休残４日。付与日は4/29のため、４日で新開工場長へline済 | R5: 45971 | S5: 0.54861111 | T5: 尾崎 | U5: /appsheet/rireki_photo/4.対応画像２ー１.041443.jpg | W5: 本人より、12/20退職、12/末現金給与、1/7松山空港発(1/7退寮)、1/10東京発でチケットとった。チケット送付依頼し、そのスケジュールにて進めると伝える。1/10羽田空港11:45発 | AP5: 最終出勤12/18 12/19と12/20は有給使用
A6: 5 | B6: 45960 | C6: 0.42792824 | D6: 尾崎 | E6: 07001616 | F6: アトム705 | G6: 購入 | H6: 完了 | I6: /appsheet/rireki_photo/5.登録画像１－１.012008.jpg | J6: /appsheet/rireki_photo/5.登録画像１－２.012009.jpg | K6: ヒエンの妹が入社するので、エアコン設置依頼 | L6: 45960 | M6: 0.44371528 | N6: 尾崎 | Q6: 竹内空調さんへ11/18までに設置依頼 | R6: 45966 | S6: 0.44652778 | T6: 尾崎 | U6: /appsheet/rireki_photo/5.対応画像２ー１.043834.jpg | W6: 竹内空調にて設置済み 三菱エアコン 77,000税別 月末締め翌月OK
A7: 6 | B7: 45961 | C7: 0.3125 | D7: 尾崎 | F7: コーポ津吉1-6 | G7: 修理 | H7: 完了 | K7: コーポ津吉1-6で３日間Wifiが使えない状態の申し出。 | L7: 45962 | M7: 0.47222222 | N7: 尾崎 | Q7: 電源及び配線再起動により稼働、マデ休みにより
A8: 7 | B8: 45961 | C8: 0.69521991 | D8: 尾崎 | E8: 07018606 | G8: 問合せ | H8: 完了 | I8: /appsheet/rireki_photo/7.登録画像１－１.074924.jpg | J8: /appsheet/rireki_photo/7.登録画像１－２.074924.jpg | K8: 新開工場長より、インドネシア時より、脊髄がまがる病気で重たいもの等をもつ仕事を変更してほしいとの申し出あり。入国前の健康診断でも問題がないため入国ができ、入国後の健康診断でも該当ないため、本人と面談を行う | L8: 45962 | M8: 0.60416667 | N8: 尾崎 | Q8: デフィとヤニと４人で牛渕２号館ではなし。病院には行ってない。とりあえず、できるところまでやってみて、ダメになる前に上長へ。新開工場長へ報告済み
A9: 8 | B9: 45963 | C9: 0.52013889 | D9: 尾崎 | E9: 07013638 | G9: 妊娠 | H9: 対応中 | K9: エカより、ニマが妊娠13週との連絡あり。今後について、相談すると伝える。 | L9: 45965 | M9: 0.35666667 | N9: 尾崎 | Q9: 新開工場長へline連絡 | R9: 45966 | S9: 0.52430556 | T9: 尾崎 | W9: エカと３人で津吉社長室にて話す。出産予定5/5、つばきウイメンズで出産予定、日本にて産みたい。エカも特定２号受けたい。入社が2025/6/17、転職のため、特定１号の期限が2027/3までのため、入官へ確認 | X9: 46091 | Y9: 0.53799769 | Z9: 尾崎 | AA9: /appsheet/rireki_photo/8.対応画像３ー１.235743.jpg | AC9: 出産を県立中央病院へ変更した。予定通り3/25より産休予定
A10: 9 | B10: 45965 | C10: 0.54489583 | D10: 池内 | E10: 07011609 | G10: 問合せ | H10: 完了 | K10: 11/4ヅエンから尾崎さんへ就労証明書発行依頼あり。→恒岡さんへ記入依頼済。出来上がり次第ヅエンへ届ける。 | L10: 45966 | M10: 0.45833333 | N10: 尾崎 | Q10: 本人へ就労証明書と年末調整の書類を渡す。年末調整は後日取りに来ると伝える。 | R10: 45972 | S10: 0.3849537 | T10: 尾崎 | W10: 年末調整及び送金明細書回収する
A11: 10 | B11: 45967 | C11: 0.4025463 | D11: 池内 | E11: 07001423 | F11: アトム401 | G11: 病院 | H11: 完了 | K11: 11/6朴さんより宮内工場長へ連絡あり。ディンが4か月ほど生理が来ていないらしく、11/18に中四国が婦人科へ連れていくとのこと。 | N11: 池内 | Q11: 一応、生理再開したとのことで病院は行かないことになった。
A12: 11 | B12: 45968 | C12: 0.2875 | D12: 尾崎 | E12: 07013682 | G12: 退職 | H12: 完了 | I12: /appsheet/rireki_photo/11.登録画像１－１.215912.jpg | K12: 新開工場長より、２/２０退職、１０日後退寮の申し出あり、確認依頼。 | L12: 45971 | M12: 0.54861111 | N12: 尾崎 | Q12: 2/20退職してインドネシアに帰国する。2/末給料、3/1に松山発の予定。
A13: 12 | B13: 45968 | C13: 0.33855324 | D13: 尾崎 | E13: 07001618 | F13: アトム404 | G13: 病院 | H13: 完了 | I13: /appsheet/rireki_photo/12.登録画像１－１.231036.jpg | K13: 宮内工場長に、皮膚に発疹みたいなものがあり、病院に行きたい申し出あり。11/7、９時に連れていく旨連絡。 | L13: 45968 | N13: 池内 | Q13: 二宮皮ふ科受診。全身にかゆみと発疹あり。蕁麻疹と診断。２日前くらいから出ているので、食べ物などのアレルギーではなさそう。免疫低下やストレス？薬飲んで様子見る。
A14: 13 | B14: 45968 | C14: 0.3666088 | D14: 尾崎 | E14: 07012622 | G14: 病院 | H14: 完了 | K14: 11/17月曜日、子宮筋腫の手術 | L14: 45981 | M14: 0.48888889 | N14: 尾崎 | Q14: 恒岡さんより、デルタ四国の通訳よりTELあり、手術跡が大きく、当初11/30までやすみだったが、12/20ごろまでには出勤すると連絡あり。後日、12/1～の休暇届作成すること | R14: 45987 | S14: 0.62157407 | T14: 尾崎 | W14: 本人と面談。12/3水曜日が通院日。12/20まで傷口が大きいため休暇申出。12/3病院受診時に診断書をもらうとのこと
A15: 14 | B15: 45968 | C15: 0.52083333 | D15: 尾崎 | E15: 07018631 | G15: 紛失 | H15: 完了 | K15: 在留カードが、銀行口座作成してから紛失。探したが見つからず。とりあえず、コピーを渡す。 | L15: 45969 | N15: 池内 | Q15: 11/6在留カード紛失の申し出。11/8に南署にて遺失物届を出した。受理番号1669。11/10に入管へ在留カード再発行申請をする予定。 | R15: 45971 | S15: 0.51388889 | T15: 尾崎 | W15: 入官にて在留カード再発行を行い、昼、食堂にて渡す。
A16: 15 | B16: 45968 | C16: 0.5625 | D16: 尾崎 | E16: 07011606 | G16: 一時帰国 | H16: 完了 | K16: ２号試験終了後、２月初めから、２ヶ月一時帰国したい申し出あり。水沼さん了承。 | L16: 46016 | M16: 0.56597222 | N16: 尾崎 | O16: /appsheet/rireki_photo/15.対応画像１ー２.073801.jpg | Q16: 1/24～３/24まで一時帰国。広島空港発着
A17: 16 | B17: 45971 | C17: 0.43055556 | D17: 尾崎 | E17: 07013679 | G17: 病院 | H17: 完了 | K17: 新開工場長より、手が痛いので病院へ連れていってほしいとの依頼あり。以前、尾崎に話してたとのこと。10/4に日曜日に診察できる整形外科の案内があり、南松山病院を案内。その当時、ハクと一緒に行くと行っていたが、実際に診察したかどうかは不明。本日お昼に確認する。 | L17: 45971 | M17: 0.52708333 | N17: 尾崎 | Q17: 手首は痛いが、木曜日か金曜日でOK。新開工場長へ伝え、時間が分かったら連絡依頼。10/4は整形外科の先生がいないため診察しなかった。金澤整形でもOK | R17: 45974 | T17: 池内 | W17: 11.13金澤受診。重いものや手首の曲げで負担かかっている。レントゲンにて、左手首、少し炎症してる。電気治療を何度か行いリハビリで様子見る。次回は11.29リハビリ。イーサンは次回より１人で受診
A18: 17 | B18: 45971 | C18: 0.48396991 | D18: 池内 | E18: 07013665 | F18: ビレッジ2-502 | G18: 病院 | H18: 完了 | K18: 同部屋のアルバシタから、アイナの体調不良とLINEあり。数日前から声が出なくなっていた。近くのよしおか内科を案内。 | L18: 45971 | M18: 0.52916667 | N18: 尾崎 | Q18: アルバシタと話す。イナは今日11:30～仕事で熱はなく声が出ない様子。明日、昼からなので、午前中、病院へ行くなら８時までにLINE依頼 | R18: 45972 | T18: 池内 | U18: /appsheet/rireki_photo/17.対応画像２ー１.052518.jpg | W18: 11/11 よしおか内科受診。熱はないため検査なし。鼻水・咳・声枯れの症状で薬飲んで様子見。仕事は通常通り勤務する。
A19: 18 | B19: 45971 | C19: 0.57321759 | D19: 尾崎 | E19: 07011602 | G19: 退職 | H19: 完了 | K19: 2026/2月に退職して帰国したい申し出。新開工場長へ連絡済み。帰りの飛行機代を確認依頼。 | L19: 45988 | M19: 0.52430556 | N19: 尾崎 | O19: 履歴_Images/18.対応画像１ー２.025523.jpg | P19: /appsheet/rireki_photo/18.対応画像１－２.025523.jpg | Q19: 2/14広島空港13:00発チケット、交通手段確認 | R19: 46010 | S19: 0.52680556 | T19: 尾崎 | V19: /appsheet/rireki_photo/18.対応画像２－２.065708.jpg | W19: 広島空港までは自分で行くとのこと | X19: 46062 | Y19: 0.66180556 | Z19: 尾崎 | AA19: /appsheet/rireki_photo/18.対応画像３ー１.065516.jpg | AB19: /appsheet/rireki_photo/18.対応画像３－２.065516.jpg | AC19: 銀行及び転出届、広島空港２つ荷物をヤマト運輸持ち込み。保険証回収済み。家の鍵と自転車鍵はハンヘ土曜日に渡すとのこと。
A20: 19 | B20: 45972 | C20: 0.53215278 | D20: 尾崎 | E20: 07012626 | G20: 退職 | H20: 完了 | I20: /appsheet/rireki_photo/19.登録画像１－１.082907.jpg | J20: /appsheet/rireki_photo/19.登録画像１－２.082907.jpg | K20: 退寮日が変更になった。11/20退職、11/21退寮、11/21の15時頃の飛行機。11/21の9時部屋の立ち会いだが、事前に１８日～２０日までに部屋確認すると伝える | L20: 45975 | M20: 0.43541667 | N20: 尾崎 | O20: 履歴_Images/19.対応画像１ー２.082907.jpg | P20: /appsheet/rireki_photo/19.対応画像１－２.082910.jpg | Q20: 日曜日に掃除とゴミを捨てるよう指示。最終11/21の１０時訪問予定 | R20: 45982 | S20: 0.41666667 | T20: 尾崎 | W20: 退去確認。部屋の鍵、自転車の鍵、保険証預り終了。デルタ四国立会
A21: 20 | B21: 45972 | C21: 0.56527778 | D21: 尾崎 | E21: 07012622 | G21: 問合せ | H21: 完了 | K21: ビレッジ中野さんから、松山南警察地域課高山さん958-0110より自転車が置かれており撤去依頼があったと連絡あり。 | L21: 45972 | M21: 0.57054398 | N21: 尾崎 | Q21: 昼休憩にて本人がおり、自転車撤去に向かう。朝、出勤時にアンディ二が自転車でこけてククが自転車で会社に連れて行った。アンディ二の自転車をチャンが乗って行って、チャンの自転車を日野車体の車庫に置いたため、日野車体より警察に連絡が入る。仕事終わりに取りに行く予定だった。 | R21: 45972 | S21: 0.58333333 | T21: 尾崎 | W21: チャン同席の上、日野車体に訪問し、お詫びし自転車を回収する。結構お怒りモードだったが、ご迷惑おかけしたことお詫びし了承をえる。 | AP21: 大澤専務に報告後、新開工場長へ栗ご飯の素持参予定
A22: 21 | B22: 45973 | C22: 0.32853009 | D22: 尾崎 | E22: 07013685 | G22: 病院 | H22: 完了 | I22: /appsheet/rireki_photo/21.登録画像１－１.024607.jpg | J22: /appsheet/rireki_photo/21.登録画像１－２.024607.jpg | K22: 昨日から背中が痛いので病院へ行きたいとの申し出あり。 | L22: 45974 | N22: 池内 | Q22: 右脇腹あたりが痛む。息するのも痛みがあるため、金澤受診。レントゲンをとり、症状から骨にヒビが入ってる可能性があるとのこと。固定バンドをつけて生活するように言われた。11.20に金澤を受診するよう言われた。１人では不安なので付き添って欲しいとのこと。仕事については、本人の無理のない範囲で行うよう伝えた | R22: 45981 | T22: 池内 | W22: 呼吸時の痛みは治まったが、まだ起き上がるとき辛い。固定バンド外してたので、お風呂以外はバントするよう伝えた。12/4受診予定 | X22: 45999 | Z22: 池内 | AC22: 12/4にて、通院終了
A23: 22 | B23: 45973 | C23: 0.53592593 | D23: 尾崎 | E23: 07012625 | G23: 妊娠 | H23: 完了 | K23: 昨日、病院へ行って妊娠４週ぐらい。まだ小さいため、安定したら再度話す。新開工場長へは連絡済み | L23: 45978 | M23: 0.52777778 | N23: 尾崎 | Q23: ブイより、流産したと報告あり。タオは本日休み。
A24: 23 | B24: 45975 | C24: 0.46601852 | D24: 池内 | E24: 07001423 | F24: アトム401 | G24: 病院 | H24: 完了 | K24: 藤原さんより、ディンが体調不良なのか、仕事に来てないので部屋に見に行って欲しいとのことで渡部さんに見に行ってもらった。生理痛がひどく寝込んでいた。15日の昼から仕事に行くとのこと。18日には中四国と一緒に婦人科へ受診することになっている→病院行かなくていいとのこと。 | L24: 45975 | N24: 渡部
A25: 24 | B25: 45975 | C25: 0.95833333 | D25: 尾崎 | E25: 07018624 | F25: 牛渕１ | G25: 病院 | H25: 完了 | I25: /appsheet/rireki_photo/24.登録画像１－１.013658.jpg | K25: エヴィより、手が腫れて病院へ行きたいとの申し出あり。11/15土曜日8:45迎え行くと伝える | L25: 45976 | M25: 0.375 | N25: 尾崎 | O25: 履歴_Images/24.対応画像１ー２.013658.jpg | P25: /appsheet/rireki_photo/24.対応画像１－２.013658.jpg | Q25: 金澤整形に受診、新開工場長と相談し、手の固定されてるので11/16休み、11/17病院へ行き、手の固定がどうなるかで勤務するか判断。11/17、11/20に病院へ行くと伝える。11/17金澤整形受診、痛みもまだあり固定器具もはずせないため、11/20受診まで休み、新開工場長へ連絡済み | R25: 45981 | T25: 池内 | U25: /appsheet/rireki_photo/24.対応画像２ー１.005843.jpg | W25: まだ内出血で腫れている。指を曲げるような仕事は控えるよう言われた。本人が早く仕事復帰したいというので、新開さんへ事情を伝えた上で11/20昼から勤務してみるとのこと。次回11/27受診予定。 | X25: 45995 | Z25: 池内 | AC25: 12/4受診。また来週も来るよう言われたが、本人はもう行かなくても大丈夫と言ってるので、今回で通院終了。 | AP25: 11/27 経過良好だが、まだ少し痛み残っているため12/4に受診予定がある。オクトリヴィアも4日に受診なので二人で行くよう伝えた。12/11再診。痛みはないが右手握れない。
A26: 25 | B26: 45975 | C26: 0.54166667 | D26: 渡部 | E26: 07001618 | F26: アトム404 | G26: 問合せ | H26: 完了 | K26: 宮内工場長より、アトムマンションに自転車を停めていたところ、紛失したとのこと。本人に詳細確認予定。 | L26: 45976 | M26: 0.5 | N26: 渡部 | Q26: ロンに詳細を確認したところ、11/11(火)の15時頃に買い物に行こうとしたところ無くなっていた。鍵はかけておいていた。代替自転車が必要とのことで、準備が出来し伝える。 | R26: 45976 | S26: 0.5 | T26: 池内 | U26: /appsheet/rireki_photo/25.対応画像２ー１.054120.jpg | W26: 自転車6656（B-0246656）が準備できたので、ロンに鍵を渡した。
A27: 26 | B27: 45976 | C27: 0.55780093 | D27: 渡部 | E27: 07012622 | G27: 病院 | H27: 完了 | K27: 子宮筋腫の手術のため、デルタより病院からの連帯保証人に雇用主様にて対応をお願いしたいとのメールあり。専務に確認したところ弊社で対応する旨了承済み。傷病手当で進めるようにとのこと。 | L27: 45967 | M27: 0.83333333 | N27: 渡部 | R27: 45975 | S27: 0.41666667 | T27: 渡部 | W27: 病院からの書類をデルタへ渡した。休暇届けをデルタの松岡さんに代筆で記入してもらう。傷病手当の書類を2セット渡し済み。11/20締めで1回目の申請をすると伝えた。 | X27: 46013 | Y27: 0.4375 | Z27: 渡部 | AC27: デルタ 松岡さんより、傷病手当の書類が揃い次第、持って来られる予定。 | AP27: 書類回収により申請終了
A28: 27 | B28: 45976 | C28: 0.47916667 | D28: 尾崎 | E28: 07018627 | F28: 中野２ | G28: 修理 | H28: 完了 | K28: 自転車が何かおかしい。中野２に置いている | L28: 45976 | M28: 0.57361111 | N28: 尾崎 | O28: 履歴_Images/27.対応画像１ー２.044644.jpg | Q28: 後輪にネジが刺さっていたため、抜いて対応終了
A29: 28 | B29: 45978 | C29: 0.32796296 | D29: 尾崎 | E29: 07013631 | F29: ビレッジ3-507 | G29: 病院 | H29: 完了 | K29: ナウファルより腰が痛いので病院へ連れていってほしいと連絡あり | L29: 45978 | M29: 0.375 | N29: 尾崎 | Q29: 金澤整形受診。ぎっくり腰のため、次回11/20、痛みがまだあるようなら、11/27受診依頼。次回は自転車で行くよう指示。 | R29: 45988 | T29: 池内 | W29: 痛みほぼ治った。今ある薬飲み切ってもう病院行かなくていいとのこと。
A30: 29 | B30: 45978 | C30: 0.34761574 | D30: 池内 | E30: 07018616 | F30: 牛渕１ | G30: 病院 | H30: 完了 | K30: 入社時の健康診断で貧血で要治療判定。専務より、貧血で倒れるといけないので病院を受診するよう言われた。有給がないため、土曜日に受診できる中野クリニックに行く予定。11/29午前中受診予定 | L30: 45990 | M30: 0.37506944 | N30: 渡部 | Q30: 中野クリニック受診。鉄欠乏性貧血と診断され、1カ月薬を服用し、飲みきったら再度受診し採血の予定。
A31: 30 | B31: 45976 | C31: 0.90277778 | D31: 尾崎 | E31: 07013669 | F31: ビレッジ3-508 | G31: 修理 | H31: 完了 | I31: /appsheet/rireki_photo/30.登録画像１－１.234126.jpg | J31: /appsheet/rireki_photo/30.登録画像１－２.001414.jpg | K31: 自転車がパンクしたと申し出あり。月曜日に対応する。カギが必要と伝える。 | L31: 45978 | M31: 0.625 | N31: 尾崎 | O31: 履歴_Images/30.対応画像１ー２.065249.jpg | P31: /appsheet/rireki_photo/30.対応画像１－２.065248.jpg | Q31: タイヤ交換、4,000円、鍵を前かごにいれる
A32: 31 | B32: 45979 | C32: 0.33490741 | D32: 池内 | E32: 07018621 | F32: 牛渕１ | G32: 修理 | H32: 完了 | K32: 11/17の夜からガスが使えなくなったとの連絡あり。尾崎さんに見に行ってもらう。 | L32: 45979 | M32: 0.39583333 | N32: 尾崎 | O32: 履歴_Images/31.対応画像１ー２.023432.jpg | P32: /appsheet/rireki_photo/31.対応画像１－２.023432.jpg | Q32: トーカイガス089-932-3351に来てもらい、復旧。ガス欠だった。
A33: 32 | B33: 45980 | C33: 0.51388889 | D33: 尾崎 | E33: 07011612 | F33: コーポ津吉1-2 | G33: 病院 | H33: 完了 | I33: /appsheet/rireki_photo/32.登録画像１－１.215921.jpg | K33: 健診で大腸がんの健診を受けるよう話す。来週夜勤のため受診可能。 | L33: 45981 | M33: 0.50979167 | N33: 尾崎 | O33: 履歴_Images/32.対応画像１ー２.074922.jpg | P33: /appsheet/rireki_photo/32.対応画像１－２.074922.jpg | Q33: ■ 診察予約 【診察日時】2025年11月25日 10:30 【医療機関】眞柴消化器内科クリニック（TEL: 0899681202) 11/28(金)12：00～16:00大腸内視鏡検査 28日は仕事休むこと新開さんへ連絡済 | R33: 45989 | S33: 0.68055556 | T33: 池内 | W33: 検査問題なく終了。異常もなく、結果は問題なし。
A34: 33 | B34: 45981 | C34: 0.50809028 | D34: 尾崎 | E34: 07001605 | G34: 一時帰国 | H34: 完了 | K34: 宮内工場長より2025/12/25～2/3まで一時帰国の申出あり。チケットは中温で取得の要請あり。 | L34: 45982 | M34: 0.61393519 | N34: 尾崎 | O34: 履歴_Images/33.対応画像１ー２.030953.jpg | P34: /appsheet/rireki_photo/33.対応画像１－２.030953.jpg | Q34: 関西国際空港 12/25 10:00発 13:30着 ハノイ 2/2 01:05発 06:55着 往復115,800-にてチケット手配
A35: 34 | B35: 45985 | C35: 0.405 | D35: 池内 | E35: 07018630 | F35: 中野２ | G35: 病院 | H35: 完了 | K35: 11/23に歯が痛く熱もあり病院に行きたいとLINEあり。休日2連休で病院も休診で職員も休日のため、25日まで様子見るとのこと。 | L35: 45985 | M35: 0.42083333 | N35: 尾崎 | O35: 履歴_Images/34.対応画像１ー２.010745.jpg | P35: /appsheet/rireki_photo/34.対応画像１－２.022749.jpg | Q35: 11/25、9:30～グリーン歯科予約 11/25右奥歯下が腫れてて抜くしかない。３日分の化膿止めと熱覚ましをもらい、12/2に抜く予定。病院の先生より、疲れと化膿及び熱があるため木曜日まで休み。木曜日に症状連絡依頼→11/27少し腫れているが、痛み治まってきたので11/28から出勤。 | R35: 45993 | T35: 池内 | U35: /appsheet/rireki_photo/34.対応画像２ー１.022749.jpg | W35: 12/2抜歯した。12/9 9：30に消毒の為、再受診
A36: 35 | B36: 45986 | C36: 0.49087963 | D36: 尾崎 | E36: 07013633 | G36: 結婚 | H36: 対応中 | K36: ナナより、デウィマシトと来年結婚する。2026/7/18～9/4まで帰国結婚、中温で２人で住居したい申出。日程については、新開工場長と相談済。 | L36: 46058 | M36: 0.51597222 | N36: 尾崎 | Q36: ナナとLINE交換しやり取りすると伝える | R36: 46065 | S36: 0.53194444 | T36: 尾崎 | U36: /appsheet/rireki_photo/35.対応画像２ー１.224711.jpg | V36: /appsheet/rireki_photo/35.対応画像２－２.224710.jpg | W36: ナナより、チケットもらう
A37: 36 | B37: 45987 | C37: 0.60922454 | D37: 尾崎 | F37: 牛渕２ | G37: 問合せ | H37: 完了 | I37: /appsheet/rireki_photo/36.登録画像１－１.053858.jpg | K37: ６、２５、３６、８、１、１２、１５、１４ | L37: 45987 | M37: 0.62375 | N37: 尾崎 | Q37: ６の自転車を中野１へ移動
A38: 37 | B38: 45987 | C38: 0.6172338 | D38: 尾崎 | F38: 牛渕１ | G38: 修理 | H38: 完了 | I38: /appsheet/rireki_photo/37.登録画像１－１.055108.jpg | K38: 電気が弱い | L38: 45987 | M38: 0.61736111 | N38: 尾崎 | O38: 履歴_Images/37.対応画像１ー２.055108.jpg | Q38: 電球が切れているため、電球交換
A39: 38 | B39: 45988 | C39: 0.52805556 | D39: 池内 | E39: 07013653 | F39: 牛渕２ | G39: 病院 | H39: 完了 | K39: 口の周りが荒れて痛みがあり皮膚科に行きたいと申し出。１人で行くのは不安なので着いてきてほしいとのこと。11/29 9:00八木皮膚科受診予定 | L39: 45990 | N39: 池内 | Q39: 歯磨き粉や、リップクリームが合わないのかも？ワセリン100パーのものを使うこと、口の周りを拭きすぎないことを指導された。塗り薬を1～2週間使って治らなければ再受診。
A40: 39 | B40: 45988 | C40: 0.84733796 | D40: 池内 | E40: 07013649 | G40: 退職 | H40: 完了 | I40: /appsheet/rireki_photo/39.登録画像１－１.112134.jpg | K40: デラよりLINEで退職したい申し出あり。いつ頃退職して帰国したいのかヒアリングする。有給残12日（12月付与）と４時間 | L40: 45990 | N40: 池内 | O40: /appsheet/rireki_photo/39.対応画像１ー２.013036.jpg | Q40: デラと話し、退職希望日は1/20だが、1月が厳しいなら2/20でも構わない。とりあえず体調がよくないので帰国したいとのこと。新開さんへLINE済。→新開さんより2/20退職で。とのこと。デラにLINE済
A41: 40 | B41: 45991 | C41: 0.35028935 | D41: 尾崎 | E41: 07013655 | G41: 一時帰国 | H41: 完了 | I41: /appsheet/rireki_photo/40.登録画像１－１.232819.jpg | J41: /appsheet/rireki_photo/40.登録画像１－２.232819.jpg | K41: 母親が手術のため、一時帰国を希望、12/14～1/10まで | L41: 45991 | M41: 0.79722222 | N41: 尾崎 | O41: 履歴_Images/40.対応画像１ー２.230924.jpg | Q41: 新開工場長相談済。12/14～1/10まで。有給等後日と伝える。→12/2有給提出したとのこと | R41: 46005 | S41: 0.37833333 | T41: 尾崎 | W41: 松山空港送迎完了
A42: 41 | B42: 45992 | C42: 0.33150463 | D42: 尾崎 | E42: 07018614 | G42: 問合せ | H42: 完了 | K42: エヴィより、銀行のキャッシュカードが間違えてロックがかかったとのこと。 | L42: 45992 | N42: 池内 | Q42: 伊予銀富永様へ確認済。12/2に暗所番号変更手続き書類持ってきてくれる。 | R42: 45995 | T42: 池内 | W42: 大街道支店にてキャッシュカード即時発行。レギタへカードも渡し完了
A43: 42 | B43: 45911 | C43: 0.48986111 | D43: 尾崎 | E43: 07013663 | F43: 牛渕１別棟 | G43: 一時帰国 | H43: 完了 | K43: 新開工場長よりメルヴァ12/15～1/9帰国希望のラインあり。 | L43: 45994 | M43: 0.50208333 | N43: 池内 | O43: /appsheet/rireki_photo/42.対応画像１ー２.030538.jpg | P43: /appsheet/rireki_photo/42.対応画像１－２.030537.jpg | Q43: チケットにて日程確認。12/14～1/10一時帰国 | R43: 46005 | S43: 0.37773148 | T43: 尾崎 | W43: 松山空港送迎完了
A44: 43 | B44: 45993 | C44: 0.33072917 | D44: 尾崎 | E44: 07013667 | F44: ビレッジ3-501 | G44: 病院 | H44: 完了 | K44: 新開工場長より昨日掃除中に頭をぶつけ、仕事を続けてたが、その後駐輪場で倒れた。今日休んでおり、昼から男の子より病院へ行きたいと申出があったため、確認依頼。朝一確認すると伝える。 | L44: 45993 | M44: 0.45833333 | N44: 尾崎 | Q44: 現在、意識もしっかりしており、ご飯もさっき食べた。朝まではしんどかったが現在は大丈夫とのことで様子を見る。昨日１９時頃頭をぶつけ２２時頃退社。ライハンと一緒に自転車を押してかえった。本日は休みにし何か調子がおかしかったら連絡依頼。新開工場長連絡済。 | R44: 45994 | S44: 0.3680787 | T44: 池内 | U44: /appsheet/rireki_photo/43.対応画像２ー１.003909.jpg | W44: 体調は大丈夫と返信もあり、12/3も朝から出勤しているようなので、そのまま様子見。
A45: 44 | B45: 45993 | C45: 0.34652778 | D45: 尾崎 | E45: 07013654 | G45: 妊娠 | H45: 完了 | K45: 新開工場長より、妊娠したとの申し出あり。 | L45: 46058 | M45: 0.525 | N45: 尾崎 | Q45: チカと話す。家族帯同ビザに夫に資格変更してもらう。3/20退職にてスケジュール。出産予定は８月とのこと | R45: 46101 | S45: 0.54920139 | T45: 尾崎 | W45: 3/20退職
A46: 45 | B46: 45994 | C46: 0.68028935 | D46: 池内 | E46: 07013644 | F46: 牛渕２ | G46: 退職 | H46: 完了 | K46: 12/3に退職の申し出。帰国し、大学へ通いたいとのこと。本人は、2/20退職希望しているが、新開さんは3/20ではだめかとのこと。（12月に有給12日付与予定で計14日になる予定） | L46: 45996 | N46: 池内 | O46: /appsheet/rireki_photo/45.対応画像１ー２.072915.jpg | P46: /appsheet/rireki_photo/45.対応画像１－２.013015.jpg | Q46: 本人は3月には大学が始まるので2月退職を強く希望。新開さんへ了承をもらい、2/20退職で進める。
A47: 46 | B47: 45996 | C47: 0.95 | D47: 尾崎 | E47: 07018617 | F47: 牛渕１ | G47: 携帯 | H47: 完了 | K47: エヴィより12/6土曜日に携帯契約したい申し出。 | L47: 45997 | M47: 0.41666667 | N47: 尾崎 , 池内 | Q47: 牛渕より楽天へ。契約時、リヴァニ、ギム、ジラも来て契約。
A48: 47 | B48: 45998 | C48: 0.90614583 | D48: 尾崎 | E48: 07013632 | F48: ビレッジ4-501 | G48: 修理 | H48: 完了 | K48: 自転車パンクして修理の依頼あり。明日対応すると伝える | L48: 45999 | M48: 0.625 | N48: 尾崎 | O48: /appsheet/rireki_photo/47.対応画像１ー２.083045.jpg | P48: /appsheet/rireki_photo/47.対応画像１－２.083045.jpg | Q48: カドタ自転車にて前輪のブレーキと後輪交換。6,000円
A49: 48 | B49: 45997 | C49: 0.77837963 | D49: 尾崎 | E49: 07001608 | F49: アトム305 | G49: 修理 | H49: 完了 | I49: /appsheet/rireki_photo/48.登録画像１－１.094142.jpg | J49: /appsheet/rireki_photo/48.登録画像１－２.094142.jpg | K49: 天井から水が落ちてくる。蛍光灯が切れた | L49: 46001 | M49: 0.72222222 | N49: 尾崎 | O49: /appsheet/rireki_photo/48.対応画像１ー２.085452.jpg | P49: /appsheet/rireki_photo/48.対応画像１－２.085452.jpg | Q49: 蛍光灯交換済。水漏れは行った時には確認できず。
A50: 49 | B50: 46000 | C50: 0.41371528 | D50: 尾崎 | F50: ビレッジ2-502 , ビレッジ4-502 | G50: クレーム | H50: 完了 | K50: ビレッジ中野さんより、2-502と4-502の段ボールの出し方の指導依頼。段ボールは縛って出すことになってる。 | L50: 46000 | M50: 0.52916667 | N50: 尾崎 | Q50: アルバシタとプジャにLINEにて部屋の全員へ通知依頼
A51: 50 | B51: 45997 | C51: 0.625 | D51: 尾崎 | F51: アトム404 | G51: クレーム | H51: 完了 | K51: アトム404と604について、カンの出し方の指導依頼。ペットやプラスチックにカンが含まれている | L51: 46000 | M51: 0.50501157 | N51: 尾崎 | Q51: 昼礼時に全員に注意喚起
A52: 51 | B52: 46000 | C52: 0.49721065 | D52: 尾崎 | G52: クレーム | H52: 完了 | K52: 石崎さんより、アトム606の人より騒音のクレームあり。注意及び気を付けるよう依頼あり | L52: 46001 | M52: 0.50396991 | N52: 尾崎 | Q52: 昼礼後、注意喚起
A53: 52 | B53: 46000 | C53: 0.52439815 | D53: 池内 | E53: 07013631 | G53: 病院 | H53: 完了 | I53: /appsheet/rireki_photo/52.登録画像１－１.041311.jpg | K53: ナウファルより、レザが頭痛で休むので病院へ連れていってほしいと連絡あり。一人で行けないか確認中 | N53: 池内 | Q53: 風邪ではなく疲れからのようなので、様子見。
A54: 53 | B54: 46004 | C54: 0.87521991 | D54: 尾崎 | E54: 07013648 | F54: 牛渕２ | G54: 問合せ | H54: 完了 | K54: ナウファルより、インドネシアで洪水の災害で、家が浸水したと連絡あり。月曜日に確認すると返信 | L54: 46017 | M54: 0.51828704 | N54: 尾崎 | Q54: インドネシアで被害を受け５日間連絡が取れなく被害を受けたが、どうしようもないためとのことで終了
A55: 54 | B55: 46006 | C55: 0.56565972 | D55: 尾崎 | E55: 07013629 | G55: 問合せ | H55: 完了 | K55: ククより、妻を2/10～２ヶ月間、短期滞在ビザで呼びたい。一緒に生活したい。申請するために、住民票、納税、課税証明書を取得してほしい申し出。 | L55: 46007 | M55: 0.52140046 | N55: 尾崎 | Q55: 本人と面談。マンスリーマンションの説明を行い、ククの部屋にいるなら協力すると伝え、別途部屋を用意することはしないと伝える。短期滞在ビザの申請については協力すると伝える。 | R55: 46041 | S55: 0.35739583 | T55: 尾崎 | W55: 1/19入管へ特定技能１号として申請 | X55: 46108 | Z55: 尾崎 | AC55: 3/27入管より入国許可の通知が届く
A56: 55 | B56: 46006 | C56: 0.5940162 | D56: 池内 | E56: 17000007 | G56: 病院 | H56: 完了 | K56: 12/15 最近胃の不調がある。宮内工場長が朴さんへ病院へ連れていくよう連絡済 | L56: 46008 | N56: 池内 | Q56: 12/17朴さん同行で受診。胃カメラをし、12/23に再受診予定 | R56: 46014 | S56: 0.3852662 | T56: 尾崎 | W56: 朴さんより、病院に行って診察するも、特に問題なし。本人も納得とのことで終了。
A57: 56 | B57: 46006 | C57: 0.59596065 | D57: 池内 | E57: 07013601 | F57: ビレッジ4-505 | G57: 購入 | H57: 完了 | K57: H＆Cが用意した冷蔵庫が小さすぎるため、全然入れれなくて困っている。大きい冷蔵庫がほしいとのこと。尾崎さんへ相談 | N57: 池内 | Q57: 新しいものを購入するのは難しいが中古のものはあれば優先的に譲る。すぐの対応はできないと伝えている。
A58: 57 | B58: 46007 | C58: 0.34230324 | D58: 池内 | E58: 07013667 | F58: ビレッジ3-501 | G58: 病院 | H58: 完了 | I58: /appsheet/rireki_photo/57.登録画像１－１.231749.jpg | J58: /appsheet/rireki_photo/57.登録画像１－２.231749.jpg | K58: 頭が痛く、病院へ行きたい申し出あり。よしおか内科へ行けるか確認。１人で行けそうなので、先に行ってもらい、後で駆けつけるとLINE | L58: 46007 | M58: 0.4171412 | N58: 尾崎 | O58: /appsheet/rireki_photo/57.対応画像１ー２.235720.jpg | Q58: よしおか内科受診。現在、36.1度、はなみずのみの症状のため、症状抗生物質をもらい様子見。まだ体調が悪いため、通院予定。
A59: 58 | B59: 46008 | C59: 0.39694444 | D59: 池内 | E59: 07004405 | F59: アトム602 | G59: 病院 | H59: 完了 | K59: 12/17 頭痛で早退。薬あるということで、昼に様子見行く | L59: 46008 | M59: 0.56283565 | N59: 池内 , 渡部 | Q59: 部屋も見たが不在。
A60: 59 | B60: 46010 | C60: 0.35875 | D60: 尾崎 | E60: 07001605 | F60: アトム504 | G60: 修理 | H60: 完了 | I60: /appsheet/rireki_photo/59.登録画像１－１.233826.jpg | K60: 宮内工場長より電球交換の依頼。風呂の電球交換
A61: 60 | B61: 46010 | C61: 0.36857639 | D61: 池内 | E61: 07001423 | G61: 病院 | H61: 完了 | K61: 12/16に朴さんと婦人科受診。生理不順の改善が見られないため、12/23に検査結果が出る予定とのこと。引き続き朴さんと連携を取りながら様子見る。 | L61: 46014 | M61: 0.45289352 | N61: 尾崎 | Q61: 朴さんより、本日病院受診したが、１１月に生理が来てるとのことで、特に問題はないようだとのこと。２月までまだないようなら再度受診予定
A62: 61 | B62: 46010 | C62: 0.38038194 | D62: 池内 | E62: 07018630 | G62: 病院 | H62: 完了 | K62: ギムから頭痛と吐き気で休んでいる。と連絡あり。病院は自転車で行くのしんどいから行かないとのこと
A63: 62 | B63: 46010 | C63: 0.53143519 | D63: 尾崎 | E63: 07018623 | F63: 牛渕１ | G63: 病院 | H63: 完了 | K63: エヴィより、呼吸が１週間ほどしんどいので、原因がしりたい。土曜日に呼吸器内科受診予定 | L63: 46011 | N63: 池内 | Q63: カハリの病院の結果は異常はありませんでした。 ですが、背骨が少し曲がっていて姿勢が悪くなっているので、それのせいで息が苦しくなることがあるのかもしれません。 長時間同じ姿勢にならないように気をつけてみてください。とのこと。 | R63: 46016 | T63: 池内 | U63: /appsheet/rireki_photo/62.対応画像２ー１.232701.jpg | W63: ラストノからカハリ良くならない、痛いと言っているとのことで他院受診希望。12/27 11：30 眞柴消化器内科予約 | X63: 46018 | Z63: 池内 | AC63: 眞柴消化器内科へ受診。レントゲン、採血異常なし。息苦しさは休みの日にはならない。年末年始の休暇でしっかり体休めるようにつたえた。
A64: 63 | B64: 46010 | C64: 0.8827662 | D64: 池内 | E64: 07013665 | F64: ビレッジ2-502 | G64: 修理 | H64: 完了 | I64: /appsheet/rireki_photo/63.登録画像１－１.121300.jpg | K64: イナからガス使えなくなったとのこと。連絡来たのが夜なので、翌日20日に対応すると伝えた。 | L64: 46011 | M64: 0.37638889 | N64: 尾崎 | O64: /appsheet/rireki_photo/63.対応画像１ー２.001016.jpg | P64: /appsheet/rireki_photo/63.対応画像１－２.001016.jpg | Q64: 四国ガス燃料、990-1200へ連絡。ACの表示は長時間ガスを使用したため安全装置が働いて、止まったとのこと。鍵の開けて解除し、復旧。イナに解除方法伝える
A65: 64 | B65: 46010 | C65: 0.54166667 | D65: 渡部 | E65: 07001627 | G65: 帰国 | H65: 完了 | K65: 宮内工場長より、家庭の事情により2026/1/27より一時帰国もしくは退職の予定とのこと。 | L65: 46010 | M65: 0.54166667 | N65: 渡部 | R65: 46015 | S65: 0.57847222 | T65: 渡部 | W65: 宮内工場長より、1/24退職、1/24給料現金払い、1/25退寮 1/22、23有給使用 最終出勤日1/21 帰りの飛行機代は会社負担になるのか宮内工場長より確認してほしいとのこと。 | X65: 46047 | Y65: 0.52766204 | AC65: 1/25のバスにて関空へ
A66: 65 | B66: 46011 | C66: 0.5062963 | D66: 尾崎 | F66: 牛渕１ | G66: 修理 | H66: 完了 | I66: /appsheet/rireki_photo/65.登録画像１－１.030930.jpg | K66: 牛渕１のレンジの皿が割れた。皿を交換する | L66: 46013 | M66: 0.40814815 | N66: 尾崎 | Q66: 廃棄予定電子レンジより交換にて終了
A67: 66 | B67: 46011 | C67: 0.44722222 | D67: 尾崎 | E67: 07018631 | F67: 中野２ | G67: 携帯 | H67: 完了 | K67: 携帯契約したい申し出。12/27午前中に行きたい | L67: 46011 | M67: 0.69861111 | N67: 尾崎 | Q67: 楽天重信 10:00で予約 | S67: 0.47869213 | T67: 尾崎 | W67: 携帯契約で終了 070-9449-6583
A68: 67 | B68: 46011 | C68: 0.55820602 | D68: 尾崎 | E68: 07013625 | G68: 結婚 | H68: 申請中 | I68: /appsheet/rireki_photo/67.登録画像１－１.075345.jpg | K68: 新開工場長よりラティフとミャナが7/21～9/20まで結婚のため一時帰国希望のＬＩＮＥあり。 | L68: 46045 | M68: 0.53472222 | N68: 尾崎 | O68: /appsheet/rireki_photo/67.対応画像１ー２.055640.jpg | P68: /appsheet/rireki_photo/67.対応画像１－２.055640.jpg | Q68: チケット画面
A69: 68 | B69: 46013 | C69: 0.28462963 | D69: 尾崎 | E69: 07018616 | F69: 牛渕１ | G69: 修理 | H69: 完了 | I69: /appsheet/rireki_photo/68.登録画像１－１.215049.jpg | J69: /appsheet/rireki_photo/68.登録画像１－２.215049.jpg | K69: 自転車修理依頼 | L69: 46013 | M69: 0.44861111 | N69: 尾崎 | O69: /appsheet/rireki_photo/68.対応画像１ー２.074701.jpg | P69: /appsheet/rireki_photo/68.対応画像１－２.074701.jpg | Q69: カドタ自転車にて修理。2,600円
A70: 69 | B70: 46013 | C70: 0.35409722 | D70: 尾崎 | E70: 18001403 | F70: アトム605 | G70: 修理 | H70: 完了 | I70: /appsheet/rireki_photo/69.登録画像１－１.233325.jpg | J70: /appsheet/rireki_photo/69.登録画像１－２.233325.jpg | K70: 宮内工場長より昨日自転車で事故したとの報告あり。8:05に相手先に電話するも出ず。8:13朴さんに一報し、本人より事故の状況聞き取り依頼。 | L70: 46013 | M70: 0.98958333 | N70: 尾崎 | O70: /appsheet/rireki_photo/69.対応画像１ー２.075527.jpg | P70: /appsheet/rireki_photo/69.対応画像１－２.081445.jpg | Q70: 11:45相手の母親より連絡あり。090-3379-6981、山根さん、担当者などを送付いただいた。 | R70: 46014 | S70: 0.32600694 | T70: 尾崎 | U70: /appsheet/rireki_photo/69.対応画像２ー１.001324.jpg | V70: /appsheet/rireki_photo/69.対応画像２－２.053112.jpg | W70: シーに聞き取り（ダット通訳）写真の場所にてぶつかった、朴さんより、連絡をとるがシーより連絡がないとのこと。 | X70: 46106 | Z70: 尾崎 | AA70: /appsheet/rireki_photo/69.対応画像３ー１.002148.jpg | AB70: /appsheet/rireki_photo/69.対応画像３－２.002148.jpg | AC70: 3/25に2,600円の振込を行ったと連絡あり。 | AG70: /appsheet/rireki_photo/69.対応画像４ー１.002148.jpg
A71: 70 | B71: 46013 | C71: 0.47916667 | D71: 渡部 | E71: 07001616 | F71: アトム705 | G71: クレーム | H71: 完了 | K71: アトム606の方より、毎日騒音がひどいとのことでアトムへ怒鳴りこんできているとのこと。 | L71: 46013 | M71: 0.53125 | N71: 渡部 | Q71: ヒエンに気を付けるよう伝えた。ご主人、トゥーにも伝えてもらうようにした。 | R71: 46014 | S71: 0.3303125 | T71: 尾崎 | W71: ヒエンに聞き取り、夜が遅く料理をしている可能性があるため、再度、注意を依頼
A72: 71 | B72: 46014 | C72: 0.26388889 | D72: 尾崎 | E72: 07012625 07017701 | G72: 問合せ | H72: 完了 | I72: /appsheet/rireki_photo/71.登録画像１－１.232114.jpg | K72: 給料について問い合わせあり | L72: 46014 | M72: 0.34791667 | N72: 尾崎 | O72: /appsheet/rireki_photo/71.対応画像１ー２.232220.jpg | Q72: 新開工場長へLINEにて連絡。対応依頼。 | R72: 46017 | S72: 0.51741898 | T72: 尾崎 | W72: 新開工場長より説明を受け納得したとの回答あり
A73: 72 | B73: 46014 | C73: 0.82013889 | D73: 尾崎 | E73: 07013614 | G73: 一時帰国 , 結婚 | H73: 完了 | I73: /appsheet/rireki_photo/72.登録画像１－１.224426.jpg | K73: 新開工場長より、LINEにて、2025/4/20～6/3まで、自身の結婚のため一時帰国の申し出あり。また、次の特定２号の試験の申し出ありとのこと | L73: 46072 | M73: 0.51736111 | N73: 尾崎 | Q73: 連番 127 日付 2026/02/19 時間 12:39:07 登録者 尾崎 実習生 コフィファー ヌル コエリヤー View Ref (実習生) 申請区分 一時帰国 完了区分 申請中 登録記事 4/20～6/5帰国。在留カード更新、4/15頃行う | R73: 46093 | S73: 0.35696759 | T73: 尾崎 | W73: 3/12入管へ提出
A74: 73 | B74: 46015 | C74: 0.51377315 | D74: 尾崎 | E74: 07013631 | G74: 携帯 | H74: 完了 | I74: /appsheet/rireki_photo/73.登録画像１－１.032137.jpg | J74: /appsheet/rireki_photo/73.登録画像１－２.032137.jpg | K74: 楽天より弁護士を使ってメールあり、対応してほしいとのこと。市ヶ谷中央法律事務所 05031172527 | L74: 46015 | N74: 池内 | Q74: 弁護士事務所へ電話したが本人同席でないと対応できないと言われた。後日レザと改めて電話する | T74: 池内 | W74: レザ同席の元、弁護士事務所へ連絡。滞納分R7.7～10月分￥13,195。12/25レザからお金を預かり支払い済。
A75: 74 | B75: 46015 | C75: 0.51554398 | D75: 尾崎 | E75: 07018615 | F75: 牛渕１ | G75: 問合せ | H75: 完了 | K75: スハルより、サエと一緒に別棟に移っていいかの問い合わせ。ウフィック、ウイッティOKとのことで部屋を見て決めたい | L75: 46017 | M75: 0.51502315 | N75: 尾崎 | Q75: 別棟へ移動はいやとのことで、食堂の前に移る。ウィックに２名探すよう指示。
A76: 75 | B76: 46015 | C76: 0.52361111 | D76: 尾崎 | E76: 07013626 | F76: 中野２ | G76: 購入 | H76: 完了 | I76: /appsheet/rireki_photo/75.登録画像１－１.053631.jpg | K76: 中野２の自転車置場が、夜間暗いため電気を設置依頼 | L76: 46015 | M76: 0.60763889 | N76: 尾崎 | O76: /appsheet/rireki_photo/75.対応画像１ー２.053631.jpg | P76: /appsheet/rireki_photo/75.対応画像１－２.053631.jpg | Q76: ダイキにて購入し、仮設置 | R76: 46016 | S76: 0.43174769 | T76: 尾崎 | W76: 12/26にナウファルにて問題ないとの回答。
A77: 76 | B77: 46017 | C77: 0.54652778 | D77: 尾崎 | E77: 07011608 | G77: 問合せ | H77: 完了 | K77: チンや子供で大変なため、育児休暇を延長依頼。確認すると伝える | L77: 46017 | M77: 0.59946759 | N77: 尾崎 | Q77: 1/31まで延長にて回答、本人了承
A78: 77 | B78: 46025 | C78: 0.7309375 | D78: 尾崎 | E78: 07018616 | F78: 牛渕１ | G78: 問合せ | H78: 完了 | I78: /appsheet/rireki_photo/77.登録画像１－１.083652.jpg | J78: /appsheet/rireki_photo/77.登録画像１－２.083652.jpg | L78: 46025 | M78: 0.73125 | N78: 尾崎 | O78: /appsheet/rireki_photo/77.対応画像１ー２.083652.jpg | P78: /appsheet/rireki_photo/77.対応画像１－２.084647.jpg | Q78: 参加登録はしましたが、１人で参加はむずかしいので確認すること | R78: 46027 | S78: 0.55763889 | T78: 尾崎 | U78: /appsheet/rireki_photo/77.対応画像２ー１.042450.jpg | V78: /appsheet/rireki_photo/77.対応画像２－２.042450.jpg | W78: アイシャーも成人式出席のため、参加登録。東温市役所にも、２名で参加、連絡して問題ない回答
A79: 78 | B79: 46026 | C79: 0.64583333 | D79: 尾崎 | E79: 07018604 | F79: ビレッジ4-501 | G79: 病院 | H79: 完了 | I79: /appsheet/rireki_photo/78.登録画像１－１.080618.jpg | J79: /appsheet/rireki_photo/78.登録画像１－２.080618.jpg | K79: 明日、病院へ連れて行ってほしいと連絡あり。熱３８咳と喉が痛い症状。明日、よしおか内科予約し連絡する。朝８時までに症状報告依頼。サニアも同じ症状のため病院へ行きたい | L79: 46027 | M79: 0.48853009 | N79: 尾崎 | Q79: よしおか内科受診、リズキはインフルB、サニアは該当なし。サニアはインフルの薬でていないとのこと。 | R79: 46029 | S79: 0.61895833 | T79: 尾崎 | W79: リズキより薬の追加がほしいと連絡あり。よしおか内科に確認。４日分の薬と１０回分の咳止めを処方してもらい840円。
A80: 79 | B80: 46027 | C80: 0.25694444 | D80: 尾崎 | E80: 07013674 | F80: コーポ津吉2-4 | G80: 病院 | H80: 完了 | I80: /appsheet/rireki_photo/79.登録画像１－１.225855.jpg | K80: アリフより、マヤンとダナンが熱との連絡あり。 | L80: 46027 | M80: 0.49094907 | N80: 尾崎 | Q80: 本日の病院は雨等により無理とのことで、1/6(火曜日)10:30で再予約 | R80: 46028 | S80: 0.43809028 | T80: 池内 , 尾崎 | W80: 1/6よしおか内科受診。ダナンはインフルA。解熱すれば11日より勤務。マヤングは陰性で熱もないため、昼から勤務。
A81: 80 | B81: 46027 | C81: 0.36737269 | D81: 尾崎 | E81: 07013661 | F81: ビレッジ1-205 | G81: 修理 | H81: 完了 | I81: /appsheet/rireki_photo/80.登録画像１－１.235023.jpg | K81: 給湯器が使用できないとの申し出あり。管理人に確認すると伝える | L81: 46027 | M81: 0.48770833 | N81: 尾崎 | Q81: お湯が出たと報告あり。完了
A82: 81 | B82: 46028 | C82: 0.71391204 | D82: 池内 | E82: 07018605 | F82: 牛渕２ | G82: 病院 | H82: 完了 | K82: 5日くらい前から、頭痛、左胸あたりが痛み苦しくなる。吐き気あり。夜も寝れないなどの症状があり、病院へ行きたいとのこと。 | L82: 46028 | M82: 0.60430556 | N82: 池内 | Q82: 1/6くぼた呼吸器内科へ受診。症状を伝えたが尿検査、血圧測って終了。仮病じゃないかと言われ、吐き気の薬飲み処方。とりあえず、処方された薬飲んで様子見。 | R82: 46039 | T82: 池内 | W82: 1/17に病状確認。本人的に治ったとのこと。
A83: 82 | B83: 46028 | C83: 0.5341088 | D83: 尾崎 | E83: 07013640 | G83: 一時帰国 | H83: 完了 | I83: /appsheet/rireki_photo/82.登録画像１－１.231529.jpg | K83: 一時帰国の申出。3/12に変更～4/10までアンディニと一緒とのこと
A84: 83 | B84: 46029 | C84: 0.89174769 | D84: 尾崎 | E84: 07018607 | F84: 牛渕２ | G84: 病院 | H84: 完了 | I84: /appsheet/rireki_photo/83.登録画像１－１.122539.jpg | J84: /appsheet/rireki_photo/83.登録画像１－２.123809.jpg | K84: 手がぶつぶつができて痒いので病院へ行きたい申し出あり。新開工場長へLINE連絡済み | L84: 46030 | M84: 0.6046412 | N84: 池内 | Q84: 1/8八木皮膚科受診。両手の手の甲、両腕、両足にひどめの湿疹でかゆい。乾燥がひどいのが原因。塗り薬多めに貰い様子見てみる。
A85: 84 | B85: 46030 | C85: 0.28414352 | D85: 尾崎 | E85: 07013646 | F85: ビレッジ4-407 | G85: 病院 | H85: 完了 | I85: /appsheet/rireki_photo/84.登録画像１－１.215241.jpg | K85: 新開工場長より、月曜日1/5より指が少し腫れていると連絡あり。今週様子見て治らないようなら来週病院へ | L85: 46030 | M85: 0.50138889 | N85: 尾崎 | O85: /appsheet/rireki_photo/84.対応画像１ー２.080221.jpg | Q85: 左手中指、右手薬指が痛い、来週痛いようなら再度連絡依頼。→1/24（土）金澤整形受診 | R85: 46046 | S85: 0.45208333 | T85: 池内 | W85: 金澤受診。レントゲンでは異常はないが、リウマチの可能性もあるかもしれないので採血を実施。次回1/31に検査結果とリハビリ予定(ナナと二人で行くとのこと)
A86: 85 | B86: 46028 | C86: 0.51736111 | D86: 尾崎 | E86: 07013678 | F86: コーポ津吉1-6 | G86: 修理 | H86: 完了 | I86: /appsheet/rireki_photo/85.登録画像１－１.002700.jpg | K86: 冷蔵庫が冷えない申し出があり、確認に行くと冷蔵が出来ない様子 | L86: 46030 | M86: 0.45763889 | N86: 尾崎 | O86: /appsheet/rireki_photo/85.対応画像１ー２.080138.jpg | Q86: 冷えないため、専務に相談、2019年8月購入のため、購入相談、OK | R86: 46031 | S86: 0.5875 | T86: 尾崎 | U86: /appsheet/rireki_photo/85.対応画像２ー１.080702.jpg | W86: ケーズ電気にて購入、1/17土曜日配達 | X86: 46039 | Y86: 0.99375 | Z86: 尾崎 | AC86: ケーズ電気にて購入搬入
A87: 86 | B87: 46031 | C87: 0.61621528 | D87: 池内 | E87: 07001628 | F87: アトム402 | G87: 帰国 | H87: 申請中 | I87: /appsheet/rireki_photo/86.登録画像１－１.055902.jpg | K87: 宮内工場長より、ヌーの一時帰国6/15～8/2の連絡あり。（飛行機は6/16 9:20大阪発～8/1 7:50大阪着）
A88: 87 | B88: 46033 | C88: 0.80405093 | D88: 池内 | E88: 07013676 | F88: 中野３ | G88: 病院 | H88: 対応中 | I88: /appsheet/rireki_photo/87.登録画像１－１.102030.jpg | K88: ミャナより現在しばらくばね指で通院しているが、薬でも改善しないため、手術になるとのこと。1/17の朝に受診予定のために一緒に話を聞きに行くことにする。 | L88: 46039 | M88: 0.39114583 | N88: 池内 | Q88: 金澤より、日赤へ紹介状を送ってもらった。後日、日赤へいつ受診行くかなど連絡来る。引き続き池内対応します。→1/28 13:00～日赤 | R88: 46050 | S88: 0.55840278 | T88: 池内 | W88: 日赤の整形受診。ばね指の症状の、指の引っ掛かりが強い。今回は注射で痛み緩和の処置。1か月後に改善がなければ手術の日程を決めましょうという話になった。次回、2月25日(水)13:10～ | X88: 46078 | Z88: 池内 | AC88: 3/17 午前中手術 3/25抜糸 予定。新開工場長と大西さん連絡済み
A89: 88 | B89: 46034 | C89: 0.84168981 | D89: 尾崎 | E89: 07018616 | F89: 牛渕１ | G89: 修理 | H89: 完了 | I89: /appsheet/rireki_photo/88.登録画像１－１.111237.jpg | K89: 自転車のペダル修理依頼 | L89: 46035 | M89: 0.38263889 | N89: 尾崎 | O89: /appsheet/rireki_photo/88.対応画像１ー２.001235.jpg | P89: /appsheet/rireki_photo/88.対応画像１－２.001235.jpg | R89: 46039 | S89: 0.65902778 | T89: 尾崎 | W89: クランプを抜くには特殊な工具が必要なため、門田サイクルへ、月曜日まで預ける | X89: 46041 | Y89: 0.61041667 | Z89: 尾崎 | AA89: /appsheet/rireki_photo/88.対応画像３ー１.054033.jpg | AB89: /appsheet/rireki_photo/88.対応画像３－２.054033.jpg | AC89: 古い自転車の部品と交換。工賃2,000円
A90: 89 | B90: 46034 | C90: 0.8428125 | D90: 尾崎 | E90: 07013662 | G90: 修理 | H90: 完了 | I90: /appsheet/rireki_photo/89.登録画像１－１.111450.jpg | K90: 自転車のパンク修理依頼。会社にある様子 | L90: 46035 | M90: 0.53611111 | N90: 尾崎 | O90: /appsheet/rireki_photo/89.対応画像１ー２.035224.jpg | Q90: 修理終了
A91: 90 | B91: 46035 | C91: 0.51736111 | D91: 尾崎 | E91: 07013638 | G91: 病院 | H91: 完了 | K91: エカより、1/15午後、ニマを椿ウイメンズに一緒にいってほしいとの話があり。時間を連絡依頼 | L91: 46036 | M91: 0.82083333 | N91: 尾崎 | O91: /appsheet/rireki_photo/90.対応画像１ー２.124350.jpg | Q91: 明日の病院はなし。次回は自分で行くとの申し出
A92: 91 | B92: 46037 | C92: 0.41878472 | D92: 尾崎 | E92: 07011614 | F92: ビレッジ2-506 | G92: 病院 | H92: 完了 | I92: /appsheet/rireki_photo/91.登録画像１－１.010524.jpg | J92: /appsheet/rireki_photo/91.登録画像１－２.074303.jpg | K92: おやしらずがいたく歯医者にいくと連絡あり。あとで、病院の予約ずみの様子。グリーン歯科 9:00 | L92: 46039 | M92: 0.40208333 | N92: 尾崎 | Q92: おやしらずを抜く、なにもなければ、終了
A93: 92 | B93: 46038 | C93: 0.52609954 | D93: 池内 | E93: 07013644 | F93: 牛渕２ | G93: 病院 | H93: 完了 | K93: 1/16発熱で早退したと連絡あり。38度くらい。17日(土)に八木耳鼻咽喉科にて発熱外来受けれるようにこちらで病院の手配をする。病院へはインフル、コロナの検査希望をつたえた。予約制ではないので朝8：30～11：00までに受付するように伝えた。 | L93: 46039 | N93: 池内 | Q93: インフルA。発症日が1/16(金)で、1/21まで自宅療養。新開さんへ連絡済。特定1号保険は未加入
A94: 93 | B94: 46038 | C94: 0.95034722 | D94: 尾崎 | E94: 07018622 | F94: 牛渕１ | G94: 問合せ | H94: 対応中 | I94: /appsheet/rireki_photo/93.登録画像１－１.135003.jpg | J94: /appsheet/rireki_photo/93.登録画像１－２.135003.jpg | K94: エヴィより、牛渕に国民年金の紙が来たとのこと。確認すると伝える | L94: 46043 | M94: 0.89596065 | N94: 尾崎 | Q94: アイシャーからとの返事
A95: 94 | B95: 46039 | C95: 0.35645833 | D95: 尾崎 | E95: 07013662 | F95: ビレッジ4-502 | G95: 修理 | H95: 完了 | I95: /appsheet/rireki_photo/94.登録画像１－１.233403.jpg | K95: エヴィより連絡あり。 | L95: 46039 | M95: 0.39583333 | N95: 尾崎 | O95: /appsheet/rireki_photo/94.対応画像１ー２.022552.jpg | Q95: 一度取り外す、中野１へ | R95: 46039 | S95: 0.475 | T95: 尾崎 | U95: /appsheet/rireki_photo/94.対応画像２ー１.022552.jpg | V95: /appsheet/rireki_photo/94.対応画像２－２.022552.jpg | W95: 4-507ヒダヤットの部屋の分と交換する | X95: 46039 | Y95: 0.69861111 | Z95: 尾崎 | AA95: /appsheet/rireki_photo/94.対応画像３ー１.094705.jpg | AC95: パイプに穴が開いたため、パイプ交換
A96: 95 | B96: 46041 | C96: 0.44538194 | D96: 尾崎 | E96: 07001616 | F96: アトム705 | G96: クレーム | H96: 完了 | I96: /appsheet/rireki_photo/95.登録画像１－１.011729.jpg | J96: /appsheet/rireki_photo/95.登録画像１－２.011729.jpg | K96: アトム６０６の谷森さんより騒音についての問い合わせあり。 | L96: 46045 | M96: 0.45208333 | N96: 尾崎 | Q96: 谷森さんへ連絡して確認。現在のところ、穏やかな日々を送っているとのこと。何かあれば、連絡を依頼。
A97: 96 | B97: 46041 | C97: 0.88601852 | D97: 池内 | E97: 07018624 | F97: コーポ津吉2-4 | G97: 病院 | H97: 完了 | K97: 21時頃、ジラより電話があり、ベリが外で倒れ気絶したとのこと。ジラがコーポ津吉まで連れて帰った。新開工場長へ連絡をし、様子を見に行っていただく。 | L97: 46041 | M97: 0.9375 | N97: 池内 | O97: /appsheet/rireki_photo/96.対応画像１ー２.133221.jpg | Q97: 新開工場長よりべリの様子を見に行っていただき、意識あり、熱無し。薬飲ませて対応していただきました。翌朝、べリの様子を見に行き報告すると伝えました | R97: 46042 | S97: 0.70833333 | T97: 尾崎 | U97: /appsheet/rireki_photo/96.対応画像２ー１.225707.jpg | V97: /appsheet/rireki_photo/96.対応画像２－２.225706.jpg | W97: 平成脳神経外科受診、MRI、血液検査共に問題なし。血圧102/56で血圧が低いため、脳に血液が送られるにが低下したため、脳低血圧による失神ではないかとのこと。脱水症状もあるため、水分及び食事をきちんととるよう指示。専務より、２日は休んで体調整えるよう指示あり。山本統括にも報告済み | X97: 46045 | Z97: 池内 | AC97: 1/23より勤務している
A98: 97 | B98: 46042 | C98: 0.54181713 | D98: 尾崎 | E98: 07018614 | F98: 牛渕１ | G98: 問合せ | H98: 完了 | I98: /appsheet/rireki_photo/97.登録画像１－１.040204.jpg | K98: レギタより、オリフェアとノビと３人で下の部屋に移動したいと申請あり。 | L98: 46046 | M98: 0.525625 | N98: 尾崎 | Q98: ３人が移動したと報告あり
A99: 98 | B99: 46044 | C99: 0.39540509 | D99: 池内 | E99: 07001628 | F99: アトム402 | G99: 一時帰国 | H99: 完了 | I99: /appsheet/rireki_photo/98.登録画像１－１.003330.jpg | K99: 宮内工場長より、ヌーの一時帰国2/5～3/7の連絡あり。（飛行機は2/5 13：30広島発～3/7 12:00広島着）
A100: 99 | B100: 46045 | C100: 0.61177083 | D100: 尾崎 | E100: 07011610 | F100: ビレッジ1-303 | G100: 一時帰国 | H100: 完了 | K100: 3/1～家の建築のため一時帰国したい申出。新開工場長へ報告済みだが、本人より伝えるよう伝える。 | L100: 46059 | M100: 0.4150463 | N100: 尾崎 | O100: /appsheet/rireki_photo/99.対応画像１ー２.010017.jpg | P100: /appsheet/rireki_photo/99.対応画像１－２.012048.jpg | Q100: 飛行機チケット受領。2/26～4/14の飛行機（広島発着）2/25最終出勤、4/15勤務開始
...

Sheet 集計
N1: 通訳 | O1: ベトナム | P1: NGUYEN VAN HOI | Q1: グエン バン ホイ | R1: 070-1057-6789 | S1: 埼玉県さいたま市桜区西堀2-10-36-302号
A2: 区分 | B2: 区分人数 | C2: 男女区分 | D2: 男女人数 | E2: 国籍 | F2: 国籍人数 | G2: 実習生 | H2: 特定技能 | O2: インドネシア | P2: AO HENDARSO | Q2: アオ ヘンダルソ | R2: 090-9822-1984
A3: 本社 | B3: =COUNTIFS(管理表!C:C,A3,管理表!AH:AH,"<>退職") -> 35 | C3: 男 | D3: =COUNTIFS(管理表!C:C,A3,管理表!AH:AH,"<>退職",管理表!J:J,C3) -> 11 | E3: ベトナム | F3: =COUNTIFS(管理表!C:C,A3,管理表!AH:AH,"<>退職",管理表!J:J,C3,管理表!D:D,E3) -> 11 | G3: =COUNTIFS(管理表!C:C,A3,管理表!AH:AH,"<>退職",管理表!J:J,C3,管理表!D:D,E3,管理表!Q:Q,"*実習*") -> 4 | H3: =COUNTIFS(管理表!C:C,A3,管理表!AH:AH,"<>退職",管理表!J:J,C3,管理表!D:D,E3,管理表!Q:Q,"*特定*") -> 7
E4: インドネシア | F4: =COUNTIFS(管理表!C:C,A3,管理表!AH:AH,"<>退職",管理表!J:J,C3,管理表!D:D,E4) -> 0 | G4: =COUNTIFS(管理表!C:C,A3,管理表!AH:AH,"<>退職",管理表!J:J,C3,管理表!D:D,E4,管理表!Q:Q,"*実習*") -> 0 | H4: =COUNTIFS(管理表!C:C,A3,管理表!AH:AH,"<>退職",管理表!J:J,C3,管理表!D:D,E4,管理表!Q:Q,"*特定*") -> 0
C5: 女 | D5: =COUNTIFS(管理表!C:C,A3,管理表!AH:AH,"<>退職",管理表!J:J,C5) -> 24 | E5: ベトナム | F5: =COUNTIFS(管理表!C:C,A3,管理表!AH:AH,"<>退職",管理表!J:J,C5,管理表!D:D,E5) -> 24 | G5: =COUNTIFS(管理表!C:C,A3,管理表!AH:AH,"<>退職",管理表!J:J,C5,管理表!D:D,E5,管理表!Q:Q,"*実習*") -> 13 | H5: =COUNTIFS(管理表!C:C,A3,管理表!AH:AH,"<>退職",管理表!J:J,C5,管理表!D:D,E5,管理表!Q:Q,"*特定*") -> 11
E6: インドネシア | F6: =COUNTIFS(管理表!C:C,A3,管理表!AH:AH,"<>退職",管理表!J:J,C5,管理表!D:D,E6) -> 0 | G6: =COUNTIFS(管理表!C:C,A3,管理表!AH:AH,"<>退職",管理表!J:J,C5,管理表!D:D,E6,管理表!Q:Q,"*実習*") -> 0 | H6: =COUNTIFS(管理表!C:C,A3,管理表!AH:AH,"<>退職",管理表!J:J,C5,管理表!D:D,E6,管理表!Q:Q,"*特定*") -> 0
A7: 協同本社 | B7: =COUNTIFS(管理表!C:C,A7,管理表!AH:AH,"<>退職") -> 4 | C7: 男 | D7: =COUNTIFS(管理表!C:C,A7,管理表!AH:AH,"<>退職",管理表!J:J,C7) -> 2 | E7: ベトナム | F7: =COUNTIFS(管理表!C:C,A7,管理表!AH:AH,"<>退職",管理表!J:J,C7,管理表!D:D,E7) -> 2 | G7: =COUNTIFS(管理表!C:C,A7,管理表!AH:AH,"<>退職",管理表!J:J,C7,管理表!D:D,E7,管理表!Q:Q,"*実習*") -> 2 | H7: =COUNTIFS(管理表!C:C,A7,管理表!AH:AH,"<>退職",管理表!J:J,C7,管理表!D:D,E7,管理表!Q:Q,"*特定*") -> 0
E8: インドネシア | F8: =COUNTIFS(管理表!C:C,A7,管理表!AH:AH,"<>退職",管理表!J:J,C7,管理表!D:D,E8) -> 0 | G8: =COUNTIFS(管理表!C:C,A7,管理表!AH:AH,"<>退職",管理表!J:J,C7,管理表!D:D,E8,管理表!Q:Q,"*実習*") -> 0 | H8: =COUNTIFS(管理表!C:C,A7,管理表!AH:AH,"<>退職",管理表!J:J,C7,管理表!D:D,E8,管理表!Q:Q,"*特定*") -> 0
C9: 女 | D9: =COUNTIFS(管理表!C:C,A7,管理表!AH:AH,"<>退職",管理表!J:J,C9) -> 2 | E9: ベトナム | F9: =COUNTIFS(管理表!C:C,A7,管理表!AH:AH,"<>退職",管理表!J:J,C9,管理表!D:D,E9) -> 2 | G9: =COUNTIFS(管理表!C:C,A7,管理表!AH:AH,"<>退職",管理表!J:J,C9,管理表!D:D,E9,管理表!Q:Q,"*実習*") -> 2 | H9: =COUNTIFS(管理表!C:C,A7,管理表!AH:AH,"<>退職",管理表!J:J,C9,管理表!D:D,E9,管理表!Q:Q,"*特定*") -> 0
E10: インドネシア | F10: =COUNTIFS(管理表!C:C,A7,管理表!AH:AH,"<>退職",管理表!J:J,C9,管理表!D:D,E10) -> 0 | G10: =COUNTIFS(管理表!C:C,A7,管理表!AH:AH,"<>退職",管理表!J:J,C9,管理表!D:D,E10,管理表!Q:Q,"*実習*") -> 0 | H10: =COUNTIFS(管理表!C:C,A7,管理表!AH:AH,"<>退職",管理表!J:J,C9,管理表!D:D,E10,管理表!Q:Q,"*特定*") -> 0
A11: 本社小計 | B11: =B3+B7 -> 39 | C11: 男 | D11: =D3+D7 -> 13 | E11: ベトナム | F11: =F3+F7 -> 13 | G11: =G3+G7 -> 6 | H11: =H3+H7 -> 7
E12: インドネシア | F12: =F4+F8 -> 0 | G12: =G4+G8 -> 0 | H12: =H4+H8 -> 0
C13: 女 | D13: =D5+D9 -> 26 | E13: ベトナム | F13: =F5+F9 -> 26 | G13: =G5+G9 -> 15 | H13: =H5+H9 -> 11
E14: インドネシア | F14: =F6+F10 -> 0 | G14: =G6+G10 -> 0 | H14: =H6+H10 -> 0
A15: 津吉 | B15: =COUNTIFS(管理表!C:C,A15,管理表!AH:AH,"<>退職") -> 109 | C15: 男 | D15: =COUNTIFS(管理表!C:C,A15,管理表!AH:AH,"<>退職",管理表!J:J,C15) -> 33 | E15: ベトナム | F15: =COUNTIFS(管理表!C:C,A15,管理表!AH:AH,"<>退職",管理表!J:J,C15,管理表!D:D,E15) -> 2 | G15: =COUNTIFS(管理表!C:C,A15,管理表!AH:AH,"<>退職",管理表!J:J,C15,管理表!D:D,E15,管理表!Q:Q,"*実習*") -> 0 | H15: =COUNTIFS(管理表!C:C,A15,管理表!AH:AH,"<>退職",管理表!J:J,C15,管理表!D:D,E15,管理表!Q:Q,"*特定*") -> 2
E16: インドネシア | F16: =COUNTIFS(管理表!C:C,A15,管理表!AH:AH,"<>退職",管理表!J:J,C15,管理表!D:D,E16) -> 31 | G16: =COUNTIFS(管理表!C:C,A15,管理表!AH:AH,"<>退職",管理表!J:J,C15,管理表!D:D,E16,管理表!Q:Q,"*実習*") -> 0 | H16: =COUNTIFS(管理表!C:C,A15,管理表!AH:AH,"<>退職",管理表!J:J,C15,管理表!D:D,E16,管理表!Q:Q,"*特定*") -> 31
C17: 女 | D17: =COUNTIFS(管理表!C:C,A15,管理表!AH:AH,"<>退職",管理表!J:J,C17) -> 76 | E17: ベトナム | F17: =COUNTIFS(管理表!C1:C1024,A15,管理表!AH:AH,"<>退職",管理表!J:J,C17,管理表!D:D,E17) -> #VALUE! | G17: =COUNTIFS(管理表!C:C,A15,管理表!AH:AH,"<>退職",管理表!J:J,C17,管理表!D:D,E17,管理表!Q:Q,"*実習*") -> 0 | H17: =COUNTIFS(管理表!C:C,A15,管理表!AH:AH,"<>退職",管理表!J:J,C17,管理表!D:D,E17,管理表!Q:Q,"*特定*") -> 8
E18: インドネシア | F18: =COUNTIFS(管理表!C:C,A15,管理表!AH:AH,"<>退職",管理表!J:J,C17,管理表!D:D,E18) -> 68 | G18: =COUNTIFS(管理表!C:C,A15,管理表!AH:AH,"<>退職",管理表!J:J,C17,管理表!D:D,E18,管理表!Q:Q,"*実習*") -> 0 | H18: =COUNTIFS(管理表!C:C,A15,管理表!AH:AH,"<>退職",管理表!J:J,C17,管理表!D:D,E18,管理表!Q:Q,"*特定*") -> 68
A19: 合計 | B19: =B3+B7+B15 -> 148 | C19: 男 | D19: =D3+D7+D15 -> 46 | E19: ベトナム | F19: =F3+F7+F15 -> 15 | G19: =G3+G7+G15 -> 6 | H19: =H3+H7+H15 -> 9 | N19: 5211
E20: インドネシア | F20: =F4+F8+F16 -> 31 | G20: =G4+G8+G16 -> 0 | H20: =H4+H8+H16 -> 31
C21: 女 | D21: =D5+D9+D17 -> 102 | E21: ベトナム | F21: =F5+F9+F17 -> #VALUE! | G21: =G5+G9+G17 -> 15 | H21: =H5+H9+H17 -> 19 | K21: 松山市末広町 | L21: ７９０－００２３
E22: インドネシア | F22: =F6+F10+F18 -> 68 | G22: =G6+G10+G18 -> 0 | H22: =H6+H10+H18 -> 68 | K22: 松山市中野町 | L22: ７９１－１１２１
A24: 区分 | B24: 区分人数 | C24: 男女区分 | D24: 男女人数 | E24: 国籍 | F24: 国籍人数 | G24: 実習生 | H24: 特定技能 | I24: 本社 | J24: 協同本社 | K24: 津吉
A25: 関東食肉 | B25: =COUNTIFS(管理表!N:N,A25,管理表!AH:AH,"<>退職") -> 9 | C25: 男 | D25: =COUNTIFS(管理表!N:N,A25,管理表!AH:AH,"<>退職",管理表!J:J,C25) -> 2 | E25: ベトナム | F25: =COUNTIFS(管理表!N:N,A25,管理表!AH:AH,"<>退職",管理表!J:J,C25,管理表!D:D,E25) -> 2 | G25: =COUNTIFS(管理表!N:N,A25,管理表!AH:AH,"<>退職",管理表!J:J,C25,管理表!D:D,E25,管理表!Q:Q,"*実習*") -> 2 | H25: =COUNTIFS(管理表!N:N,A25,管理表!AH:AH,"<>退職",管理表!J:J,C25,管理表!D:D,E25,管理表!Q:Q,"*特定*") -> 0 | I25: =COUNTIFS(管理表!N:N,A25,管理表!AH:AH,"<>退職",管理表!J:J,C25,管理表!D:D,E25,管理表!C:C,"本社") -> 2 | J25: =COUNTIFS(管理表!N:N,A25,管理表!AH:AH,"<>退職",管理表!J:J,C25,管理表!D:D,E25,管理表!C:C,"協同本社") -> 0 | K25: =COUNTIFS(管理表!N:N,A25,管理表!AH:AH,"<>退職",管理表!J:J,C25,管理表!D:D,E25,管理表!C:C,"津吉") -> 0
E26: インドネシア | F26: =COUNTIFS(管理表!N:N,A25,管理表!AH:AH,"<>退職",管理表!J:J,C25,管理表!D:D,E26) -> 0 | G26: =COUNTIFS(管理表!N:N,A25,管理表!AH:AH,"<>退職",管理表!J:J,C25,管理表!D:D,E26,管理表!Q:Q,"*実習*") -> 0 | H26: =COUNTIFS(管理表!N:N,A25,管理表!AH:AH,"<>退職",管理表!J:J,C25,管理表!D:D,E26,管理表!Q:Q,"*特定*") -> 0 | I26: =COUNTIFS(管理表!N:N,A25,管理表!AH:AH,"<>退職",管理表!J:J,C25,管理表!D:D,E26,管理表!C:C,"本社") -> 0 | J26: =COUNTIFS(管理表!N:N,A25,管理表!AH:AH,"<>退職",管理表!J:J,C25,管理表!D:D,E26,管理表!C:C,"協同本社") -> 0 | K26: =COUNTIFS(管理表!N:N,A25,管理表!AH:AH,"<>退職",管理表!J:J,C25,管理表!D:D,E26,管理表!C:C,"津吉") -> 0
C27: 女 | D27: =COUNTIFS(管理表!N:N,A25,管理表!AH:AH,"<>退職",管理表!J:J,C27) -> 7 | E27: ベトナム | F27: =COUNTIFS(管理表!N:N,A25,管理表!AH:AH,"<>退職",管理表!J:J,C27,管理表!D:D,E27) -> 7 | G27: =COUNTIFS(管理表!N:N,A25,管理表!AH:AH,"<>退職",管理表!J:J,C27,管理表!D:D,E27,管理表!Q:Q,"*実習*") -> 7 | H27: =COUNTIFS(管理表!N:N,A25,管理表!AH:AH,"<>退職",管理表!J:J,C27,管理表!D:D,E27,管理表!Q:Q,"*特定*") -> 0 | I27: =COUNTIFS(管理表!N:N,A25,管理表!AH:AH,"<>退職",管理表!J:J,C27,管理表!D:D,E27,管理表!C:C,"本社") -> 7 | J27: =COUNTIFS(管理表!N:N,A25,管理表!AH:AH,"<>退職",管理表!J:J,C27,管理表!D:D,E27,管理表!C:C,"協同本社") -> 0 | K27: =COUNTIFS(管理表!N:N,A25,管理表!AH:AH,"<>退職",管理表!J:J,C27,管理表!D:D,E27,管理表!C:C,"津吉") -> 0
E28: インドネシア | F28: =COUNTIFS(管理表!N:N,A25,管理表!AH:AH,"<>退職",管理表!J:J,C27,管理表!D:D,E28) -> 0 | G28: =COUNTIFS(管理表!N:N,A25,管理表!AH:AH,"<>退職",管理表!J:J,C27,管理表!D:D,E28,管理表!Q:Q,"*実習*") -> 0 | H28: =COUNTIFS(管理表!N:N,A25,管理表!AH:AH,"<>退職",管理表!J:J,C27,管理表!D:D,E28,管理表!Q:Q,"*特定*") -> 0 | I28: =COUNTIFS(管理表!N:N,A25,管理表!AH:AH,"<>退職",管理表!J:J,C27,管理表!D:D,E28,管理表!C:C,"本社") -> 0 | J28: =COUNTIFS(管理表!N:N,A25,管理表!AH:AH,"<>退職",管理表!J:J,C27,管理表!D:D,E28,管理表!C:C,"協同本社") -> 0 | K28: =COUNTIFS(管理表!N:N,A25,管理表!AH:AH,"<>退職",管理表!J:J,C27,管理表!D:D,E28,管理表!C:C,"津吉") -> 0
A29: デルタ四国 | B29: =COUNTIFS(管理表!N:N,A29,管理表!AH:AH,"<>退職") -> 3 | C29: 男 | D29: =COUNTIFS(管理表!N:N,A29,管理表!AH:AH,"<>退職",管理表!J:J,C29) -> 1 | E29: ベトナム | F29: =COUNTIFS(管理表!N:N,A29,管理表!AH:AH,"<>退職",管理表!J:J,C29,管理表!D:D,E29) -> 1 | G29: =COUNTIFS(管理表!N:N,A29,管理表!AH:AH,"<>退職",管理表!J:J,C29,管理表!D:D,E29,管理表!Q:Q,"*実習*") -> 0 | H29: =COUNTIFS(管理表!N:N,A29,管理表!AH:AH,"<>退職",管理表!J:J,C29,管理表!D:D,E29,管理表!Q:Q,"*特定*") -> 1 | I29: =COUNTIFS(管理表!N:N,A29,管理表!AH:AH,"<>退職",管理表!J:J,C29,管理表!D:D,E29,管理表!C:C,"本社") -> 0 | J29: =COUNTIFS(管理表!N:N,A29,管理表!AH:AH,"<>退職",管理表!J:J,C29,管理表!D:D,E29,管理表!C:C,"協同本社") -> 0 | K29: =COUNTIFS(管理表!N:N,A29,管理表!AH:AH,"<>退職",管理表!J:J,C29,管理表!D:D,E29,管理表!C:C,"津吉") -> 1
E30: インドネシア | F30: =COUNTIFS(管理表!N:N,A29,管理表!AH:AH,"<>退職",管理表!J:J,C29,管理表!D:D,E30) -> 0 | G30: =COUNTIFS(管理表!N:N,A29,管理表!AH:AH,"<>退職",管理表!J:J,C29,管理表!D:D,E30,管理表!Q:Q,"*実習*") -> 0 | H30: =COUNTIFS(管理表!N:N,A29,管理表!AH:AH,"<>退職",管理表!J:J,C29,管理表!D:D,E30,管理表!Q:Q,"*特定*") -> 0 | I30: =COUNTIFS(管理表!N:N,A29,管理表!AH:AH,"<>退職",管理表!J:J,C29,管理表!D:D,E30,管理表!C:C,"本社") -> 0 | J30: =COUNTIFS(管理表!N:N,A29,管理表!AH:AH,"<>退職",管理表!J:J,C29,管理表!D:D,E30,管理表!C:C,"協同本社") -> 0 | K30: =COUNTIFS(管理表!N:N,A29,管理表!AH:AH,"<>退職",管理表!J:J,C29,管理表!D:D,E30,管理表!C:C,"津吉") -> 0
C31: 女 | D31: =COUNTIFS(管理表!N:N,A29,管理表!AH:AH,"<>退職",管理表!J:J,C31) -> 2 | E31: ベトナム | F31: =COUNTIFS(管理表!N:N,A29,管理表!AH:AH,"<>退職",管理表!J:J,C31,管理表!D:D,E31) -> 2 | G31: =COUNTIFS(管理表!N:N,A29,管理表!AH:AH,"<>退職",管理表!J:J,C31,管理表!D:D,E31,管理表!Q:Q,"*実習*") -> 0 | H31: =COUNTIFS(管理表!N:N,A29,管理表!AH:AH,"<>退職",管理表!J:J,C31,管理表!D:D,E31,管理表!Q:Q,"*特定*") -> 2 | I31: =COUNTIFS(管理表!N:N,A29,管理表!AH:AH,"<>退職",管理表!J:J,C31,管理表!D:D,E31,管理表!C:C,"本社") -> 0 | J31: =COUNTIFS(管理表!N:N,A29,管理表!AH:AH,"<>退職",管理表!J:J,C31,管理表!D:D,E31,管理表!C:C,"協同本社") -> 0 | K31: =COUNTIFS(管理表!N:N,A29,管理表!AH:AH,"<>退職",管理表!J:J,C31,管理表!D:D,E31,管理表!C:C,"津吉") -> 2
E32: インドネシア | F32: =COUNTIFS(管理表!N:N,A29,管理表!AH:AH,"<>退職",管理表!J:J,C31,管理表!D:D,E32) -> 0 | G32: =COUNTIFS(管理表!N:N,A29,管理表!AH:AH,"<>退職",管理表!J:J,C31,管理表!D:D,E32,管理表!Q:Q,"*実習*") -> 0 | H32: =COUNTIFS(管理表!N:N,A29,管理表!AH:AH,"<>退職",管理表!J:J,C31,管理表!D:D,E32,管理表!Q:Q,"*特定*") -> 0 | I32: =COUNTIFS(管理表!N:N,A29,管理表!AH:AH,"<>退職",管理表!J:J,C31,管理表!D:D,E32,管理表!C:C,"本社") -> 0 | J32: =COUNTIFS(管理表!N:N,A29,管理表!AH:AH,"<>退職",管理表!J:J,C31,管理表!D:D,E32,管理表!C:C,"協同本社") -> 0 | K32: =COUNTIFS(管理表!N:N,A29,管理表!AH:AH,"<>退職",管理表!J:J,C31,管理表!D:D,E32,管理表!C:C,"津吉") -> 0
A33: 中四国 | B33: =COUNTIFS(管理表!N:N,A33,管理表!AH:AH,"<>退職") -> 37 | C33: 男 | D33: =COUNTIFS(管理表!N:N,A33,管理表!AH:AH,"<>退職",管理表!J:J,C33) -> 12 | E33: ベトナム | F33: =COUNTIFS(管理表!N:N,A33,管理表!AH:AH,"<>退職",管理表!J:J,C33,管理表!D:D,E33) -> 12 | G33: =COUNTIFS(管理表!N:N,A33,管理表!AH:AH,"<>退職",管理表!J:J,C33,管理表!D:D,E33,管理表!Q:Q,"*実習*") -> 4 | H33: =COUNTIFS(管理表!N:N,A33,管理表!AH:AH,"<>退職",管理表!J:J,C33,管理表!D:D,E33,管理表!Q:Q,"*特定*") -> 8 | I33: =COUNTIFS(管理表!N:N,A33,管理表!AH:AH,"<>退職",管理表!J:J,C33,管理表!D:D,E33,管理表!C:C,"本社") -> 9 | J33: =COUNTIFS(管理表!N:N,A33,管理表!AH:AH,"<>退職",管理表!J:J,C33,管理表!D:D,E33,管理表!C:C,"協同本社") -> 2 | K33: =COUNTIFS(管理表!N:N,A33,管理表!AH:AH,"<>退職",管理表!J:J,C33,管理表!D:D,E33,管理表!C:C,"津吉") -> 1
E34: インドネシア | F34: =COUNTIFS(管理表!N:N,A33,管理表!AH:AH,"<>退職",管理表!J:J,C33,管理表!D:D,E34) -> 0 | G34: =COUNTIFS(管理表!N:N,A33,管理表!AH:AH,"<>退職",管理表!J:J,C33,管理表!D:D,E34,管理表!Q:Q,"*実習*") -> 0 | H34: =COUNTIFS(管理表!N:N,A33,管理表!AH:AH,"<>退職",管理表!J:J,C33,管理表!D:D,E34,管理表!Q:Q,"*特定*") -> 0 | I34: =COUNTIFS(管理表!N:N,A33,管理表!AH:AH,"<>退職",管理表!J:J,C33,管理表!D:D,E34,管理表!C:C,"本社") -> 0 | J34: =COUNTIFS(管理表!N:N,A33,管理表!AH:AH,"<>退職",管理表!J:J,C33,管理表!D:D,E34,管理表!C:C,"協同本社") -> 0 | K34: =COUNTIFS(管理表!N:N,A33,管理表!AH:AH,"<>退職",管理表!J:J,C33,管理表!D:D,E34,管理表!C:C,"津吉") -> 0
C35: 女 | D35: =COUNTIFS(管理表!N:N,A33,管理表!AH:AH,"<>退職",管理表!J:J,C35) -> 25 | E35: ベトナム | F35: =COUNTIFS(管理表!N:N,A33,管理表!AH:AH,"<>退職",管理表!J:J,C35,管理表!D:D,E35) -> 25 | G35: =COUNTIFS(管理表!N:N,A33,管理表!AH:AH,"<>退職",管理表!J:J,C35,管理表!D:D,E35,管理表!Q:Q,"*実習*") -> 8 | H35: =COUNTIFS(管理表!N:N,A33,管理表!AH:AH,"<>退職",管理表!J:J,C35,管理表!D:D,E35,管理表!Q:Q,"*特定*") -> 17 | I35: =COUNTIFS(管理表!N:N,A33,管理表!AH:AH,"<>退職",管理表!J:J,C35,管理表!D:D,E35,管理表!C:C,"本社") -> 17 | J35: =COUNTIFS(管理表!N:N,A33,管理表!AH:AH,"<>退職",管理表!J:J,C35,管理表!D:D,E35,管理表!C:C,"協同本社") -> 2 | K35: =COUNTIFS(管理表!N:N,A33,管理表!AH:AH,"<>退職",管理表!J:J,C35,管理表!D:D,E35,管理表!C:C,"津吉") -> 6
E36: インドネシア | F36: =COUNTIFS(管理表!N:N,A33,管理表!AH:AH,"<>退職",管理表!J:J,C35,管理表!D:D,E36) -> 0 | G36: =COUNTIFS(管理表!N:N,A33,管理表!AH:AH,"<>退職",管理表!J:J,C35,管理表!D:D,E36,管理表!Q:Q,"*実習*") -> 0 | H36: =COUNTIFS(管理表!N:N,A33,管理表!AH:AH,"<>退職",管理表!J:J,C35,管理表!D:D,E36,管理表!Q:Q,"*特定*") -> 0 | I36: =COUNTIFS(管理表!N:N,A33,管理表!AH:AH,"<>退職",管理表!J:J,C35,管理表!D:D,E36,管理表!C:C,"本社") -> 0 | J36: =COUNTIFS(管理表!N:N,A33,管理表!AH:AH,"<>退職",管理表!J:J,C35,管理表!D:D,E36,管理表!C:C,"協同本社") -> 0 | K36: =COUNTIFS(管理表!N:N,A33,管理表!AH:AH,"<>退職",管理表!J:J,C35,管理表!D:D,E36,管理表!C:C,"津吉") -> 0
A37: H&C | B37: =COUNTIFS(管理表!N:N,A37,管理表!AH:AH,"<>退職") -> 77 | C37: 男 | D37: =COUNTIFS(管理表!N:N,A37,管理表!AH:AH,"<>退職",管理表!J:J,C37) -> 24 | E37: ベトナム | F37: =COUNTIFS(管理表!N:N,A37,管理表!AH:AH,"<>退職",管理表!J:J,C37,管理表!D:D,E37) -> 0 | G37: =COUNTIFS(管理表!N:N,A37,管理表!AH:AH,"<>退職",管理表!J:J,C37,管理表!D:D,E37,管理表!Q:Q,"*実習*") -> 0 | H37: =COUNTIFS(管理表!N:N,A37,管理表!AH:AH,"<>退職",管理表!J:J,C37,管理表!D:D,E37,管理表!Q:Q,"*特定*") -> 0 | I37: =COUNTIFS(管理表!N:N,A37,管理表!AH:AH,"<>退職",管理表!J:J,C37,管理表!D:D,E37,管理表!C:C,"本社") -> 0 | J37: =COUNTIFS(管理表!N:N,A37,管理表!AH:AH,"<>退職",管理表!J:J,C37,管理表!D:D,E37,管理表!C:C,"協同本社") -> 0 | K37: =COUNTIFS(管理表!N:N,A37,管理表!AH:AH,"<>退職",管理表!J:J,C37,管理表!D:D,E37,管理表!C:C,"津吉") -> 0
E38: インドネシア | F38: =COUNTIFS(管理表!N:N,A37,管理表!AH:AH,"<>退職",管理表!J:J,C37,管理表!D:D,E38) -> 24 | G38: =COUNTIFS(管理表!N:N,A37,管理表!AH:AH,"<>退職",管理表!J:J,C37,管理表!D:D,E38,管理表!Q:Q,"*実習*") -> 0 | H38: =COUNTIFS(管理表!N:N,A37,管理表!AH:AH,"<>退職",管理表!J:J,C37,管理表!D:D,E38,管理表!Q:Q,"*特定*") -> 24 | I38: =COUNTIFS(管理表!N:N,A37,管理表!AH:AH,"<>退職",管理表!J:J,C37,管理表!D:D,E38,管理表!C:C,"本社") -> 0 | J38: =COUNTIFS(管理表!N:N,A37,管理表!AH:AH,"<>退職",管理表!J:J,C37,管理表!D:D,E38,管理表!C:C,"協同本社") -> 0 | K38: =COUNTIFS(管理表!N:N,A37,管理表!AH:AH,"<>退職",管理表!J:J,C37,管理表!D:D,E38,管理表!C:C,"津吉") -> 24
C39: 女 | D39: =COUNTIFS(管理表!N:N,A37,管理表!AH:AH,"<>退職",管理表!J:J,C39) -> 53 | E39: ベトナム | F39: =COUNTIFS(管理表!N:N,A37,管理表!AH:AH,"<>退職",管理表!J:J,C39,管理表!D:D,E39) -> 0 | G39: =COUNTIFS(管理表!N:N,A37,管理表!AH:AH,"<>退職",管理表!J:J,C39,管理表!D:D,E39,管理表!Q:Q,"*実習*") -> 0 | H39: =COUNTIFS(管理表!N:N,A37,管理表!AH:AH,"<>退職",管理表!J:J,C39,管理表!D:D,E39,管理表!Q:Q,"*特定*") -> 0 | I39: =COUNTIFS(管理表!N:N,A37,管理表!AH:AH,"<>退職",管理表!J:J,C39,管理表!D:D,E39,管理表!C:C,"本社") -> 0 | J39: =COUNTIFS(管理表!N:N,A37,管理表!AH:AH,"<>退職",管理表!J:J,C39,管理表!D:D,E39,管理表!C:C,"協同本社") -> 0 | K39: =COUNTIFS(管理表!N:N,A37,管理表!AH:AH,"<>退職",管理表!J:J,C39,管理表!D:D,E39,管理表!C:C,"津吉") -> 0
E40: インドネシア | F40: =COUNTIFS(管理表!N:N,A37,管理表!AH:AH,"<>退職",管理表!J:J,C39,管理表!D:D,E40) -> 53 | G40: =COUNTIFS(管理表!N:N,A37,管理表!AH:AH,"<>退職",管理表!J:J,C39,管理表!D:D,E40,管理表!Q:Q,"*実習*") -> 0 | H40: =COUNTIFS(管理表!N:N,A37,管理表!AH:AH,"<>退職",管理表!J:J,C39,管理表!D:D,E40,管理表!Q:Q,"*特定*") -> 53 | I40: =COUNTIFS(管理表!N:N,A37,管理表!AH:AH,"<>退職",管理表!J:J,C39,管理表!D:D,E40,管理表!C:C,"本社") -> 0 | J40: =COUNTIFS(管理表!N:N,A37,管理表!AH:AH,"<>退職",管理表!J:J,C39,管理表!D:D,E40,管理表!C:C,"協同本社") -> 0 | K40: =COUNTIFS(管理表!N:N,A37,管理表!AH:AH,"<>退職",管理表!J:J,C39,管理表!D:D,E40,管理表!C:C,"津吉") -> 53
A41: INA | B41: =COUNTIFS(管理表!N:N,A41,管理表!AH:AH,"<>退職") -> 15 | C41: 男 | D41: =COUNTIFS(管理表!N:N,A41,管理表!AH:AH,"<>退職",管理表!J:J,C41) -> 3 | E41: ベトナム | F41: =COUNTIFS(管理表!N:N,A41,管理表!AH:AH,"<>退職",管理表!J:J,C41,管理表!D:D,E41) -> 0 | G41: =COUNTIFS(管理表!N:N,A41,管理表!AH:AH,"<>退職",管理表!J:J,C41,管理表!D:D,E41,管理表!Q:Q,"*実習*") -> 0 | H41: =COUNTIFS(管理表!N:N,A41,管理表!AH:AH,"<>退職",管理表!J:J,C41,管理表!D:D,E41,管理表!Q:Q,"*特定*") -> 0 | I41: =COUNTIFS(管理表!N:N,A41,管理表!AH:AH,"<>退職",管理表!J:J,C41,管理表!D:D,E41,管理表!C:C,"本社") -> 0 | J41: =COUNTIFS(管理表!N:N,A41,管理表!AH:AH,"<>退職",管理表!J:J,C41,管理表!D:D,E41,管理表!C:C,"協同本社") -> 0 | K41: =COUNTIFS(管理表!N:N,A41,管理表!AH:AH,"<>退職",管理表!J:J,C41,管理表!D:D,E41,管理表!C:C,"津吉") -> 0
E42: インドネシア | F42: =COUNTIFS(管理表!N:N,A41,管理表!AH:AH,"<>退職",管理表!J:J,C41,管理表!D:D,E42) -> 3 | G42: =COUNTIFS(管理表!N:N,A41,管理表!AH:AH,"<>退職",管理表!J:J,C41,管理表!D:D,E42,管理表!Q:Q,"*実習*") -> 0 | H42: =COUNTIFS(管理表!N:N,A41,管理表!AH:AH,"<>退職",管理表!J:J,C41,管理表!D:D,E42,管理表!Q:Q,"*特定*") -> 3 | I42: =COUNTIFS(管理表!N:N,A41,管理表!AH:AH,"<>退職",管理表!J:J,C41,管理表!D:D,E42,管理表!C:C,"本社") -> 0 | J42: =COUNTIFS(管理表!N:N,A41,管理表!AH:AH,"<>退職",管理表!J:J,C41,管理表!D:D,E42,管理表!C:C,"協同本社") -> 0 | K42: =COUNTIFS(管理表!N:N,A41,管理表!AH:AH,"<>退職",管理表!J:J,C41,管理表!D:D,E42,管理表!C:C,"津吉") -> 3
C43: 女 | D43: =COUNTIFS(管理表!N:N,A41,管理表!AH:AH,"<>退職",管理表!J:J,C43) -> 12 | E43: ベトナム | F43: =COUNTIFS(管理表!N:N,A41,管理表!AH:AH,"<>退職",管理表!J:J,C43,管理表!D:D,E43) -> 0 | G43: =COUNTIFS(管理表!N:N,A41,管理表!AH:AH,"<>退職",管理表!J:J,C43,管理表!D:D,E43,管理表!Q:Q,"*実習*") -> 0 | H43: =COUNTIFS(管理表!N:N,A41,管理表!AH:AH,"<>退職",管理表!J:J,C43,管理表!D:D,E43,管理表!Q:Q,"*特定*") -> 0 | I43: =COUNTIFS(管理表!N:N,A41,管理表!AH:AH,"<>退職",管理表!J:J,C43,管理表!D:D,E43,管理表!C:C,"本社") -> 0 | J43: =COUNTIFS(管理表!N:N,A41,管理表!AH:AH,"<>退職",管理表!J:J,C43,管理表!D:D,E43,管理表!C:C,"協同本社") -> 0 | K43: =COUNTIFS(管理表!N:N,A41,管理表!AH:AH,"<>退職",管理表!J:J,C43,管理表!D:D,E43,管理表!C:C,"津吉") -> 0
E44: インドネシア | F44: =COUNTIFS(管理表!N:N,A41,管理表!AH:AH,"<>退職",管理表!J:J,C43,管理表!D:D,E44) -> 12 | G44: =COUNTIFS(管理表!N:N,A41,管理表!AH:AH,"<>退職",管理表!J:J,C43,管理表!D:D,E44,管理表!Q:Q,"*実習*") -> 0 | H44: =COUNTIFS(管理表!N:N,A41,管理表!AH:AH,"<>退職",管理表!J:J,C43,管理表!D:D,E44,管理表!Q:Q,"*特定*") -> 12 | I44: =COUNTIFS(管理表!N:N,A41,管理表!AH:AH,"<>退職",管理表!J:J,C43,管理表!D:D,E44,管理表!C:C,"本社") -> 0 | J44: =COUNTIFS(管理表!N:N,A41,管理表!AH:AH,"<>退職",管理表!J:J,C43,管理表!D:D,E44,管理表!C:C,"協同本社") -> 0 | K44: =COUNTIFS(管理表!N:N,A41,管理表!AH:AH,"<>退職",管理表!J:J,C43,管理表!D:D,E44,管理表!C:C,"津吉") -> 12
A45: 中温 | B45: =COUNTIFS(管理表!N:N,A45,管理表!AH:AH,"<>退職") -> 5 | C45: 男 | D45: =COUNTIFS(管理表!N:N,A45,管理表!AH:AH,"<>退職",管理表!J:J,C45) -> 2 | E45: ベトナム | F45: =COUNTIFS(管理表!N:N,A45,管理表!AH:AH,"<>退職",管理表!J:J,C45,管理表!D:D,E45) -> 0 | G45: =COUNTIFS(管理表!N:N,A45,管理表!AH:AH,"<>退職",管理表!J:J,C45,管理表!D:D,E45,管理表!Q:Q,"*実習*") -> 0 | H45: =COUNTIFS(管理表!N:N,A45,管理表!AH:AH,"<>退職",管理表!J:J,C45,管理表!D:D,E45,管理表!Q:Q,"*特定*") -> 0 | I45: =COUNTIFS(管理表!N:N,A45,管理表!AH:AH,"<>退職",管理表!J:J,C45,管理表!D:D,E45,管理表!C:C,"本社") -> 0 | J45: =COUNTIFS(管理表!N:N,A45,管理表!AH:AH,"<>退職",管理表!J:J,C45,管理表!D:D,E45,管理表!C:C,"協同本社") -> 0 | K45: =COUNTIFS(管理表!N:N,A45,管理表!AH:AH,"<>退職",管理表!J:J,C45,管理表!D:D,E45,管理表!C:C,"津吉") -> 0
E46: インドネシア | F46: =COUNTIFS(管理表!N:N,A45,管理表!AH:AH,"<>退職",管理表!J:J,C45,管理表!D:D,E46) -> 2 | G46: =COUNTIFS(管理表!N:N,A45,管理表!AH:AH,"<>退職",管理表!J:J,C45,管理表!D:D,E46,管理表!Q:Q,"*実習*") -> 0 | H46: =COUNTIFS(管理表!N:N,A45,管理表!AH:AH,"<>退職",管理表!J:J,C45,管理表!D:D,E46,管理表!Q:Q,"*特定*") -> 2 | I46: =COUNTIFS(管理表!N:N,A45,管理表!AH:AH,"<>退職",管理表!J:J,C45,管理表!D:D,E46,管理表!C:C,"本社") -> 0 | J46: =COUNTIFS(管理表!N:N,A45,管理表!AH:AH,"<>退職",管理表!J:J,C45,管理表!D:D,E46,管理表!C:C,"協同本社") -> 0 | K46: =COUNTIFS(管理表!N:N,A45,管理表!AH:AH,"<>退職",管理表!J:J,C45,管理表!D:D,E46,管理表!C:C,"津吉") -> 2
C47: 女 | D47: =COUNTIFS(管理表!N:N,A45,管理表!AH:AH,"<>退職",管理表!J:J,C47) -> 3 | E47: ベトナム | F47: =COUNTIFS(管理表!N:N,A45,管理表!AH:AH,"<>退職",管理表!J:J,C47,管理表!D:D,E47) -> 0 | G47: =COUNTIFS(管理表!N:N,A45,管理表!AH:AH,"<>退職",管理表!J:J,C47,管理表!D:D,E47,管理表!Q:Q,"*実習*") -> 0 | H47: =COUNTIFS(管理表!N:N,A45,管理表!AH:AH,"<>退職",管理表!J:J,C47,管理表!D:D,E47,管理表!Q:Q,"*特定*") -> 0 | I47: =COUNTIFS(管理表!N:N,A45,管理表!AH:AH,"<>退職",管理表!J:J,C47,管理表!D:D,E47,管理表!C:C,"本社") -> 0 | J47: =COUNTIFS(管理表!N:N,A45,管理表!AH:AH,"<>退職",管理表!J:J,C47,管理表!D:D,E47,管理表!C:C,"協同本社") -> 0 | K47: =COUNTIFS(管理表!N:N,A45,管理表!AH:AH,"<>退職",管理表!J:J,C47,管理表!D:D,E47,管理表!C:C,"津吉") -> 0
E48: インドネシア | F48: =COUNTIFS(管理表!N:N,A45,管理表!AH:AH,"<>退職",管理表!J:J,C47,管理表!D:D,E48) -> 3 | G48: =COUNTIFS(管理表!N:N,A45,管理表!AH:AH,"<>退職",管理表!J:J,C47,管理表!D:D,E48,管理表!Q:Q,"*実習*") -> 0 | H48: =COUNTIFS(管理表!N:N,A45,管理表!AH:AH,"<>退職",管理表!J:J,C47,管理表!D:D,E48,管理表!Q:Q,"*特定*") -> 3 | I48: =COUNTIFS(管理表!N:N,A45,管理表!AH:AH,"<>退職",管理表!J:J,C47,管理表!D:D,E48,管理表!C:C,"本社") -> 0 | J48: =COUNTIFS(管理表!N:N,A45,管理表!AH:AH,"<>退職",管理表!J:J,C47,管理表!D:D,E48,管理表!C:C,"協同本社") -> 0 | K48: =COUNTIFS(管理表!N:N,A45,管理表!AH:AH,"<>退職",管理表!J:J,C47,管理表!D:D,E48,管理表!C:C,"津吉") -> 3
A49: 合計 | B49: =B25+B29+B33+B37+B41+B45 -> 146 | C49: 男 | D49: =D25+D29+D33+D37+D41+D45 -> 44 | E49: ベトナム | F49: =F25+F29+F33+F37+F41+F45 -> 15 | G49: =G25+G29+G33+G37+G41+G45 -> 6 | H49: =H25+H29+H33+H37+H41+H45 -> 9 | I49: =I25+I29+I33+I37+I41+I45 -> 11 | J49: =J25+J29+J33+J37+J41+J45 -> 2 | K49: =K25+K29+K33+K37+K41+K45 -> 2
E50: インドネシア | F50: =F26+F30+F34+F38+F42+F46 -> 29 | G50: =G26+G30+G34+G38+G42+G46 -> 0 | H50: =H26+H30+H34+H38+H42+H46 -> 29 | I50: =I26+I30+I34+I38+I42+I46 -> 0 | J50: =J26+J30+J34+J38+J42+J46 -> 0 | K50: =K26+K30+K34+K38+K42+K46 -> 29
C51: 女 | D51: =D27+D31+D35+D39+D43+D47 -> 102 | E51: ベトナム | F51: =F27+F31+F35+F39+F43+F47 -> 34 | G51: =G27+G31+G35+G39+G43+G47 -> 15 | H51: =H27+H31+H35+H39+H43+H47 -> 19 | I51: =I27+I31+I35+I39+I43+I47 -> 24 | J51: =J27+J31+J35+J39+J43+J47 -> 2 | K51: =K27+K31+K35+K39+K43+K47 -> 8
E52: インドネシア | F52: =F28+F32+F36+F40+F44+F48 -> 68 | G52: =G28+G32+G36+G40+G44+G48 -> 0 | H52: =H28+H32+H36+H40+H44+H48 -> 68 | I52: =I28+I32+I36+I40+I44+I48 -> 0 | J52: =J28+J32+J36+J40+J44+J48 -> 0 | K52: =K28+K32+K36+K40+K44+K48 -> 68

Sheet 入社予定
A1: 区 | B1: No | C1: 勤務地 | D1: 国籍 | E1: 社員コード | F1: 写真 | G1: フリガナ | H1: 氏名 | I1: 呼名 | J1: 性別 | K1: 生年月日 | L1: 年齢 | M1: 配偶者 | N1: 登録支援機関 | O1: 入社日 | P1: 帰国予定 | Q1: 実習区分 | R1: 住所 | S1: 個・相部屋 | T1: 家賃負担 | U1: 雇用条件書 | V1: カード期限 | W1: 在留カード番号 | X1: 雇用保険番号 | Y1: 自転車渡日 | Z1: 自転車No-防犯 | AA1: 自転車回収日 | AB1: 日本語検定 | AC1: 試験資格 | AD1: 一時退職日 | AE1: 一時帰国From | AF1: 一時帰国To | AG1: 再入社 | AH1: 退職区分 | AI1: 退職日 | AJ1: 帰国費用 | AK1: 部署長 | AL1: 備考
C3: 本社 | D3: ベトナム | G3: チャン ティ シン | H3: TRAN THI SINH | J3: 女 | K3: 36088 | L3: =DATEDIF(K3,TODAY(),"Y") -> 27 | M3: 夫婦 | N3: 関東食肉 | O3: 2026/4月末頃 | P3: ライの妻 | Q3: 技能実習1号 | R3: 和泉北1-20-28アトムスカイマンション304 | S3: 相 | T3: 10000 | U3: 45726 | AL3: 2/18面接 合格 ライの奥さん
C4: 本社 | D4: ベトナム | G4: ダオ ティ トゥイ リン | H4: DAO THI THUY LINH | J4: 女 | K4: 39110 | L4: 19 | M4: 無 | N4: 関東食肉 | O4: 2026/2月末 ～3月頃 | P4: ゴックの妹 | Q4: 技能実習1号 | R4: 和泉北1-20-28アトムスカイマンション406 | S4: 個 | T4: ゴック、タオ 家賃どうするか | AL4: ゴックの妹
C6: 本社 | D6: ベトナム | G6: バン ティ タム | H6: BANG THI TAM | I6: バン | J6: 女 | K6: 37885 | L6: 22 | M6: 有 | N6: 中四国 | O6: 46143 | Q6: 技能実習1号 | R6: ハーさんの弟の奥さん ハーさんと同部屋希望 アトム401 | S6: 相 | T6: 10000 | AL6: 2025/9/22面接 合格
C10: 津吉 | D10: インドネシア | G10: アルム ムティアラ ヴァレンティネザ プトリ | H10: ARUM MUTIARA VALENTINEZA PUTRI | J10: 女 | K10: 35080 | L10: 30 | M10: 夫婦 | N10: 中温 | O10: 2026/5月頃 | Q10: 特定技能１号 | R10: ククの奥さん 松山市中野町442-1 | S10: 夫婦 | AL10: ククの奥さん
C11: 津吉 | D11: インドネシア | G11: アグス プラヨガ | H11: AGUS PRAYOGA | I11: ヨガ | J11: 男 | K11: 36119 | L11: 27 | M11: 夫婦 | N11: 中温 | O11: 2026/5月頃 | Q11: 特定技能１号 | R11: 松山市上野町774番地ビレッジハウス松山上野3ｰ508 | S11: 夫婦 | AL11: エヴィの夫
C12: 津吉 | D12: インドネシア | G12: ナスルル ファーミ | H12: NASRUL FAHMI | J12: 男 | K12: 35924 | L12: 27 | M12: 夫婦 | N12: 中温 | O12: 2026/5月頃 | Q12: 特定技能１号 | R12: ヌルアンディニの夫 松山市上野町774番地ビレッジハウス松山上野4-501 | S12: 夫婦 | AL12: ヌルアンディニの夫
D14: ベトナム | G14: グエン ティ フォアン マイ | H14: NGUYEN THI HOANG MAI | J14: 女 | K14: 38635 | L14: =DATEDIF(K14,TODAY(),"Y") -> 20 | N14: 中温 | Q14: 特定活動告示9号
D15: ベトナム | G15: ゴー グエン トゥエット バン | H15: NGO NGUYEN TUYET BANG | J15: 女 | K15: 38130 | L15: =DATEDIF(K15,TODAY(),"Y") -> 21 | N15: 中温 | Q15: 特定活動告示9号
D16: ベトナム | G16: ホー ティ ホン アン | H16: HO THI HONG AN | J16: 女 | K16: 38295 | L16: =DATEDIF(K16,TODAY(),"Y") -> 21 | N16: 中温 | Q16: 特定活動告示9号
D17: ベトナム | G17: グエン ファム トゥオン ヴィ | H17: NGUYEN PHAM TUONG VY | J17: 女 | K17: 38321 | L17: =DATEDIF(K17,TODAY(),"Y") -> 21 | N17: 中温 | Q17: 特定活動告示9号
D18: ベトナム | G18: ダン ティ ゴック ヴァン | H18: DANG THI NGOC VANG | J18: 女 | K18: 38692 | L18: =DATEDIF(K18,TODAY(),"Y") -> 20 | N18: 中温 | Q18: 特定活動告示9号
D19: ベトナム | G19: ダン ティ トゥイ アイン | H19: DANG THI THUY ANH | J19: 女 | K19: 38288 | L19: =DATEDIF(K19,TODAY(),"Y") -> 21 | N19: 中温 | Q19: 特定活動告示9号
D20: ベトナム | G20: ホー ティ ホン トム | H20: HO THI HONG THOM | J20: 女 | K20: 38631 | L20: =DATEDIF(K20,TODAY(),"Y") -> 20 | N20: 中温 | Q20: 特定活動告示9号
D21: ベトナム | G21: グエン レー スアン ハイン | H21: NGUYEN LE XUAN HANH | J21: 女 | K21: 38032 | L21: =DATEDIF(K21,TODAY(),"Y") -> 22 | N21: 中温 | Q21: 特定活動告示9号
D22: ベトナム | G22: ゴー ミ アイン | H22: NGO MY ANH | J22: 女 | K22: 38355 | L22: =DATEDIF(K22,TODAY(),"Y") -> 21 | N22: 中温 | Q22: 特定活動告示9号
D23: ベトナム | G23: チャン グエン カ ハン | H23: TRAN NGUYEN KHA HAN | J23: 女 | K23: 38234 | L23: =DATEDIF(K23,TODAY(),"Y") -> 21 | N23: 中温 | Q23: 特定活動告示9号
D24: ベトナム | G24: チュオン ゴック ジェップ | H24: TRUONG NGOC DIEP | J24: 女 | K24: 38513 | L24: =DATEDIF(K24,TODAY(),"Y") -> 20 | N24: 中温 | Q24: 特定活動告示9号
D25: ベトナム | G25: グエン フォン ガン | H25: NGUYEN PHUONG NGAN | J25: 女 | K25: 38655 | L25: =DATEDIF(K25,TODAY(),"Y") -> 20 | N25: 中温 | Q25: 特定活動告示9号
C27: 津吉 | D27: インドネシア | G27: バングン ケダトン | H27: BANGUN KEDHATON | J27: 男 | K27: 37439 | L27: 23 | N27: 中温 | Q27: 特定技能１号 | R27: レイハン友人つながり
C28: 津吉 | D28: インドネシア | G28: アクマル クルニアワン | H28: AKMAL KURNIAWAN | J28: 男 | K28: 37928 | L28: 22 | N28: 中温 | Q28: 特定技能１号 | R28: レイハン友人 | AL28: 4/8面接 合格
C29: 津吉 | D29: インドネシア | G29: ムハッマド イマム アル フィトリ | H29: MUHAMMAD IMAM AL FITRI | J29: 男 | K29: 37950 | L29: 22 | N29: 中温 | Q29: 特定技能１号 | R29: レイハン友人 | AL29: 4/8面接 合格
C30: 津吉 | D30: インドネシア | G30: ハリ テグ プラセティオ | H30: HARI TEGUH PRASETIO | J30: 男 | K30: 37428 | L30: 23 | N30: 中温 | Q30: 特定技能１号 | R30: エヴィ夫 友人 | AL30: 4/8面接 合格
C31: 津吉 | D31: インドネシア | G31: アリファ ハフィゾトゥン ハサナ | H31: ALIFAH HAFIZHOTUN HASANAH | J31: 女 | K31: 37856 | L31: 22 | N31: 中温 | Q31: 特定技能１号 | R31: サエ 友人 | AL31: 4/13面接 合格
C32: 津吉 | D32: インドネシア | G32: トリ ヌル インダー レスタリ | H32: TRI NUR INDAH LESTARI | J32: 女 | K32: 38591 | L32: 20 | N32: 中温 | Q32: 特定技能１号 | R32: アイシャ、エヴィ 友人 | AL32: 4/13面接 合格
A34: R | C34: 津吉 | D34: インドネシア | G34: イルハム マウラナ | H34: ILHAM MAULANA | I34: イルハム | J34: 男 | K34: 36320 | L34: 26 | M34: 無 | O34: 46023 | Q34: 特定技能１号 | R34: 中野町457-1 | S34: 相 | U34: 45778 | AL34: 4/25面接 合格
A35: R | C35: 津吉 | D35: インドネシア | G35: リヴォ デャルマザル | H35: RIVO DHARMAZAL | I35: リヴォ | J35: 男 | K35: 37822 | L35: 22 | M35: 無 | O35: 46023 | Q35: 特定技能１号 | S35: 相 | U35: 45778 | AL35: 4/25面接 合格
A36: R | C36: 津吉 | D36: インドネシア | G36: アルディアヌス バワメネウィ | H36: ARDIANUS BAWAMENEWI | I36: アルディ | J36: 男 | K36: 36228 | L36: 26 | M36: 無 | O36: 46023 | Q36: 特定技能１号 | S36: 相 | U36: 45778 | AL36: 4/25面接 合格
A37: R | C37: 津吉 | D37: インドネシア | G37: エム フィクリ イクサン | H37: M. FIKRI IKHSAN | I37: フィクリ | J37: 男 | K37: 38361 | L37: 21 | M37: 無 | O37: 46023 | Q37: 特定技能１号 | S37: 相 | U37: 45778 | AL37: 4/25面接 合格
A38: R | C38: 津吉 | D38: インドネシア | G38: ヒクマル ハナフィス | H38: HIKMAL HANAFIS | I38: ヒクマル | J38: 男 | K38: 38534 | L38: 20 | M38: 無 | O38: 46023 | Q38: 特定技能１号 | R38: 中野町457-1 | S38: 相 | U38: 45778 | AL38: 4/25面接 合格
A39: R | C39: 津吉 | D39: インドネシア | G39: フェルナ マルヤニ | H39: FERNA MARYANI | I39: フェルナ | J39: 女 | K39: 37302 | L39: 23 | M39: 無 | O39: 46023 | Q39: 特定技能１号 | R39: 東温市牛渕170-３ | S39: 相 | U39: 45778 | AL39: 4/25面接 合格
A40: R | C40: 津吉 | D40: インドネシア | G40: エラ マルリアナ リヤンティ | H40: ELA MARLIANA RIYANTI | I40: エラ | J40: 女 | K40: 36977 | L40: 24 | M40: 無 | O40: 46023 | Q40: 特定技能１号 | R40: 東温市牛渕170-３ | S40: 相 | U40: 45778 | AL40: 4/25面接 合格
A41: R | C41: 津吉 | D41: インドネシア | G41: ファンニ ヨランダ | H41: FANNY YOLANDA | I41: ファンニ | J41: 女 | K41: 35581 | L41: 28 | M41: 無 | O41: 46023 | Q41: 特定技能１号 | R41: 東温市牛渕170-３ | S41: 相 | U41: 45778 | AL41: 4/25面接 合格
A42: R | C42: 津吉 | D42: インドネシア | G42: リディア アフィザ | H42: LIDYA AFIZA | I42: リディア | J42: 女 | K42: 35156 | L42: 29 | M42: 無 | O42: 46023 | Q42: 特定技能１号 | R42: 東温市牛渕170-３ | S42: 相 | U42: 45778 | AL42: 4/25面接 合格
A43: R | C43: 津吉 | D43: インドネシア | G43: セプティ エカ ドウィジャヤンティ | H43: SEPTI EKA DWIJAYANTI | I43: エカ | J43: 女 | K43: 38239 | L43: 21 | M43: 無 | O43: 46023 | Q43: 特定技能１号 | R43: 東温市牛渕170-３ | S43: 相 | U43: 45778 | AL43: 4/25面接 合格
A44: R | C44: 津吉 | D44: インドネシア | G44: デフィアナ レトノワティ | H44: DEVIANA RETNOWATI | I44: レトノ | J44: 女 | K44: 36613 | L44: 25 | M44: 無 | O44: 46023 | Q44: 特定技能１号 | R44: 東温市牛渕170-３ | S44: 相 | U44: 45778 | AL44: 4/25面接 合格
A45: R | C45: 津吉 | D45: インドネシア | G45: ムハマド バユ アセガフ | H45: MUHAMMAD BAYU ASSEGAF | I45: バユ | J45: 男 | K45: 38352 | L45: 21 | M45: 無 | O45: 46023 | Q45: 特定技能１号 | R45: 中野① 3人 or中野② 7人 | S45: 相 | U45: 45778 | AL45: 4/25面接 合格
A46: R | C46: 津吉 | D46: インドネシア | G46: アディ プラタマ マウルディ | H46: ADI PRATAMA MAULUDY | I46: アディ | J46: 男 | K46: 35637 | L46: 28 | M46: 無 | O46: 46023 | Q46: 特定技能１号 | S46: 相 | U46: 45778 | AL46: 4/25面接 合格
A47: R | C47: 津吉 | D47: インドネシア | G47: フィルサン アヌグラー | H47: FIRSAN ANUGRAH | I47: フィルサン | J47: 男 | K47: 37311 | L47: 23 | M47: 無 | O47: 46023 | Q47: 特定技能１号 | S47: 相 | U47: 45778 | AL47: 4/25面接 合格
A48: R | C48: 津吉 | D48: インドネシア | G48: スルヤ アンガ ジャテサプトラ | H48: SURYA ANGGA JATISAPUTRA | I48: アンガ | J48: 男 | K48: 38238 | L48: 21 | M48: 無 | O48: 46023 | Q48: 特定技能１号 | S48: 相 | U48: 45778 | AL48: 4/25面接 合格
A49: R | C49: 津吉 | D49: インドネシア | G49: ラフマド グナワン | H49: RAHMAD GUNAWAN | I49: ラフマド | J49: 男 | K49: 34565 | L49: 31 | M49: 無 | O49: 46023 | Q49: 特定技能１号 | S49: 相 | U49: 45778 | AL49: 4/25面接 合格
D51: ベトナム | G51: ブイ ティ フェ | H51: BUI THI HUE | J51: 女 | K51: 38306 | L51: 21 | M51: 無 | Q51: 特定技能１号
D52: ベトナム | G52: レー ティ スアン | H52: LE THI XOAN | J52: 女 | K52: 37156 | L52: 24 | M52: 無 | Q52: 特定技能１号
D53: ベトナム | G53: ファン ティ トゥエット ニー | H53: PHAN THI TUYET | J53: 女 | K53: 37596 | L53: 23 | M53: 無 | Q53: 特定技能１号
D54: ベトナム | G54: グエン ヴァン ゴック | H54: NGUYEN VAN NGOC | J54: 男 | K54: 38462 | L54: 20 | M54: 無 | Q54: 特定技能１号
D55: ベトナム | G55: ファム ティ トゥン | H55: PHAM THI TUNG | J55: 女 | K55: 32543 | L55: 36 | M55: 有 | Q55: 特定技能１号
D56: ベトナム | G56: チャン ティ エン | H56: TRAN THI YEN | J56: 女 | K56: 34494 | L56: 31 | M56: 有 | Q56: 特定技能１号
D57: ベトナム | G57: ブイ ヴァン バイ | H57: BUI VAN BAY | J57: 男 | K57: 36702 | L57: 25 | M57: 無 | Q57: 特定技能１号
D58: ベトナム | G58: ファム ティ タン | H58: PHAM THI THANH | J58: 女 | K58: 33646 | L58: 34 | M58: 有 | Q58: 特定技能１号
D59: ベトナム | G59: グエン ティ タイン チュック | H59: NGUYEN THI THANH CHUC | J59: 女 | K59: 37370 | L59: 23 | M59: 無 | Q59: 特定技能１号
D61: ベトナム | G61: グエン ティ ニュー クイ | H61: NGUYEN NHU QUYNH | J61: 女 | K61: 38204 | L61: =DATEDIF(K61,TODAY(),"Y") -> 21 | M61: 無 | Q61: 特定技能１号
D62: ベトナム | G62: チャン ティ ホア ミー | H62: TRAN THI HOA MY | J62: 女 | K62: 38236 | L62: =DATEDIF(K62,TODAY(),"Y") -> 21 | M62: 無 | Q62: 特定技能１号
D63: ベトナム | G63: ブイ ズン クイン | H63: BUI DUY QUYNH | J63: 男 | K63: 37792 | L63: =DATEDIF(K63,TODAY(),"Y") -> 22 | M63: 無 | Q63: 特定技能１号
D64: ベトナム | G64: ルオン ティ モン チン | H64: LUONG THI MONG TRINH | J64: 女 | K64: 35481 | L64: =DATEDIF(K64,TODAY(),"Y") -> 29 | M64: 無 | Q64: 特定技能１号
D65: ベトナム | G65: グエン コン トゥアン アイン | H65: NGUYEN CONG TUAN ANH | J65: 男 | K65: 36731 | L65: =DATEDIF(K65,TODAY(),"Y") -> 25 | M65: 無 | Q65: 特定技能１号
D66: ベトナム | G66: ヴォ― ティ トゥイ アン | H66: VO THI THUY AN | J66: 女 | K66: 31252 | L66: =DATEDIF(K66,TODAY(),"Y") -> 40 | M66: 無 | Q66: 特定技能１号
D67: ベトナム | G67: ゴー ティ トゥオン | H67: NGO THI THUONG | J67: 女 | K67: 33031 | L67: =DATEDIF(K67,TODAY(),"Y") -> 35 | M67: 有 | Q67: 特定技能１号
D68: ベトナム | G68: ホー ティ ロアン | H68: HO THI LOAN | J68: 女 | K68: 33453 | L68: =DATEDIF(K68,TODAY(),"Y") -> 34 | M68: 無 | Q68: 特定技能１号
D69: ベトナム | G69: チャン ティ ホア | H69: TRAN THI HOA | J69: 女 | K69: 33131 | L69: =DATEDIF(K69,TODAY(),"Y") -> 35 | M69: 有 | Q69: 特定技能１号
D70: ベトナム | G70: ホアン チイ クイン チャン | H70: HOANG THI QUYNH TRANG | J70: 女 | K70: 36680 | L70: =DATEDIF(K70,TODAY(),"Y") -> 25 | M70: 有 | Q70: 特定技能１号
D71: ベトナム | G71: グエン トゥ タオ | H71: NGUYEN THU TAO | J71: 女 | K71: 34306 | L71: =DATEDIF(K71,TODAY(),"Y") -> 32 | M71: 有 | Q71: 特定技能１号
D72: ベトナム | G72: グエン チイ リー | H72: NGUYEN THI LY | J72: 女 | K72: 34390 | L72: =DATEDIF(K72,TODAY(),"Y") -> 32 | M72: 有 | Q72: 特定技能１号
... D74: ベトナム | G74: ファム チュオン アン | H74: PHAM TRUONG AN | J74: 男 | K74: 35665 | L74: =DATEDIF(K74,TODAY(),"Y") -> 28 | M74: 無 | Q74: 特定技能１号
A76: R | D76: インドネシア | G76: １ | H76: AISMA | J76: 男 | K76: 36367 | L76: =DATEDIF(K76,TODAY(),"Y") -> 26 | M76: 無 | Q76: 特定技能１号 | AL76: 2026/4/2面接
A77: R | D77: インドネシア | G77: ２ | H77: AFIF MUNIRUDIN | J77: 男 | K77: 36350 | L77: =DATEDIF(K77,TODAY(),"Y") -> 26 | M77: 無 | Q77: 特定技能１号 | AL77: 2026/4/2面接
A78: R | D78: インドネシア | G78: ３ | H78: ROHMAN SAWALUDIN | J78: 男 | K78: 38313 | L78: =DATEDIF(K78,TODAY(),"Y") -> 21 | M78: 無 | Q78: 特定技能１号 | AL78: 2026/4/2面接
A79: R | D79: インドネシア | G79: ４ | H79: ANDIKA TRI FILDA | J79: 男 | K79: 38977 | L79: =DATEDIF(K79,TODAY(),"Y") -> 19 | M79: 無 | Q79: 特定技能１号 | AL79: 2026/4/2面接
A80: R | D80: インドネシア | G80: ５ | H80: ARDIA RESSA SETIA KURNIAWAN | J80: 男 | K80: 36352 | L80: =DATEDIF(K80,TODAY(),"Y") -> 26 | M80: 有 | Q80: 特定技能１号 | AL80: 2026/4/2面接
A81: R | D81: インドネシア | G81: ６ | H81: FACRUL MUFLY HASAN | J81: 男 | K81: 38524 | L81: =DATEDIF(K81,TODAY(),"Y") -> 20 | M81: 無 | Q81: 特定技能１号 | AL81: 2026/4/2面接
A82: R | D82: インドネシア | G82: ７ | H82: DEDEN DENI ALPIKIH | J82: 男 | K82: 35403 | L82: =DATEDIF(K82,TODAY(),"Y") -> 29 | M82: 無 | Q82: 特定技能１号 | AL82: 2026/4/2面接
A83: R | D83: インドネシア | G83: ８ | H83: UMI SURYANTI | J83: 女 | K83: 37899 | L83: =DATEDIF(K83,TODAY(),"Y") -> 22 | M83: 無 | Q83: 特定技能１号 | AL83: 2026/4/2面接
A84: R | D84: インドネシア | G84: ９ | H84: ALIN MARLINA | J84: 女 | K84: 35897 | L84: =DATEDIF(K84,TODAY(),"Y") -> 28 | M84: 有 | Q84: 特定技能１号 | AL84: 2026/4/2面接
A85: R | D85: インドネシア | G85: １０ | H85: AMELIA AGNES ISRAEL | J85: 女 | K85: 38957 | L85: =DATEDIF(K85,TODAY(),"Y") -> 19 | M85: 無 | Q85: 特定技能１号 | AL85: 2026/4/2面接
D87: インドネシア | G87: シティ ヌル アジーザ | H87: SITI NUR AZIEZAH | I87: アジーザ | J87: 女 | K87: 37649 | L87: =DATEDIF(K87,TODAY(),"Y") -> 23 | M87: 無 | Q87: 特定技能１号
D88: インドネシア | G88: マイ クラデア ザンデイ | H88: MAY CLAUDHEA ZHANDY | I88: デア | J88: 女 | K88: 39222 | L88: =DATEDIF(K88,TODAY(),"Y") -> 18 | M88: 無 | Q88: 特定技能１号
D89: インドネシア | G89: ノフィア レスタリ | H89: NOVIA LESTARI | I89: ノフィア | J89: 女 | K89: 35750 | L89: =DATEDIF(K89,TODAY(),"Y") -> 28 | M89: 無 | Q89: 特定技能１号
D90: インドネシア | G90: フェッビ プトリ ヴァレンチナ | H90: FEBBY PUTRI VALENTINA | I90: フェッビ | J90: 女 | K90: 38030 | L90: =DATEDIF(K90,TODAY(),"Y") -> 22 | M90: 無 | Q90: 特定技能１号
D91: インドネシア | G91: ピピット アユ レスタリ | H91: PIPIT AYU LESTARI | I91: ピピット | J91: 女 | K91: 38739 | L91: =DATEDIF(K91,TODAY(),"Y") -> 20 | M91: 無 | Q91: 特定技能１号
D92: インドネシア | G92: ナディアトゥル フスナ ハニファー | H92: NADIATUL HUSNA HANIFAH | I92: ナディア | J92: 女 | K92: 36397 | L92: =DATEDIF(K92,TODAY(),"Y") -> 26 | M92: 無 | Q92: 特定技能１号
D93: インドネシア | G93: ムハンマド イブヌ アブディル ジャディド アリフィン | H93: MUHAMMAD IBNU ABDIL JADID ARIFIN | I93: イブヌ | J93: 男 | K93: 38894 | L93: =DATEDIF(K93,TODAY(),"Y") -> 19 | M93: 無 | Q93: 特定技能１号
D94: インドネシア | G94: アフリザル | H94: AFRIZAL | J94: 男 | K94: 38002 | L94: =DATEDIF(K94,TODAY(),"Y") -> 22 | M94: 無 | Q94: 特定技能１号
D95: インドネシア | G95: ロニ ヌルハディ | H95: RONI NURHADI | J95: 男 | K95: 35317 | L95: =DATEDIF(K95,TODAY(),"Y") -> 29 | M95: 無 | Q95: 特定技能１号
D96: インドネシア | G96: ムハマド ユヌス | H96: MUHAMAD YUNUS | I96: ユヌス | J96: 男 | K96: 36597 | L96: =DATEDIF(K96,TODAY(),"Y") -> 26 | M96: 無 | Q96: 特定技能１号
D97: インドネシア | G97: ヌル ジヤダトゥン ニクマー | H97: NUR ZIYADATUN NIKMAH | I97: ジヤ | J97: 女 | K97: 37444 | L97: =DATEDIF(K97,TODAY(),"Y") -> 23 | M97: 無 | Q97: 特定技能１号
D98: インドネシア | G98: リニア ラハユ セティアワティ | H98: LINIA RAHAYU SETIAWATI | I98: リニア | J98: 女 | K98: 37449 | L98: =DATEDIF(K98,TODAY(),"Y") -> 23 | M98: 無 | Q98: 特定技能１号
D99: インドネシア | G99: スリス ヤナ | H99: SULIS YANA | I99: スリス | J99: 女 | K99: 39135 | L99: =DATEDIF(K99,TODAY(),"Y") -> 19 | M99: 無 | Q99: 特定技能１号
D100: インドネシア | G100: トゥティク ラーマ ソリハ | H100: TUTIK RAHMA SOLIHAH | I100: ラーマ | J100: 女 | K100: 38846 | L100: =DATEDIF(K100,TODAY(),"Y") -> 19 | M100: 無 | Q100: 特定技能１号
D101: インドネシア | G101: アフィコ コリアトゥル ハニム | H101: AFIQOH QORIATUL HANIM | I101: アフィコ | J101: 女 | K101: 38448 | L101: =DATEDIF(K101,TODAY(),"Y") -> 21 | M101: 無 | Q101: 特定技能１号
D102: インドネシア | G102: イチャ ウィジャヤンティ | H102: ICA WIJAYANTI | I102: イチャ | J102: 女 | K102: 37321 | L102: =DATEDIF(K102,TODAY(),"Y") -> 24 | M102: 無 | Q102: 特定技能１号
D103: インドネシア | G103: イルハム アルファリッチ | H103: ILHAM ALFARIZZI | I103: イルハム | J103: 男 | K103: 38642 | L103: =DATEDIF(K103,TODAY(),"Y") -> 20 | M103: 無 | Q103: 特定技能１号
D104: インドネシア | G104: ナビラ フィアマニッラ ラーマン | H104: NABILA FIAMAILLAH RACHMAN | I104: ナビラ | J104: 女 | K104: 38496 | L104: =DATEDIF(K104,TODAY(),"Y") -> 20 | M104: 無 | Q104: 特定技能１号
C106: 津吉 | D106: ベトナム | G106: ブー ティ トゥ ハー | H106: VU THI THU HA | I106: ハー | J106: 女 | K106: 37624 | L106: =DATEDIF(K106,TODAY(),"Y") -> 23 | N106: 関東食肉 | O106: ？2025/11/21頃 | P106: 47757 | Q106: 特定技能１号 | R106: ご主人と住む ビレッジハウス | S106: 相 | Z106: 自身で購入 | AL106: 2025/5/23面接 合格 津吉工場のリンさんの知人 現在香川で実習生2号として就業中。2025/9末 退職予定、10/3に一時帰国後、 10/18結婚予定 11月から中温で働く予定 ご主人の情報を連絡もらうよう本人へ伝えた9/9 ご主人名義でビレッジ借りている ・布団、自転車は自身で用意 2025/11/12 妊娠のため、キャンセル
A107: R | C107: 津吉 | D107: インドネシア | E107: 辞退 | G107: アギン ロマン ムスタフ | H107: AGIN ROMAN MUSTAF | I107: アギン | J107: 男 | K107: 38017 | L107: =DATEDIF(K107,TODAY(),"Y") -> 22 | M107: 無 | O107: 2025/05頃 | Q107: 特定技能１号 | S107: 相 | T107: 10000 | AL107: 2/5面接 合格
C108: 津吉 | D108: インドネシア | E108: 辞退 | G108: シティ マルヤティ | H108: SITI MARYATI | J108: 女 | K108: 34908 | L108: =DATEDIF(K108,TODAY(),"Y") -> 30 | M108: 無 | O108: 2025/05頃 | Q108: 特定技能１号 | S108: 相 | T108: 10000 | AL108: 2/5面接 合格 H&C人材保証 旅費送出期間負担
C109: 津吉 | D109: インドネシア | E109: 辞退 | G109: アリファ ハフィジョトゥン ハサナ | H109: ALIFAH HAFIZHOTUN HASANAH | J109: 女 | K109: 37856 | L109: =DATEDIF(K109,TODAY(),"Y") -> 22 | M109: 無 | O109: 2025/05頃 | Q109: 特定技能１号 | S109: 相 | T109: 10000 | AL109: 2/5面接 合格 H&C人材保証 旅費送出期間負担
C111: 津吉 | D111: ベトナム | E111: 辞退 | G111: チャン ゴック ロン | H111: TRAN NGOC LONG | J111: 男 | K111: 37661 | L111: =DATEDIF(K111,TODAY(),"Y") -> 23 | M111: 無 | O111: 2025/06頃 | Q111: 特定技能１号 | S111: 相 | T111: 10000 | AL111: 3/11面接 合格 2025/3/31父親休止のため辞退
C112: 津吉 | D112: ベトナム | E112: 辞退 | G112: ファム ヴァン ダット | H112: PHAM VAN DAT | J112: 男 | K112: 34174 | L112: =DATEDIF(K112,TODAY(),"Y") -> 32 | M112: 無 | O112: 2025/06頃 | Q112: 特定技能１号 | S112: 相 | T112: 10000 | AL112: 3/11面接 合格 2025/05/02辞退
A113: R | C113: 津吉 | D113: インドネシア | E113: 辞退 | G113: ミラ リスワティ | H113: MIRA LISWATI | J113: 女 | K113: 38005 | L113: =DATEDIF(K113,TODAY(),"Y") -> 22 | M113: 無 | O113: 2025/04頃 | Q113: 特定技能１号 | S113: 相 | T113: 10000 | AL113: 12/12面接 合格 2025/7/22辞退
A114: R | C114: 津吉 | D114: インドネシア | E114: 辞退 | G114: アユ アンジャニ | H114: AYU ANJANI | I114: アユ | J114: 女 | K114: 36423 | L114: =DATEDIF(K114,TODAY(),"Y") -> 26 | M114: 無 | O114: 2025/05頃 | Q114: 特定技能１号 | S114: 相 | T114: 10000 | AL114: 2/5面接 合格 2025/7/22辞退
D116: 本社 | H116: 津吉
...

Sheet リーダー・副
A3: 特定生リーダー・副リーダー候補
B5: （工場長。部署長推薦） | H5: 45612
A7: 部署名 | D7: 社員ＣＤ | E7: 氏名 | H7: 入社年月日 | J7: 在籍年月
A8: 製造一課 | C8: リーダー | D8: 07001609 | E8: マイン(男性) | H8: 2020.10.15 | J8: 5年
C9: リーダー | D9: 07001607 | E9: ドー (男性) | H9: 2021.01.25 | J9: 4年
C10: 副リーダー | D10: 07001613 | E10: ロアン(女性) | H10: 2018.12.01 | J10: 7年
C11: 副リーダー | D11: 07001611 | E11: ミン (女性) | H11: 2018.12.01 | J11: 7年
A12: 製造二課 | C12: リーダー | D12: 07001605 | E12: ヴィエット(男性) | H12: 2020.10.15 | J12: 5年
C13: 副リーダー | D13: 07001614 | E13: チャン (女性) | H13: 2019.06.11 | J13: 6年
A14: 製造三課 | C14: リーダー | D14: 07001610 | E14: ダット(男性) | H14: 2020.10.15 | J14: 5年
C15: 副リーダー | D15: 07004416 | E15: ヒエン(女性) | H15: 2019.06.11 | J15: 4年 | L15: ※出産のため2023年6月一時帰国中。2025年2月再入社予定
A19: 特定生リーダー・副リーダー候補
B21: （工場長。部署長推薦） | I21: 45730
A23: 部署名 | D23: 社員ＣＤ | E23: 氏名 | H23: 性別 | I23: 入社年月日 | K23: 在籍年月 | M23: 国籍
A24: 製造第一課 Aライン | D24: 07011602 | E24: グエンビックフーン | H24: 女性 | I24: 43040 | K24: （7年） | M24: ベトナム
A25: 製造第一課 Bライン | D25: 07012602 | E25: チャンティートゥータオ | H25: 女性 | I25: 44566 | K25: （2年10カ月） | M25: ベトナム
A26: 製造第一課 Ｃライン | D26: 07011613 | E26: ファムティ チン | H26: 女性 | I26: 43729 | K26: （5年） | M26: ベトナム
A27: 製造第一課 Ｃライン | D27: 07013628 | E27: アリ クスナディ | H27: 男性 | I27: 44937 | K27: （1年11カ月） | M27: インドネシア
A28: 製造第一課 Dライン | D28: 07012601 | E28: ブィ ヒュウ フン | H28: 男性 | I28: 44566 | K28: （2年10カ月） | M28: ベトナム
A29: 製造第一課 Dライン | D29: 07013606 | E29: アユサヌルフィトリヤニ | H29: 女性 | I29: 44669 | K29: （2年7カ月） | M29: インドネシア
A30: 製造第二課 | D30: 07013619 | E30: ミフタフル アリフ | H30: 男性 | I30: 44669 | K30: （2年7カ月） | M30: インドネシア
A31: 製造第四課 | D31: 07013605 | E31: エヴィ ラハユ | H31: 女性 | I31: 44669 | K31: （2年7カ月） | M31: インドネシア
A32: 製造第四課 | D32: 07013601 | E32: トリ ユニ | H32: 女性 | I32: 44669 | K32: （2年7カ月） | M32: インドネシア
A33: 製造第四課 | D33: 07013635 | E33: レイハンアリサハシカザカリ | H33: 男性 | I33: 45027 | K33: （1年7カ月） | M33: インドネシア
A34: 製造第四課 | D34: 07013634 | E34: シャールル アルル | H34: 男性 | I34: 45027 | K34: （1年7カ月） | M34: インドネシア
A35: 製品管理課（箱入） | D35: 07011606 | E35: ヴーティ ホアン | H35: 女性 | I35: 44013 | K35: （3年7カ月） | M35: ベトナム | O35: ※1回退職、再入社
A36: 製品管理課（出荷） | D36: 07013626 | E36: ムハマンドナウファルアリムフタル | H36: 男性 | I36: 44937 | K36: （1年11カ月） | M36: インドネシア
E37: 女性７名 男性６名 計１３名
B39: 特定技能生リーダー（二期）
C41: （工場長。部署長推薦） | I41: 46001
A43: 部署名 | E43: 氏名 | H43: 性別 | I43: 入社年月日 | K43: 在籍年月 | M43: 国籍
A44: 製造第一課 Aライン | E44: ミフタフディン ラティフ | H44: 男性 | I44: 44937 | K44: ２年１１ヶ月 | M44: インドネシア
A45: 製造第一課 Aライン | E45: カデック アデリア | H45: 女性 | I45: 45027 | K45: ２年８ヶ月 | M45: インドネシア
A46: 製造第一課 Dライン | E46: ジェシカ アウリア プトリ | H46: 女性 | I46: 45098 | K46: ２年５ヶ月 | M46: インドネシア
A47: 製造第三課 | E47: レストゥ グメラー | H47: 男性 | I47: 44669 | K47: ２年１０ヶ月 | M47: インドネシア | O47: ※1回退職、再入社
A48: 製造第四課 | E48: ヌル アンディ二 | H48: 女性 | I48: 45075 | K48: ２年６ヶ月 | M48: インドネシア
A49: 製造第四課 | E49: シャリファ サニア | H49: 女性 | I49: 45216 | K49: ２年２ヶ月 | M49: インドネシア
H50: ６名
B51: 特定技能生副リーダー
C53: （工場長。部署長推薦） | I53: 46001
A55: 部署名 | E55: 氏名 | H55: 性別 | I55: 入社年月日 | K55: 在籍年月 | M55: 国籍
A56: 製造第一課 Cライン | E56: アルバシタ アマリア | H56: 女性 | I56: 44669 | K56: ３年２ヶ月 | M56: インドネシア | O56: ※1回退職、再入社
A57: 製造第一課 Dライン | E57: アプリヨノ | H57: 男性 | I57: 45376 | K57: １年８ヶ月 | M57: インドネシア
A58: 製造第二課 | E58: アエプ サエプル ハク | H58: 男性 | I58: 45505 | K58: １年４ヶ月 | M58: インドネシア
A59: 製造第四課 | E59: リザル ムハマド フィルダウス | H59: 男性 | I59: 45594 | K59: １年１ヶ月 | M59: インドネシア
A60: 製造第四課 | E60: アルル ユスフ フィルダウス | H60: 男性 | I60: 45594 | K60: １年１ヶ月 | M60: インドネシア
A61: 製造第四課 | E61: プジャ サンロヒャ プルバ | H61: 女性 | I61: 45216 | K61: ２年２ヶ月 | M61: インドネシア
A62: 製品管理課（箱入） | E62: ナナ マルディアナ | H62: 男性 | I62: 45027 | K62: ２年８ヶ月 | M62: インドネシア
A63: 製品管理課（箱入） | E63: イスラ ナディア | H63: 女性 | I63: 45098 | K63: ２年５ヶ月 | M63: インドネシア

Sheet 帰国・退職予定
A1: フオ | B1: No | C1: 勤務地 | D1: 国籍 | E1: 社員コード | F1: 写真 | G1: フリガナ | H1: 氏名 | I1: 呼名 | J1: 性別 | K1: 生年月日 | L1: 年齢 | M1: 配偶者 | N1: 登録支援機関 | O1: 入社日 | P1: 帰国予定 | Q1: 実習区分 | R1: 住所 | S1: 個・相部屋 | T1: 家賃負担 | U1: 雇用条件書 | V1: カード期限 | W1: 在留カード番号 | X1: 雇用保険番号 | Y1: 自転車渡日 | Z1: 自転車No-防犯 | AA1: 自転車回収日 | AB1: 日本語検定 | AC1: 試験資格 | AD1: 一時退職日 | AE1: 一時帰国From | AF1: 一時帰国To | AG1: 再入社 | AH1: 退職区分 | AI1: 退職日 | AJ1: 帰国費用 | AK1: 備考
A2: Ｑ | B2: 129 | C2: 津吉 | D2: ベトナム | E2: 07011609 | G2: ディン ティ ヅエン | H2: DINH THI DUYEN | I2: ヅエン | J2: 女 | K2: 35903 | L2: =DATEDIF(K2,TODAY(),"Y") -> 28 | M2: 有 | N2: 中四国 | O2: 44978 | P2: 2028/02 | Q2: 特定技能１号 | R2: 伊予郡砥部町高尾田826-1コーポ麻生205 | S2: ご主人の寮 | T2: ― | V2: 45729 | W2: SA06113967PA | X2: 5099-194656-5 | Z2: 返却 | AD2: 45300 | AE2: 2024/01/10 2025/07/01 | AF2: 2024/03/08 2025/08/14 | AG2: 45362 | AH2: 退職 | AI2: 2024/9/2～ 育児休暇予定 | AK2: 2025/09に子供の入園について可否の連絡が入る予定。入園が 決まれば仕事復帰する予定。2025/7/1～8/14一時帰国 再入社時、特定1号保険に加入するか確認する 9/2～産休へ入りたいとのこと。手続き等必要か？24.7.23朴さん 住まいは探している。8/1住所変更（5/21朴さんより）3/13中四国より妊娠7週目 とのこと。予定日2024.10.13。日本で出産、育児を希望。親が 短期ﾋﾞｻﾞ（3～最長6ヵ月特定活動）で来る予定。専務→中四国本多さん、ご主人の会社へ連絡予定 夫：グエン ヴァン ヴィンさん 電話 080-2512-8225 勤務先 (株)himeken 担当者 井上次長 電話080-8633-5691 2025/10/20お子さんが1才になったが保育園が決まらず6ヵ月（2026/4/20）まで 育休の延長申請済（10/22）
B3: 19 | C3: 津吉 | D3: ベトナム | E3: 07011613 | F3: /appsheet/photograph/19.写真.032434.jpg | G3: ファム ティ チン | H3: PHAM THI CHINH | I3: ファムチン | J3: 女 | K3: 33243 | L3: =DATEDIF(K3,TODAY(),"Y") -> 35 | M3: 夫婦 | N3: 中四国 | O3: 43729 | P3: 2029/08 | Q3: 特定技能１号 | R3: 松山市上野町774番地ビレッジハウス松山上野1-303 | S3: 夫婦 | T3: 15000 | U3: 45545 | V3: 45995 | W3: SA44306016PA | X3: 5105-743701-1 | Z3: ご主人のバイクで通勤 会社支給 管理番号なし B-0128654 白26ｲﾝﾁ | AA3: 通勤方法確認書 には通勤、買い物も 会社の自転車使用 と記載あり | AE3: 45707 | AF3: 45707 | AI3: 2025/9/27～ 育児休暇予定 | AJ3: 2025/03/11帰国費用 広島⇔ハノイ74,300円 半額負担し、特定終了後は 負担しない | AP3: ビレッジハウス 個人で契約するとのこと 妊娠のため2025.9月末頃？～産休（予定日11/7）2025.5.30出産で9月頃退職後一時帰国予定。（子供が1才になるまで）再度中温へ戻りたいとの希望あり。→中四国朴さんより、日本で出産すると本人が言っているとのこと。寮は次が確定しているため、再度確認依頼済。 2024/12/04～特定技能 2024/10/04～特定活動 2024.10.20 実習3号終了予定 130ズオンデタオが夫 2024/09/18 特定技能へ申請手続き 2024/09/25コーポ津吉1-6よりビレッジ2-503へ引越→通勤届済
B4: 9 | C4: 本社 | D4: ベトナム | E4: 07001611 | F4: /appsheet/photograph/小栗_ミン_20240424.jpg | G4: ブイ ティ ミン | H4: BUI THI MINH | I4: ミン | J4: 女 | K4: 36245 | L4: =DATEDIF(K4,TODAY(),"Y") -> 27 | M4: 夫婦 | N4: 中四国 | O4: 43435 | P4: 2025/09 | Q4: 特定技能１号 | R4: 和泉北1-20-28アトムスカイマンション305 | S4: 夫婦 | T4: 20000 | U4: 45383 | V4: 46294 | W4: UH54552117PC | X4: 5103-260929-6 | Z4: 返却済 宮内工場長の自転車を乗っている | AB4: N4 2024/07/07 | AE4: 2023/12/11 2026/03/01 | AF4: 45311 | AH4: 一時帰国予定 | AL4: 〇 | AM4: ２018/10/30 | AN4: 2025/8/1～2029/9/30 | AO4: 伊予銀 | AP4: ※特定技能申請の為、ﾊﾟｽﾎﾟｰﾄと在留ｶｰﾄﾞは中四国預かり（6/13朴さんより） 2024.6.12～社員コード変わる済（特定活動になるため） 2024.6.12～9.12実習3号→特定活動 9/12～特定技能へ ※特定活動（6ヵ月）申請しその期間に特定技能へ変更予定。 2026/5/4出産予定日 一時帰国し出産予定。2026/3/24～6/29産休 6/30～2027/5/3育休
A5: 四課 | B5: 96 | C5: 津吉 | D5: インドネシア | E5: 07013638 | F5: /appsheet/photograph/IDPhoto_20250328_96_ニマトゥル マウリダ.jpg | G5: ニマトゥル マウリダ | H5: NIMATUL MAULIDA | J5: 女 | K5: 35621 | L5: =DATEDIF(K5,TODAY(),"Y") -> 28 | M5: 有 | N5: H&C | O5: 45075 | P5: 2028/04 | Q5: 特定技能１号 | R5: 松山市上野町774番地ビレッジハウス松山上野4-504 | S5: 夫婦 | T5: 20000 | U5: 45762 | V5: 46184 | W5: UH01039353PC | Z5: 自身で購入 元2309 中野住宅で使用 | AA5: 45555 | AB5: N3 2024/07/07 | AE5: 45783 | AF5: 45817 | AK5: 大西係長 | AL5: 〇 | AM5: 45071 | AN5: 2025/6/25-2028/5/24 | AP5: N3：2024/07/07 10/15連絡あり→10/31振込分より手当 2025/5/6～6/10一時帰国 帰国後 6/9～ﾋﾞﾚｯｼﾞ4-504へ夫エカと住む 2025/11/2エカより、ニマが妊娠13週との連絡あり。今後について、相談すると伝える エカと３人で津吉社長室にて話す。 出産予定2026/5/5、つばきウイメンズで出産予定。 日本にて産みたい。 エカも特定２号受けたい。入社が2025/6/17 転職のため、特定１号の期限が2027/3までのため、入官へ確認。
B6: 50 | C6: 津吉 | D6: ベトナム | E6: 07012625 07017701 | F6: /appsheet/photograph/50.写真.031439.jpg | G6: チャン ティー トゥータオ | H6: TRAN THI THU THAO | I6: タオ | J6: 女 | K6: 35807 | L6: =DATEDIF(K6,TODAY(),"Y") -> 28 | M6: 夫婦 | N6: デルタ四国 | O6: 44566 | P6: 2026/12 | Q6: 特定技能２号 | R6: 松山市上野町774番地ビレッジハウス松山上野2-507 | S6: 個 | T6: 20000 | U6: 45962 | V6: 47102 | W6: UH79100289PC | X6: 5099-602786-1 | AD6: 45756 | AE6: 45756 | AF6: 45794 | AG6: 45796 | AL6: ― | AO6: ひめぎん 末広町支店 | AP6: 自身の結婚の為一時帰国 勤務再開2025/5/19 一時退職のため、社員ｺｰﾄﾞ変更予定 2025.7.24給与口座を伊予銀行→ひめぎんへ変更したいとのこと。中温経由であれば一時的なことではなく、給与振込口座として作成するのであれば可能とのひめぎんより回答あり。 9月分の給料よりひめぎんへ変更。 在留ｶｰﾄﾞ更新申請中。更新後の在留ｶｰﾄﾞをひめぎんへ提出（ﾃﾞﾙﾀ・松岡さんへ伝え済8月末～9月頃予定） 伊予銀口座解約⇒仕事が忙しく休みが取れない為、年末までには銀行へ行く予定 2025/10 特定2号試験合格。早急に2号に移行したいとの回答。2号移行後は弊社の自社支援となる（ﾃﾞﾙﾀ松岡さんより10/27） 2025/12/21～特定2号へ移行予定 2025/11/12昨日、病院へ行って妊娠４週ぐらい。まだ小さいため、安定したら再度話す。新開工場長へは連絡済み 2025/12/15 特定2号へ移行完了 ブイよりタオが妊娠。出産予定9月。西条工場へ夫婦で行く予定のため、病院で迷っている。現在つばきウィメンズクリニック。後日相談 | AQ6: /appsheet/photograph/07012625.在留カード表裏.082059.pdf | AR6: 管理表_Files_/07012625.パスポート.070534.pdf
A7: 一課 | B7: 112 | C7: 津吉 | D7: インドネシア | E7: 07013654 | F7: /appsheet/photograph/112.写真.032346.jpg | G7: インギト チカ プテリ アディティヤン | H7: INGGIT CIKA PUTRI ADITIYAN | J7: 女 | K7: 38049 | L7: =DATEDIF(K7,TODAY(),"Y") -> 22 | M7: 有 | N7: H&C | O7: 45210 | P7: 2028/09 | Q7: 特定技能１号 | R7: 松山市松末2丁目16-17グレースフルハイツ203号 | S7: 夫婦 | T7: 0 | U7: 45908 | V7: 46359 | W7: UH63905058PC | Z7: 2330 B-0304391-V134 | AE7: 45878 | AF7: 45912 | AI7: 46101 | AJ7: 松山で出産 | AK7: 小林主任 | AL7: 〇 | AM7: 45207 | AN7: 2025/6/1～2028/10/31 | AP7: 2025.4/2新開工場長より７月～旦那（松山在住）と一緒に住みたい、 2025/6/20引越予定。ご主人名義で借りる予定。決まったら連絡が入る。（久米方面）8/11～9/12結婚のため帰国予定 2025.6.20引越 牛渕123-1→松山市松末２丁目１６－１７ココウミン（ご主人名義で借りる）へ引越 2025.7月結婚予定 ご主人：ココウミン（中国人） 勤務先：三菱自動車（技術者）090-3965-1989 在留資格：技術、人文知識、国際業務 2025/12/2新開工場長より、妊娠したとの申し出あり。 | AQ7: /appsheet/photograph/07013654.在留カード表裏.072122.pdf
B10: 28 | C10: 本社 | D10: ベトナム | E10: 07001609 | F10: /appsheet/photograph/IDPhoto_20240711_マイン.jpg | G10: トー マイン トゥ | H10: TO MANH TU | I10: マイン | J10: 男 | K10: 34747 | L10: =DATEDIF(K10,TODAY(),"Y") -> 31 | N10: 中四国 | O10: 44119 | P10: 2028/08 | Q10: 特定技能１号 | R10: 小栗1丁目3-30ﾋﾟｯｺﾛｶｽﾀｰﾆｬ308 | S10: 個 | T10: 20000 | U10: 45484 | V10: 45912 | W10: SA48074257PA | X10: 5109-022627-2 | Z10: 2020/10購入 B-0177518-1040 | AD10: 45306 | AE10: 45306 | AF10: 45341 | AG10: 45343 | AH10: 退職 | AI10: 45904 | AK10: 2025/9/4退職・9/5退寮 | AO10: 特定技能1号期間更新中 24.7.11 2025.8月か9月頃に帰国希望（工場長より） 2025/08/31ピッコロ解約し、9/5退職9/9頃帰国 9/1～9/5アトム 9/4退職、9/5退寮 有給残10日あり ※最終出勤日8/27 9/5現金払い
A11: =_xludf.IMAGE("F96",1) -> #NAME? | B11: 3 | C11: 津吉 | D11: ベトナム | E11: 07011602 | F11: /appsheet/photograph/3.写真.030343.jpg | G11: グエン ビック フーン | H11: NGUYEN BICH PHUONG | I11: フーン | J11: 女 | K11: 31664 | L11: =DATEDIF(K11,TODAY(),"Y") -> 39 | M11: 有 | N11: 中四国 | O11: 43040 | P11: 2027/01 | Q11: 特定技能１号 | R11: 松山市津吉町535-1コーポ津吉1-2 | S11: 個 | T11: 20000 | U11: 45569 | V11: 46327 | W11: UH17492757PC | X11: 5100-318256-3 | Z11: 通勤は自転車B-0128657 白26ｲﾝﾁABELIA 買い物と外出時は ｱｼｽﾄ自転車（知人から貰った） | AE11: 45711 | AF11: 45732 | AH11: 退職 | AI11: 46066 | AJ11: 帰国 帰国費用会社負担 | AL11: 〇 | AM11: 44866 | AN11: 2025/8/1～2026/7/31 ※2026年に帰国予定の 為、本人より1年間の契約 希望 | AO11: ひめぎん 末広町支店 | AP11: 2/20まで出勤・3/17より出勤 2026/2月に退職して帰国したい申し出。 新開工場長へ連絡済み。帰りの飛行機代を確認依頼。 飛行機代は会社負担（専務へ確認済11/19）
A12: 一課 | B12: 112 | C12: 津吉 | D12: インドネシア | E12: 07013654 | F12: /appsheet/photograph/112.写真.032346.jpg | G12: インギト チカ プテリ アディティヤン | H12: INGGIT CIKA PUTRI ADITIYAN | J12: 女 | K12: 38049 | L12: =DATEDIF(K12,TODAY(),"Y") -> 22 | M12: 有 | N12: H&C | O12: 45210 | P12: 2028/09 | Q12: 特定技能１号 | R12: 松山市松末2丁目16-17グレースフルハイツ203号 | S12: 夫婦 | T12: 0 | U12: 45908 | V12: 46359 | W12: UH63905058PC | Z12: 2330 B-0304391-V134 | AE12: 45878 | AF12: 45912 | AH12: 退職予定 | AI12: 46101 | AJ12: 出産 | AK12: 小林主任 | AL12: 〇 | AM12: 45207 | AN12: 2025/6/1～2028/10/31 | AP12: 2025.4/2新開工場長より７月～旦那（松山在住）と一緒に住みたい、 2025/6/20引越予定。ご主人名義で借りる予定。決まったら連絡が入る。（久米方面）8/11～9/12結婚のため帰国予定 2025.6.20引越 牛渕123-1→松山市松末２丁目１６－１７ココウミン（ご主人名義で借りる）へ引越 2025.7月結婚予定 ご主人：ココウミン（中国人） 勤務先：三菱自動車（技術者）090-3965-1989 在留資格：技術、人文知識、国際業務 2025/12/2新開工場長より、妊娠したとの申し出あり。 | AQ12: /appsheet/photograph/07013654.在留カード表裏.072122.pdf
B13: 146 | C13: 本社 | D13: ベトナム | E13: 08004401 | F13: /appsheet/photograph/146.写真.035436.jpg | G13: チン グエン ザー ハン | H13: TRINH NGUYEN GIA HAN | I13: グエン | J13: 女 | K13: 38293 | L13: =DATEDIF(K13,TODAY(),"Y") -> 21 | M13: 無 | N13: 関東食肉 | O13: 45086 | P13: 2026/05 | Q13: 技能実習2号 | R13: 和泉北1-20-28アトムスカイマンション602 | S13: 相1 | T13: 10000 | U13: 44876 | V13: 46172 | W13: UH53838943PC | Z13: 2319 B-029656-X199 | AH13: 退職予定 | AI13: 46150 | AJ13: 実習2号終了で 転職 | AM13: ― | AN13: ― | AP13: 2024.5.9～実習2号へ 2026/5/8実習2号終了で退職（転職）
B14: 152 | C14: 協同本社 | D14: ベトナム | E14: 18001401 | F14: /appsheet/photograph/小栗_ズエン_20240426.jpg | G14: グエン ティ ホン ズエン | H14: NGUYEN THI HONG DUYEN | I14: ズエン | J14: 女 | K14: 37596 | L14: =DATEDIF(K14,TODAY(),"Y") -> 23 | N14: 中四国 | O14: 45159 | P14: 2026/07 | Q14: 技能実習2号 | R14: 和泉北1-20-28アトムスカイマンション304 | S14: 相2 | T14: 10000 | U14: 44986 | V14: 46225 | W14: UH52998254EA | Z14: 2326-B-0302681 | AC14: 缶詰巻締初級 2024.3.7 | AH14: 退職予定 | AI14: 46192 | AJ14: 実習2号終了で 退職（帰国） | AK14: 6/19退職、6/22現金給与6/23帰国 | AM14: ― | AN14: ― | AP14: 2024.7.21～実習1号→2号へ パスポートと在留カード中四国預かり2025.5.16
B15: 198 | C15: 津吉 | D15: ベトナム | E15: 07012622 | F15: /appsheet/photograph/198.写真.035844.jpg | G15: グエン タイン チャン | H15: NGUYEN THANH TRANG | J15: 女 | K15: 32413 | L15: =DATEDIF(K15,TODAY(),"Y") -> 37 | M15: 無 | N15: デルタ四国 | O15: 45733 | P15: 47543 | Q15: 特定技能１号 | R15: 松山市上野町774番地ビレッジハウス松山上野2-506 | S15: 個 | T15: 15000 | U15: 45646 | V15: 46094 | W15: UH79915241MA | Y15: 45726 | Z15: アベリア 赤 B-0357434-V030 | AH15: 退職予定 | AI15: 46105 | AJ15: 転職 | AP15: 2024/11/29面接 合格 子宮筋腫の為、2025/11/16入院（県病院）、11/17手術、11/20退院予定。12/20まで自宅療養。12/21～就労可能。病院から連帯保証人を弊社で対応（専務確認済）傷病手当申請予定。 デルタより子宮筋腫の手術に伴い体調が優れない為、業務量の少ない業種へ転職希望とのことで退職の申し出あり。2026/3/24退職希望、退寮日未定。（2026/2/20）
A16: 箱入れ | B16: 113 | C16: 津吉 | D16: インドネシア | E16: 07013655 | F16: /appsheet/photograph/113.写真.031538.jpg | G16: リズカ スティヤニンシー | H16: RIZKA SETYANINGSIH | I16: リズカ | J16: 女 | K16: 36058 | L16: =DATEDIF(K16,TODAY(),"Y") -> 27 | N16: H&C | O16: 45210 | P16: 2028/09 | Q16: 特定技能１号 | R16: 東温市牛渕123-1 | S16: 2F-1-相4 | T16: 10000 | U16: 45908 | V16: 46359 | W16: UH29571459PC | Z16: 2332 B-0304393-V102 元2331 | AE16: 46005 | AF16: 46032 | AH16: 退職予定 | AI16: 46132 | AJ16: 転職 | AK16: 水沼主任 | AL16: 〇 | AM16: 45207 | AN16: 2025/6/1～2028/10/31 | AP16: 母親が手術のため、一時帰国を希望 2025/12/14～2026/1/10まで | AQ16: /appsheet/photograph/07013655.在留カード表裏.072154.pdf
B17: 121 | C17: 津吉 | D17: インドネシア | E17: 07013663 | F17: /appsheet/photograph/121.写真.032211.jpg | G17: デヴィ メルヴァ ヤヌアル | H17: DEVI MELVA YANUAR | J17: 女 | K17: 35433 | L17: =DATEDIF(K17,TODAY(),"Y") -> 29 | M17: 有 | N17: H&C | O17: 45216 | P17: 2028/09 | Q17: 特定技能１号 | R17: 東温市牛渕170-3 | S17: 離2F-1-個1 | T17: 15000 | U17: 45908 | V17: 46359 | W17: UH70743274PC | Z17: 2339 Ｂ－0304392-V135 | AA17: 45931 | AE17: 46005 | AF17: 46032 | AH17: 退職予定 | AI17: 46132 | AJ17: 転職 | AK17: 小林主任 | AL17: 〇 | AN17: 2025/6/1～2028/10/31 | AP17: 2025/12/15-2026/01/9一時帰国希望 | AQ17: /appsheet/photograph/07013663.在留カード表裏.072405.pdf
B18: 172 | C18: 津吉 | D18: インドネシア | E18: 07013679 | G18: イーサン シハブ ギッファリ | H18: IHSAN SHIHAB GIFFARI | I18: イーサン | J18: 男 | K18: 35739 | L18: =DATEDIF(K18,TODAY(),"Y") -> 28 | M18: 無 | N18: H&C | O18: 45594 | P18: 47362 | Q18: 特定技能１号 | R18: 松山市上野町774番地ビレッジハウス松山上野4-501 | S18: 個 | T18: 15000 | U18: 45870 | V18: 46322 | W18: UH28839412PC | Z18: 202409購入 26シルバー B-0343703-X157 | AH18: 退職予定 | AI18: 46132 | AJ18: 転職 | AK18: 大西係長 | AL18: ― | AN18: ― | AQ18: /appsheet/photograph/07013679.在留カード表裏.061911.pdf
B20: 130 | C20: 津吉 | D20: ベトナム | E20: 07011608 | F20: /appsheet/photograph/130.写真.jpg | G20: ズオン デ タオ | H20: DUONG DE THAO | I20: デ タオ | J20: 男 | K20: 34053 | L20: =DATEDIF(K20,TODAY(),"Y") -> 33 | M20: 夫婦 | N20: 中四国 | O20: 45301 | P20: 2029/01 | Q20: 特定技能１号 | R20: 松山市上野町774番地ビレッジハウス松山上野1-303 | S20: 夫婦 | T20: 0 | U20: 45611 | V20: 46036 | W20: UH56662900PA | X20: 寮24.1/9～ | Z20: ﾊﾞｲｸ通勤ﾎﾝﾀﾞDIO 110cc 第2種の甲）2024.5.21～ 2024/09/25車通勤ムーヴ 愛媛581の9211 822301129470 車検2026/03/05保険27/09/07 2025/4/3車両変更愛媛581ひ4257 | AA20: 入社時会社から 自転車支給なし | AE20: 45727 | AF20: 45746 | AI20: 2025/10/31～ 2026/1/31育休 | AL20: × | AN20: × | AP20: 2024.6.23車の免許取得予定 １９ファムティチンの夫 ﾊﾞｲｸ通勤届提出済5/2通勤手当5/21～変更（6月分の給料より） 2024.5.2 入社時自身で自転車を持ってきている 2024/09/28ヴィレッジ駐車場契約P1-063 月4,400円実費負担 2024/09/25車通勤届受領 2025/8/4車を買替予定とのこと。車庫証明の件でビレッジの管理人さんへ問合せありとのこと 2025.9.5引越 チン名義で借りる。ビレッジ1-303へ 2025/11/4～12/4育休 →延長1/4 →延長1/31
B24: 140 | C24: 津吉 | D24: ベトナム | E24: 07011409 | G24: ファム ティ フエン チャン | H24: PHAM THI HUYEN TRANG | I24: フェンチャン | J24: 女 | K24: 33874 | L24: =DATEDIF(K24,TODAY(),"Y") -> 33 | N24: 中四国 | O24: 44699 | P24: 2025/04 | Q24: 特定技能１号 | R24: 津吉町535-1コーポ津吉2-4 | T24: 10000 | U24: 44193 | V24: 45764 | W24: SA11837284PA | Z24: 自身で購入（ｱｼｽﾄ自転車） B-0304584 白・銀ﾊﾟﾅｿﾆｯｸ ﾋﾞﾋﾞDX 7913-B-0227913赤24ｲﾝﾁ | AA24: 会社支給の自転車 は使用していない ｺｰﾎﾟ津吉にあり | AC24: 缶詰巻締専門 2024/09/12 | AE24: 46049 | AF24: 46087 | AH24: 一時帰国 | AI24: 帰国後、 在留ｶｰﾄﾞ更新 | AJ24: 実習終了に伴い会社負担 | AK24: 24.3.21～ﾁｭｵﾝﾃｨﾄｩｰと同部屋へ引越。家賃は同じ 2025/04特定技能申請、実習終了に伴い2025/06頃一時帰国予定 日程は調整40日程度が妥当
B25: 207 | C25: 本社 | D25: ベトナム | E25: 07001628 | F25: /appsheet/photograph/207.写真.084711.jpg | G25: チャン ティ ヌー | H25: TRAN THI NU | I25: ヌー | J25: 女 | K25: 35882 | L25: =DATEDIF(K25,TODAY(),"Y") -> 28 | M25: 有 | N25: 中四国 | O25: 45890 | P25: 47665 | Q25: 特定技能１号 | R25: 和泉北1-20-28アトムスカイマンション402 | S25: 個3 | T25: 20000 | U25: 45772 | V25: 46254 | W25: UH65617663FA | Y25: 45889 | Z25: B-0247914-1017 | AE25: 46058 | AF25: 46088 | AH25: 一時帰国 | AI25: 帰国後、 在留ｶｰﾄﾞ更新 | AL25: 〇 | AM25: 45889 | AN25: 2025/9/15-2030/8/14 | AO25: 伊予銀 大街道支店 | AP25: 2025/3/27 合格 実習生2号修了者 2025.8.20入国、入寮・8/21入社 中四国は入国時のチケット手配まで（10万まで） →9/1中温へ切替予定 2026.6/15～7/30一時帰国希望（宮内工場長より2025/12/19） | AQ25: https://drive.google.com/file/d/1DApCPMDEH-5UElVN3J65K8_MTK6bl1JE/view?usp=sharing | AT25: /appsheet/photograph/07001628.通帳.010840.jpg | AU25: /appsheet/photograph/07001628.保険証.010840.jpg
B26: 26 | C26: 津吉 | D26: ベトナム | E26: 07011606 | F26: /appsheet/photograph/26.写真.001347.jpg | G26: ヴー ティ ホアン | H26: VU THI HOAN | I26: ホアン | J26: 女 | K26: 32353 | L26: =DATEDIF(K26,TODAY(),"Y") -> 37 | M26: 有 | N26: 中四国 | O26: 45111 | P26: 2028/06 | Q26: 特定技能１号 | R26: 松山市津吉町535-1コーポ津吉1-2 | S26: 個 | T26: 20000 | U26: 45407 | V26: 46206 | W26: UH16081560PA | Z26: 2104 通勤、買い物も会社支給 の自転車使用 | AC26: 2026/1月２号試験希望_統括より | AE26: 2024/07/01 2026/01/24 | AF26: 2024/08/01 2026/03/21 | AH26: 一時帰国 | AL26: 〇 | AM26: 45110 | AN26: 2025/8/1～2028/6/30 | AP26: 24.7/3頃～8/5頃一時帰国 新開工場長へ申請あり4/24 →中四国 からの日程の連絡待ち。→6/30～7/31確定（6/19中四国より） 本人からの休暇届けは7/1～8/1一時帰国（全て有給申請）となって いるため、中四国廣瀬さんへ確認依頼済（6/28中に） 一時帰国後8/6以降順風会で健診予定 24.4月分～ﾎｱﾝﾃｨﾊﾝが入寮したら家賃2万→1万へ 2026.1月 特定2号受験予定
B27: 145 | C27: 本社 | D27: ベトナム | E27: 07001625 | F27: /appsheet/photograph/145.写真.224740.jpg | G27: クアン ティ ハー | H27: QUAN THI HA | I27: ハー | J27: 女 | K27: 33172 | L27: =DATEDIF(K27,TODAY(),"Y") -> 35 | N27: 中四国 | O27: 44706 | P27: 2030/04 | Q27: 特定技能１号 | R27: 和泉北1-20-28アトムスカイマンション401 | S27: 相3 | T27: 10000 | U27: 45684 | V27: 46133 | W27: UH29608234PA | Z27: 7920 B-0247920-1767 | AC27: 缶詰巻締専門 2024/09/12 | AE27: 2025/04/25 2026/02/14 | AF27: 2025/06/10 2026/03/14 | AH27: 一時帰国予定 | AL27: 〇 | AN27: 2025/8/1～2030/3/31 | AO27: ひめぎん 末広町支店 | AP27: 2025.4.21技能実習２号終了→特定技能１号 中温残る 実習終了後、一時帰国希望 協同物産→中温へ転籍
B28: 156 | C28: 津吉 | D28: ベトナム | E28: 07011610 | F28: /appsheet/photograph/156.写真.035952.jpg | G28: ファム ティ イエン | H28: PHAM THI YEN | I28: イエン | J28: 女 | K28: 30821 | L28: =DATEDIF(K28,TODAY(),"Y") -> 41 | M28: 無 | N28: 中四国 | O28: 45364 | P28: 2029/02 | Q28: 特定技能１号 | R28: 松山市上野町774番地ビレッジハウス松山上野1-303 | S28: チン名義で 借りている | T28: 0 | U28: 45681 | V28: 46093 | W28: UH23532383PA | Z28: 2202-V183 通勤、買い物も会社支給 の自転車使用 | AE28: 2025/03/16 2026/02/26 | AF28: 2025/03/30 2026/04/14 | AH28: 一時帰国予定 | AL28: 〇 | AN28: 2025/8/1～2029/2/28 | AP28: 2024/09/25コーポ津吉1-6よりビレッジ2-503へ引越→通勤届済 3/11～3/26一時帰国を変更 2025/09/05引越 ビレッジ1-303へ（チン名義で借りる） 2025/10/21～バイク通勤へ。通勤届提出待ち 10/24通勤届一式提出済 2026/3/1～家の建築のため一時帰国したい申出。新開工場長へ報告済みだが、本人より伝えるよう伝える。 | AQ28: /appsheet/photograph/07011610.在留カード表裏.063739.pdf | AR28: /appsheet/photograph/07011610.パスポート.063907.pdf
A29: 一課 | B29: 71 | C29: 津吉 | D29: インドネシア | E29: 07013632 | F29: /appsheet/photograph/71.写真.020439.jpg | G29: ファルハン ファティ ラマダンシャー | H29: FARHAN FATHI RAMADHANSYAH | J29: 男 | K29: 37928 | L29: =DATEDIF(K29,TODAY(),"Y") -> 22 | M29: 無 | N29: H&C | O29: 45027 | P29: 2028/03 | Q29: 特定技能１号 | R29: 松山市上野町774番地ビレッジハウス松山上野4-501 | S29: 個 | T29: 15000 | U29: 46082 | V29: 46172 | W29: UH58397878PC | Z29: 2304 B-0287295-V088 | AA29: 45715 | AE29: 46091 | AF29: 46164 | AK29: 小林主任 | AL29: ― | AM29: 45024 | AN29: ― | AP29: 自転車改造中で放置のため、管理人さんよりｸﾚｰﾑ H&Cより本人へ伝えてもらう現状復帰もしくは￥5000 3/27 2025/04/14処分 2025/2/21V2-405→V4-501へ引越 2025/5/9 11:00自宅にてGWに入り休んでいるので指導 2025/7/25中野クリニック受診予定 腰痛、眠れないので欠勤が続いているため
A30: 一課 | B30: 98 | C30: 津吉 | D30: インドネシア | E30: 07013640 | F30: /appsheet/photograph/IDPhoto_20250328_98_ノヴィ ノヴィタ.jpg | G30: ノヴィ ノヴィタ | H30: NOVI NOVITA | J30: 女 | K30: 38073 | L30: =DATEDIF(K30,TODAY(),"Y") -> 22 | M30: 無 | N30: H&C | O30: 45075 | P30: 2028/04 | Q30: 特定技能１号 | R30: 松山市上野町774番地ビレッジハウス松山上野4-502 | S30: 個 | T30: 15000 | U30: 45762 | V30: 46184 | W30: UH31391623PC一時帰国後、申請 | X30: 寮23.10/21～ | Z30: 自身で購入 | AE30: 46093 | AF30: 46122 | AH30: 一時帰国予定 | AK30: 小林主任 | AL30: 〇 | AM30: 45071 | AN30: 2025/6/１～2028/5/31" | AP30: 2025/3/29～1号館1人部屋→ビレッジ4-502へ 家賃同額
A31: 四課 | B31: 99 | C31: 津吉 | D31: インドネシア | E31: 07013641 | F31: /appsheet/photograph/IDPhoto_20250328_99_ヌル アンディニ.jpg | G31: ヌル アンディニ | H31: NUR ANDINI | I31: アンディニ | J31: 女 | K31: 37451 | L31: =DATEDIF(K31,TODAY(),"Y") -> 23 | N31: H&C | O31: 45075 | P31: 2028/04 | Q31: 特定技能１号 | R31: 松山市上野町774番地ビレッジハウス松山上野4-205 | S31: 個 | T31: 15000 | U31: 45762 | V31: 46184 | W31: UH20712284PC一時帰国後、申請 | Z31: 2312 B-0287451-V177 | AA31: 45993 | AE31: 46093 | AF31: 46154 | AH31: 一時帰国予定 | AK31: 大西係長 | AL31: 〇 | AM31: 45071 | AN31: 2025/6/１～2028/5/31 | AP31: 20240529退勤中に最後の階段で足をくじいた。 2024/09/14牛渕170-3→ビレッジ4-205引越 2025/10/30新開工場長より、2026/3/13より2ヶ月ぐらい、 自身の結婚のため帰国の申し出。日程の調整確認依頼 10/30現在有休残３日、11/29付与12日、合計15日 新開工場長へline済み 3/13結婚のため、一時帰国。5/10頃帰国し 在留カード更新手続きを行うと話す。
A32: 一課 | B32: 128 | C32: 津吉 | D32: インドネシア | E32: 07013628 | F32: /appsheet/photograph/128.写真.033250.jpg | G32: アリ クスナディ | H32: ALI KUSNADI | I32: アリ | J32: 男 | K32: 36345 | L32: =DATEDIF(K32,TODAY(),"Y") -> 26 | N32: H&C | O32: 44937 | P32: 2027/12 | Q32: 特定技能１号 | R32: 松山市上野町774番地ビレッジハウス松山上野1-507 | S32: 個 | T32: 15000 | U32: 46082 | V32: 46432 | W32: LJ02919901PC | Z32: 2212 元2211 | AE32: 2024/07/02 2026/3/14 | AF32: 2024/07/30 2026/4/21 | AK32: 小林主任 | AL32: 〇 | AM32: 44922 | AN32: 2025/6/１～2027/12/31 | AP32: 一時帰国後8/1以降順風会で健診予定 一時帰国希望あり。有休残日数と次回の付与日で検討とのこと（24.4.23H&C三好さん より）一時帰国の内20日間は有給使用予定（5/9三好さんより） 2026/特定2号受験予定 | AQ32: /appsheet/photograph/07013628.在留カード表裏.015539.pdf | AW32: /appsheet/photograph/07013628.特定２号合格.011218.pdf
B33: 154 | C33: 本社 | D33: ベトナム | E33: 07001608 07007700 | F33: /appsheet/photograph/154.写真.225227.jpg | G33: グエン タイン チュン | H33: NGUYEN THANH TRUNG | I33: チュン | J33: 男 | K33: 35191 | L33: =DATEDIF(K33,TODAY(),"Y") -> 29 | M33: 夫婦 | N33: 中四国 | O33: 45159 | P33: 2026/01 | Q33: 特定技能２号 | R33: 和泉北1-20-28アトムスカイマンション305 | S33: 夫婦 | T33: 20000 | U33: 45962 | V33: 47102 | W33: UH75026157PC | Z33: 2325-B-0302682 | AB33: N3 2024/07/07 | AC33: 源泉徴収 | AD33: 45271 | AE33: 2023/12/11 2026/04/22 | AF33: 2024/01/20 2026/06/10 | AG33: 45313 | AH33: 一時帰国予定 | AL33: ― | AM33: 43117 | AN33: 2025/8/1～2025/12/31 2号移行時解約済 | AO33: 伊予銀 | AP33: 特定技能1号期間更新中 24.7.11 23.12/11一時退職 23.12/11～1/20一時帰国 2025/09/11～特定技能１号 特定2号を受験する場合、1号を1年間延長可能。 2025/12/21～特定2号へ資格変更予定 2025/12/15 特定2号へ移行完了 2026/4/22～6/10一時帰国（育休） | AQ33: /appsheet/photograph/07001608.在留カード表裏.082310.pdf | AR33: 管理表_Files_/07001608.パスポート.070219.pdf
A34: 四課 | B34: 85 | C34: 津吉 | D34: インドネシア | E34: 07013614 | F34: /appsheet/photograph/IDPhoto_20250328_85_コフィファー ヌル コエリヤー.jpg | G34: コフィファー ヌル コエリヤー | H34: KHOFIFAH NUR KHOERIYAH | I34: コフィ | J34: 女 | K34: 36874 | L34: =DATEDIF(K34,TODAY(),"Y") -> 25 | N34: H&C | O34: 44669 | P34: 2027/03 | Q34: 特定技能１号 | R34: 松山市上野町774番地ビレッジハウス松山上野4-502 | S34: 個 | T34: 15000 | U34: 45762 | V34: 46184 | W34: UH31691579PC | Z34: 自身で購入 | AE34: 2025/01/31 2026/04/20 | AF34: 2025/03/03 2026/06/03 | AH34: 一時帰国予定 | AI34: 帰国前 在留ｶｰﾄﾞ更新 | AK34: 大西係長 | AM34: 44661 | AN34: 2022/04/10-2027/04/09 | AP34: 最終出勤日1/30 2025/1/31～3/3一時帰国 1/21～1/30まで勤務の為控除無し及びH&C管理住宅 結婚のため、2026/04/20～6/3まで一時帰国希望 （新開工場長より2025/12/23）
A35: 一課 | B35: 162 | C35: 津吉 | D35: インドネシア | E35: 07013669 | F35: /appsheet/photograph/162.写真.031335.jpg | G35: アプリヨノ | H35: APRILIYONO | J35: 男 | K35: 37734 | L35: =DATEDIF(K35,TODAY(),"Y") -> 22 | N35: H&C | O35: 45376 | P35: 2029/02 | Q35: 特定技能１号 | R35: 松山市上野町774番地ビレッジハウス松山上野3-508 | S35: 個 | T35: 15000 | U35: 46047 | V35: 46135 | W35: UH04955658PC | Y35: 45376 | Z35: 2405-Ｂ－0325669 | AB35: N3 2025/07 | AE35: 46144 | AF35: 46175 | AH35: 一時帰国予定 | AK35: 小林主任 | AL35: 〇 | AM35: 45373 | AN35: 2025/6/1～2029/3/31 | AP35: 2024.5.8引越ﾋﾞﾚｯｼﾞﾊｳｽ4-507→ﾋﾞﾚｯｼﾞﾊｳｽ3-508へ 24.3.22入寮予定⇒ｲﾝﾌﾙｴﾝｻﾞの為、ﾋﾞｼﾞﾈｽﾎﾃﾙ で待機後3/26～入寮 N3手当2025.9月給料～￥5000 2026/5/2～6/2まで一時帰国予定。新開工場長へ 許可をもらったとのこと。チケット送付依頼
A36: 四課 | B36: 173 | C36: 津吉 | D36: インドネシア | E36: 07013680 | F36: /appsheet/photograph/173.写真.032032.jpg | G36: リザル ムハマド フィルダウス | H36: RIZAL MUHAMAD FIRDAUS | I36: リザル | J36: 男 | K36: 36905 | L36: =DATEDIF(K36,TODAY(),"Y") -> 25 | M36: 無 | N36: H&C | O36: 45594 | P36: 47362 | Q36: 特定技能１号 | R36: 松山市上野町774番地ビレッジハウス松山上野2-508 | S36: 個 | T36: 15000 | U36: 45870 | V36: 46322 | W36: UH14292148PC | Z36: 202409購入 26シルバー B-0343704-X240 | AE36: 46148 | AF36: 46179 | AH36: 一時帰国予定 | AK36: 大西係長 | AL36: 〇 | AN36: 2025/6/1～2029/10/31 | AP36: 2026/1/23新開工場長より、5/6～6/6まで一時帰国のメールあり。
B37: 131 | C37: 本社 | D37: ベトナム | E37: 07001618 | F37: /appsheet/photograph/131.写真.225308.jpg | G37: グエン タン ロン | H37: NGUYEN THANG LONG | I37: ロン | J37: 男 | K37: 36864 | L37: =DATEDIF(K37,TODAY(),"Y") -> 25 | M37: 無 | N37: 中四国 | O37: 44699 | P37: 2030/04 | Q37: 特定技能１号 | R37: 和泉北1-20-28アトムスカイマンション404 | S37: 個1 | T37: 20000 | U37: 46082 | V37: 46171 | W37: UH94536849PA | Y37: 45978 | Z37: 7909-202511盗難届済 B-0247909-1593鍵回収 代替B-0246656-1610 | AC37: 缶詰巻締専門 2024/09/12 | AE37: 2025/04/15 2026/5月頃 | AF37: 2025/05/19 2026/●月？ | AJ37: 4/15広島→ハノイ 42,000-会社負担 実習終了帰国 | AL37: ― | AN37: ― | AP37: 転職希望（大阪へ）× 中温残る 実習終了→特定技能申請中（2025.5） 2025.4.15～5.19一時帰国 2025.5.28～特定技能1号へ 社員ｺｰﾄﾞ変わる 2025/8/21～家賃20,000-
B38: 10 | C38: 本社 | D38: ベトナム | E38: 07001613 | F38: /appsheet/photograph/10.写真.032947.jpg | G38: グエン ティ ロアン | H38: NGUYEN THI LOAN | I38: ロアン | J38: 女 | K38: 31701 | L38: =DATEDIF(K38,TODAY(),"Y") -> 39 | M38: 有 | N38: 中四国 | O38: 43435 | P38: 2025/09 | Q38: 特定技能１号 | R38: 和泉北1-20-28アトムスカイマンション403 | S38: 個1 | T38: 20000 | U38: 45870 | V38: 46294 | W38: UH51964624PC | X38: 5103-260926-8 | Z38: 1968-B-0091968 2024/08/27自転車変更 7912(1596)赤へ 2025/08/27変更 B-0246665-1008 | AD38: 45317 | AE38: 2024/01/27 2026/5月頃 | AF38: 2024/02/27 2026/7月頃 | AG38: 45350 | AL38: 〇 | AM38: 43403 | AN38: 2025/8/1～2029/5/31 | AO38: 伊予銀 湊町支店 | AP38: ※特定技能申請の為、ﾊﾟｽﾎﾟｰﾄと在留ｶｰﾄﾞは中四国預かり（6/13朴さんより） 2024.6.12～社員コード変わる済（特定活動になるため） 2024.6.12～9/152実習3号→特定活動 9/12～特定技能へ ※特定活動（6ヵ月）申請しその期間に特定技能へ変更予定。 2022.7.18一時退職8/9～一時帰国 2024.1.26一時退職 2025/10/4 2～3年前から週に5日程下痢が続いているため、窪田クリニックを受診。便検査の結果、病原性大腸菌O-18が見つかり、ベロ毒素の検査結果は陰性。（陽性であれば保健所に届け出が必要とのこと）。除菌のため、抗生物質の薬を5日服用し、5日後に再度便検査を病院でする予定。 | AT38: /appsheet/photograph/07001613.通帳.040920.jpg
B39: 207 | C39: 本社 | D39: ベトナム | E39: 07001628 | F39: /appsheet/photograph/207.写真.084711.jpg | G39: チャン ティ ヌー | H39: TRAN THI NU | I39: ヌー | J39: 女 | K39: 35882 | L39: =DATEDIF(K39,TODAY(),"Y") -> 28 | M39: 有 | N39: 中四国 | O39: 45890 | P39: 47665 | Q39: 特定技能１号 | R39: 和泉北1-20-28アトムスカイマンション402 | S39: 個3 | T39: 20000 | U39: 45772 | V39: 46254 | W39: UH65617663FA | Y39: 45889 | Z39: B-0247914-1017 | AE39: 2026/02/05 2026/06/15 | AF39: 2026/03/07 2026/08/02 | AH39: 一時帰国予定 | AI39: 帰国後、 在留ｶｰﾄﾞ更新 | AL39: 〇 | AM39: 45889 | AN39: 2025/9/15-2030/8/14 | AO39: 伊予銀 大街道支店 | AP39: 2025/3/27 合格 実習生2号修了者 2025.8.20入国、入寮・8/21入社 中四国は入国時のチケット手配まで（10万まで） →9/1中温へ切替予定 2026.6/15～7/30一時帰国希望（宮内工場長より2025/12/19） | AQ39: https://drive.google.com/file/d/1DApCPMDEH-5UElVN3J65K8_MTK6bl1JE/view?usp=sharing | AT39: /appsheet/photograph/07001628.通帳.010840.jpg | AU39: /appsheet/photograph/07001628.保険証.010840.jpg
A40: 箱入れ | B40: 72 | C40: 津吉 | D40: インドネシア | E40: 07013633 | F40: /appsheet/photograph/72.写真.031751.jpg | G40: ナナ マルディアナ | H40: NANA MARDIANA | J40: 男 | K40: 37994 | L40: =DATEDIF(K40,TODAY(),"Y") -> 22 | N40: H&C | O40: 45027 | P40: 2028/03 | Q40: 特定技能１号 | R40: 松山市上野町774番地ビレッジハウス松山上野3-507 | S40: 個 | T40: 15000 | U40: 44940 | V40: 46172 | W40: UH92389157PC | Z40: 自身で購入 元2305-V084 | AE40: 46221 | AF40: 46269 | AH40: 一時帰国予定 | AK40: 水沼主任 | AL40: 〇 | AM40: 45024 | AN40: 2025/6/１～2028/4/30 | AP40: 2024/11/09 ビレッジハウス上野2-405⇒3-507へ移動 2025/11/25ナナより、デウィマシトと来年結婚する。 2026/7/18～9/4まで帰国結婚、中温で２人で住居したい申出。 日程については、新開工場長と相談済。
A41: 四課 | B41: 104 | C41: 津吉 | D41: インドネシア | E41: 07013646 | F41: /appsheet/photograph/104.写真.024225.jpg | G41: デウィ マシト | H41: DEWI MASITHOH | J41: 女 | K41: 36801 | L41: =DATEDIF(K41,TODAY(),"Y") -> 25 | N41: H&C | O41: 45098 | P41: 2028/05 | Q41: 特定技能１号 | R41: 松山市上野町774番地ビレッジハウス松山上野4-407 | S41: 個 | T41: 15000 | U41: 45793 | V41: 46214 | W41: UH49694920PC | Z41: 自身で購入 元2317-X236 | AE41: 46221 | AF41: 46269 | AH41: 一時帰国予定 | AK41: 大西係長 | AL41: 〇 | AM41: 45092 | AN41: 2025/6/１～2028/6/30 | AP41: 2024.6.21～牛渕123-1→ﾋﾞﾚｯｼﾞ4-407へ引越 2025/11/25ナナマルディアナと来年結婚する。 2026/7/18～9/4まで帰国結婚、中温で２人で住居したい申出。 日程については、新開工場長と相談済。
A42: 一課 | B42: 125 | C42: 津吉 | D42: インドネシア | E42: 07013625 | F42: /appsheet/photograph/125.写真.033225.jpg | G42: ミフタフディン ラティフ | H42: MIFTAHUDIN LATIF | I42: ラティフ | J42: 男 | K42: 35992 | L42: =DATEDIF(K42,TODAY(),"Y") -> 27 | N42: H&C | O42: 44937 | P42: 2027/12 | Q42: 特定技能１号 | R42: 松山市上野町774番地ビレッジハウス松山上野1-507 | S42: 個 | T42: 15000 | U42: 45976 | V42: 46067 | W42: UH84235418PC | X42: 23.5/18自転車鍵紛失 | Z42: 2208 B-0274812-V023 | AE42: 46224 | AF42: 46285 | AH42: 一時帰国予定 | AK42: 小林主任 | AL42: ― | AN42: ― | AP42: ミャナと結婚の為、2026/7/21～9/20まで 一時帰国希望。新開工場長より2025/12/22
A43: 四課 | B43: 186 | C43: 津吉 | D43: インドネシア | E43: 07013676 | F43: /appsheet/photograph/186.写真.024949.jpg | G43: ミャナ デウィ アフナン | H43: MYANA DEWI AFNAN | I43: ミャナ | J43: 女 | K43: 37822 | L43: =DATEDIF(K43,TODAY(),"Y") -> 22 | M43: 無 | N43: H&C | O43: 45587 | P43: 47362 | Q43: 特定技能１号 | R43: 松山市中野町368-6 | S43: 個 | T43: 20000 | U43: 45870 | V43: 46315 | W43: UH46862255PC | Z43: 旧2328 26シルバー B-0296140-V201 | AE43: 46224 | AF43: 46285 | AH43: 一時帰国予定 | AI43: 帰国後、 在留ｶｰﾄﾞ更新 | AK43: 大西係長 | AL43: 〇 | AM43: 45585 | AN43: 2025/6/1～2029/10/31 | AP43: 2025/9/21～1人部屋へ家賃￥20000へ 2025/10/21引越 中野①（中野町442-1）→中野③（中野町368-6）へ 家賃￥20,000-へ ラティフと結婚の為、2026/7/21～9/20まで 一時帰国希望。新開工場長より2025/12/22
B44: 163 | C44: 津吉 | D44: ベトナム | E44: 07011612 | F44: /appsheet/photograph/163.写真.032456.jpg | G44: ホアン ティ ハン | H44: HOANG THI HAN | I44: ハン | J44: 女 | K44: 32890 | L44: =DATEDIF(K44,TODAY(),"Y") -> 36 | M44: 有 | N44: 中四国 | O44: 45388 | P44: 2029/03 | Q44: 特定技能１号 | R44: 松山市津吉町535-1コーポ津吉1-2 | S44: 個 | T44: 20000 | U44: 46047 | V44: 47217 | W44: LJ41076546PC | Y44: 45386 | Z44: 2406-B-0274807 シルバー26ｲﾝﾁABELIA 買い物はｱｼｽﾄ自転車 茶 ﾔﾏﾊ ﾊﾟｽwith B-0175328 | AL44: 〇 | AM44: 45386 | AN44: 2025/8/1～2029/3/31 | AP44: 元ポエム 2024.4.4入寮 2026.1月 特定2号受験予定 | AQ44: /appsheet/photograph/07011612.在留カード表裏.062053.pdf | AR44: /appsheet/photograph/07011612.パスポート.062053.pdf
AL48: 2024.6.25入寮 ダットの奥さん 夫婦で一緒に住む
AL49: 特定技能1号期間更新中 24.7.11 2024.6.21～ｱﾄﾑ504→三和ﾏﾝｼｮﾝ末広201へ引越 6/26住所変更済（中四国で） 家賃￥21500/人。家具家電は会社負担 奥さんｱｲﾝと一緒に住む

Sheet 連絡事項
A2: 育児休暇 | B2: 07011609 | C2: 津吉 | D2: ディン ティ ヅエン | E2: 伊予郡砥部町高尾田826-1コーポ麻生205 | F2: 9/2～育児休暇 休暇中、中四国管理料月額10,000-
A4: 一時帰国 | B4: 07013637 | C4: 津吉 | D4: カデック アデリア ウィディアニタ レスタリ | E4: 松山市上野町774番地ビレッジハウス上野4-505 | F4: 9/7～9/28一時帰国→9/30より勤務確認
A6: 退職 | B6: 07012613 | C6: 津吉 | D6: チャン ヴァン ヒエン | E6: 松山市上野町774番地ビレッジハウス上野2-503 | F6: 2024/09/09退職 9/12退寮
B7: 07013658 | C7: 津吉 | D7: ラーミタ ヌル ハリザ | E7: 東温市牛渕123-1 | F7: 2024/09/29退職 10/3退寮
A9: 退寮 | B9: 07012613 | C9: 津吉 | D9: チャン ヴァン ヒエン | E9: 松山市上野町774番地ビレッジハウス上野2-503 | F9: 2024/09/12退寮
A11: 給料 | B11: 07001608 | C11: 小栗 | D11: グエン タイン チュン | E11: 和泉北1-20-28アトムスカイマンション305 | F11: N3合格 ５，０００円追加
B12: 07001608 | C12: 小栗 | D12: グエン タイン チュン | E12: 和泉北1-20-28アトムスカイマンション305 | F12: 8/21賃金改定 1,000円
B13: 07001612 | C13: 小栗 | D13: グエン ティ タム | E13: 和泉北1-20-28アトムスカイマンション304 | F13: 8/21賃金改定 1,050円 特定・N4
B14: 07001611 | C14: 小栗 | D14: ブイ ティ ミン | E14: 和泉北1-20-28アトムスカイマンション305 | F14: 8/21賃金改定 1,050円 特定・N4
B15: 07012613 | C15: 津吉 | D15: チャン ヴァン ヒエン | E15: 松山市上野町774番地ビレッジハウス上野2-503 | F15: 2024/09/末振込 9/12退寮
B16: 07012612 | C16: 津吉 | D16: グエン ゴック ガー | E16: 松山市上野町774番地ビレッジハウス上野2-506 | F16: N3合格 ５，０００円追加
A18: 引越 | B18: 07012614 | C18: 津吉 | D18: ハー ティ ヴァン | E18: 松山市上野町774番地ビレッジハウス上野2-508 | F18: 2024/10/４退職 9/末→2-506 3人部屋
B19: 07012606 | C19: 津吉 | D19: チャン クアン トゥアン | E19: 松山市上野町774番地ビレッジハウス上野2-508 | F19: 9/末→2-504 3人部屋
B21: 07011505 | C21: 津吉 | D21: ファム ティ チン | E21: 津吉町535-1コーポ津吉2-4 | F21: 10/1～ビレッジハウス上野2-503
B22: 07011610 | C22: 津吉 | D22: ファム ティ イエン | E22: 津吉町535-1コーポ津吉1-6 | F22: 10/1～ビレッジハウス上野2-503
B23: 07011504 | C23: 津吉 | D23: ファム ティ ヒエン | E23: 津吉町535-1コーポ津吉1-6 | F23: 10/1～コーポ津吉2-4 10/4退寮
A25: 通勤 | B25: 07011608 | C25: 津吉 | D25: ズオン デ タオ | E25: 松山市上野町774番地ビレッジハウス上野2-503 | F25: バイク→車通勤 申請許可後変更→許可
A27: １０月
A28: 退職 | B28: 07011504 | C28: 津吉 | D28: ファム ティ ヒエン | E28: 津吉町535-1コーポ津吉1-6 | F28: 10/3実習終了退職 10/4退寮
B29: 07012614 | C29: 津吉 | D29: ハー ティ ヴァン | E29: 松山市上野町774番地ビレッジハウス上野2-508 | F29: 2024/10/4退職 最終出勤日
B30: 07001414 | C30: 小栗 | D30: ヴー ティ タオ | E30: 和泉北1-20-28アトムスカイマンション402 | F30: 2024/10/15,16,18,19有給 10/17最終出勤 10/20退職 10/22退寮
B31: 07013620 | C31: 津吉 | D31: レストゥ グメラー | E31: 松山市上野町774番地ビレッジハウス上野3-507 | F31: 10/20にて退職(確定)
A33: 離職票 | B33: 07013658 | C33: 津吉 | D33: ラーミタ ヌル ハリザ | E33: 東温市牛渕123-1 | F33: 2024/09/29退職 10/3退寮 H&Cへ渡す⇒済
A35: 実習 →特定活動 | B35: 07011505 | C35: 津吉 | D35: ファム ティ チン | E35: 津吉町535-1コーポ津吉2-4 | F35: 10/4～特定活動
A37: 退寮 | B37: 07012614 | C37: 津吉 | D37: ハー ティ ヴァン | E37: 松山市上野町774番地ビレッジハウス上野2-508 | F37: 2024/10/10退寮
B38: 07011504 | C38: 津吉 | D38: ファム ティ ヒエン | E38: 津吉町535-1コーポ津吉1-6 | F38: 10/4退寮
B39: 07001414 | C39: 小栗 | D39: ヴー ティ タオ | E39: 和泉北1-20-28アトムスカイマンション402 | F39: 2024/10/22退寮
B40: 07013658 | C40: 津吉 | D40: ラーミタ ヌル ハリザ | E40: 東温市牛渕123-1 | F40: 2024/09/29退職 10/3退寮
B41: 07013620 | C41: 津吉 | D41: レストゥ グメラー | E41: 松山市上野町774番地ビレッジハウス上野3-507 | F41: 10/19予定だがH&C管理
A43: 給料 | B43: 07012614 | C43: 津吉 | D43: ハー ティ ヴァン | E43: 松山市上野町774番地ビレッジハウス上野2-508 | F43: 帰国日程変更のため 2024/10/８ 9時現金用意【小栗】
B44: 07011504 | C44: 津吉 | D44: ファム ティ ヒエン | E44: 津吉町535-1コーポ津吉1-6 | F44: 10/4 13:00頃本社にて現金
B45: 07001414 | C45: 小栗 | D45: ヴー ティ タオ | E45: 和泉北1-20-28アトムスカイマンション402 | F45: 2024/10/22午前中現金
B46: 07013658 | C46: 津吉 | D46: ラーミタ ヌル ハリザ | E46: 東温市牛渕123-1 | F46: 2024/10/03退寮までに現金
B47: 07013638 | C47: 津吉 | D47: ニマトゥル マウリダ | E47: 東温市牛渕170-3 | F47: N3合格 10/31給料より5,000円
B48: 07013620 | C48: 津吉 | D48: レストゥ グメラー | E48: 松山市上野町774番地ビレッジハウス上野3-507 | F48: 10/20にて退職→ 10/31現金H&Cへ 兵庫へ転職
A50: 給料控除等 | B50: 07012621 | C50: 津吉 | D50: グエン バァン ドゥ | E50: 松山市上野町774番地ビレッジハウス上野2-504 | F50: 8/21入社時給897円 10/13～956円に変更
B51: 07011608 | C51: 津吉 | D51: ズオン デ タオ | E51: 松山市上野町774番地ビレッジハウス上野2-503 | F51: ヴィレッジ駐車場10/20締め分より4,840円控除 以降 毎月駐車場代として4,400円控除必要
A53: 通勤 | B53: 07012606 | C53: 津吉 | D53: チャン クアン トゥアン | E53: 松山市上野町774番地ビレッジハウス上野2-508 | F53: 9/末→2-504 3人部屋
D54: ※住所変更に伴う申請
B55: 07011608 | C55: 津吉 | D55: ズオン デ タオ | E55: 松山市上野町774番地ビレッジハウス上野2-503 | F55: バイク→車
D56: ※通勤方法の変更 バイク→車
A58: 通勤・給料 | B58: 07011505 | C58: 津吉 | D58: ファム ティ チン | E58: 津吉町535-1コーポ津吉2-4 | F58: 10/1～ビレッジハウス上野2-503
B59: 07011610 | C59: 津吉 | D59: ファム ティ イエン | E59: 津吉町535-1コーポ津吉1-6 | F59: 10/1～ビレッジハウス上野2-503
D60: ※自転車通勤の距離変更に伴う通勤費変更 10/1～変更
A62: 入社 | C62: 津吉 | D62: イ マデ エサノピオ | E62: オクトリヴィア ザヘル | F62: 男性10名 女性10名
C63: 津吉 | D63: ラストノ スリ ムルヤ | E63: ナファ アイヌル リズキ | F63: 10/22 男性2名女性3名入社 黄色
C64: 津吉 | D64: イーサン シハブ ギッファリ | E64: ザーラ ソンジャヤ | F64: 10/29 男性8名女性7名入社 水色
C65: 津吉 | D65: リザル ムハマド フィルダウス | E65: ヌルル アフリナ セルビアンティ
C66: 津吉 | D66: ダナン アジ プリ アトモコ | E66: マヤング ヌルハサナー
C67: 津吉 | D67: アルル ユスフ フィルダウス | E67: チンティア インダー ゲスタ
C68: 津吉 | D68: ムハッマド ユスフ | E68: ミャナ デウィ アフナン
C69: 津吉 | D69: ライハン ヴィルギアン アルファレル | E69: アニサー ファッラス ナビル ザハビヤー
C70: 津吉 | D70: リヴァンドラ ジヨ マヘサ | E70: ニケン エカ ヌルリナワティ
C71: 津吉 | D71: アデゥン | E71: アルヴィタ
A73: 入社 | C73: 小栗 | D73: ボー グェン ホアイ ナム | E73: 和泉北1-20-28アトムスカイマンション604 | F73: 10/15入寮 10/16入社
C74: 小栗 | D74: ファム ヒュー タン | E74: 和泉北1-20-28アトムスカイマンション604 | F74: 10/15入寮 10/16入社
C75: 小栗 | D75: ホー ティ ニュン | E75: 和泉北1-20-28アトムスカイマンション401 | F75: 10/15入寮 10/16入社
C76: 小栗 | D76: グエン ティ リエウ | E76: 和泉北1-20-28アトムスカイマンション401 | F76: 10/15入寮 10/16入社
C77: 小栗 | D77: ディン ティ タオ グエン | E77: 和泉北1-20-28アトムスカイマンション401 | F77: 10/15入寮 10/16入社
A79: その他 | B79: 07013641 | C79: 津吉 | D79: NUR ANDINI | E79: 東温市牛渕170-3→ビレッジ4-205へ移動 | F79: H&Cへ牛渕寮費 15,352円請求10/1入金有 移動日9/14
A81: １１月
A82: 退職 | B82: 07012612 | C82: 津吉 | D82: グエン ゴック ガー | E82: 松山市上野町774番地ビレッジハウス上野2-506 | F82: 一時帰国→2024/11/20退職に変更
A84: 退寮 | B84: 07012612 | C84: 津吉 | D84: グエン ゴック ガー | E84: 松山市上野町774番地ビレッジハウス上野2-506 | F84: 11/9最終出勤 11/11～11/20有給消化 11/20退寮
A86: 一時帰国 | B86: 07013605 | C86: 津吉 | D86: エヴィ ラハユ | E86: 松山市上野町774番地ビレッジハウス上野4-205 | F86: 2024/11/27最終出勤午前中～一時帰国～2025/01/3自身の結婚
A88: 控除関係 | B88: 07013605 | C88: 津吉 | D88: エヴィ ラハユ | E88: 松山市上野町774番地ビレッジハウス上野4-205 | F88: 11/27～1/3一時帰国 12月社会保険料のみ11月末より天引 家賃は翌月 給料は通常通り 月末振込 ←社会保険料返金
B89: 07013612 | C89: 津吉 | D89: リンダ ヌルハリザ | E89: 松山市上野町774番地ビレッジハウス上野4-501 | F89: １０月給料マイナス分 33,378円控除
A91: 部屋移動 | B91: 07013633 | C91: 津吉 | D91: ナナ マルディアナ | E91: 松山市上野町774番地ビレッジハウス上野2-405 | F91: ビレッジハウス上野2-405⇒3-507へ移動 11/9に部屋移動
A93: 給料 | B93: 07012612 | C93: 津吉 | D93: グエン ゴック ガー | E93: 松山市上野町774番地ビレッジハウス上野2-506 | F93: 11/29 デルタ四国に現金
A96: １２月
A97: 一時退職 | B97: 07012606 | C97: 津吉 | D97: チャン クアン トゥアン→退職へ変更 | E97: 松山市上野町774番地ビレッジハウス上野2-504 | F97: 退職日2024/12/20 最終出勤12/19 再度勤務25/02/21
B98: 07013636 | C98: 津吉 | D98: ヨヴィト チャトゥル ヌグラハ | E98: 松山市上野町774番地ビレッジハウス上野3-103 退職日確認中 | F98: 2024/12に入り体調不良にて休み。12/21診療内科受診し一時帰国を進められる。一時退職し帰国を打診。12/20締有給すべて消化処理。12/27一時退職、1月早めに帰国
A100: 退職 | B100: 07001612 | C100: 小栗 | D100: グエン ティ タム | E100: 和泉北1-20-28アトムスカイマンション304 | F100: 最終出勤2024/12/17 退職日2024/12/20 完全帰国
A102: 退寮 | B102: 07001612 | C102: 小栗 | D102: グエン ティ タム | E102: 和泉北1-20-28アトムスカイマンション304 | F102: 退寮日2024/12/23 15:30成田行ジェットスター～
A104: 給料 | B104: 07012606 | C104: 津吉 | D104: チャン クアン トゥアン→退職へ変更 | E104: 松山市上野町774番地ビレッジハウス上野2-508 | F104: 12/末銀行振込OK、12/末の給料より12/21～2/20、 家賃30,000円控除OK
B105: 07001612 | C105: 小栗 | D105: グエン ティ タム | E105: 和泉北1-20-28アトムスカイマンション304 | F105: 12/23 午前中現金 完全帰国
A107: 再入寮・再入社 | B107: 07012606 | C107: 津吉 | D107: チャン クアン トゥアン | E107: 松山市上野町774番地ビレッジハウス上野2-508 | F107: 2024/12/21～2025/2/20一時退職 再度勤務25/02/21 家賃2か月・社会保険あれば1か月分を先に徴収→本人了承
A108: 2025年１月
A109: 入寮 | C109: 小栗 | D109: チャン ヴァン チュン | E109: 和泉北1-20-28アトムスカイマンション604 | F109: 2025/01/09入寮
C110: 小栗 | D110: ブイ ヴァン ライ | E110: 和泉北1-20-28アトムスカイマンション604 | F110: 2025/01/09入寮
A112: 入社予定 | C112: 小栗 | D112: チャン ヴァン チュン | E112: 和泉北1-20-28アトムスカイマンション604 | F112: 2025/01/10入社予定
C113: 小栗 | D113: ブイ ヴァン ライ | E113: 和泉北1-20-28アトムスカイマンション604 | F113: 2025/01/10入社予定
A114: 一時帰国 | B114: 07013614 | C114: 津吉 | D114: コフィファー ヌル コエリヤー | E114: 松山市上野町774番地ビレッジハウス上野4-502 | F114: 最終出勤日1/30 2025/1/31～3/3一時帰国 帰国日3/4 開始3/6 帰国期間の控除OKだが、８日勤務ありのため控除なし
A116: 一時退職 | B116: 07001607 | C116: 小栗 | D116: グエン タイン ド― | E116: 和泉北1-20-28アトムスカイマンション504 | F116: 1/19退職2025/1/20～2025/03/05 チケット済 3/7より再勤務
A118: 退職 | B118: 07013607 | C118: 津吉 | D118: ユリ アニ | E118: 東温市牛渕170-3 | F118: 2025/1/20に退職 福岡の会社に転職申出(内定) 有給残 15日
B119: 07013609 | C119: 津吉 | D119: ノヴィアナ ラティー | E119: 東温市牛渕170-3 | F119: 2025/1/20に退職 福岡の会社に転職申出(内定) 有給残7日
B120: 07013611 | C120: 津吉 | D120: ロチ アンジェリ ルイタン | E120: 松山市上野町774番地ビレッジハウス上野4-502 | F120: 2025/1/20に退職 結婚の為帰国大阪の旦那の会社へ転職有給残8日
B121: 07013616 | C121: 津吉 | D121: エルサ プルナマ セプティア プトリ | E121: 松山市上野町774番地ビレッジハウス上野4-205 | F121: 2025/1/20に退職 福岡の会社に転職申出(内定) 有給残13日
B122: 07013617 | C122: 津吉 | D122: アルバシタ アマリア | E122: 東温市牛渕170-3 | F122: 2025/1/20に退職 福岡の会社へ転職 有給残12日
B123: 07013612 | C123: 津吉 | D123: リンダ ヌルハリザ | E123: 松山市上野町774番地ビレッジハウス上野4-501 | F123: 妊娠中 1/20退職 1/30帰国 1/30退寮
B124: 07013670 | C124: 津吉 | D124: ノペンシウス ジュリエアント | E124: 松山市上野町774番地ビレッジハウス上野3-103 | F124: 1/20退職 残業多いため一時帰国しゆっくりしたい申出 転職
A126: 控除関係 | B126: 07001607 | C126: 小栗 | D126: グエン タイン ド― | E126: 和泉北1-20-28アトムスカイマンション504 | F126: 1/20締給料より、2月の家賃10,000円控除
A128: 2月
A129: 部屋移動 | B129: 07013671 | C129: 津吉 | D129: アエプ サエプル ハク | E129: 松山市上野町774番地ビレッジハウス上野4-501 | F129: リンダ帰国後部屋移動 4-501→2-405予定→そのまま
A131: 入社 | B131: 07001616 | C131: 小栗 | D131: チャン ティ トゥー ヒエン | E131: 和泉北1-20-28アトムスカイマンション705 | F131: 2/21入国 2/25衛生講習9:00 2/26入社
A133: 一時帰国 | B133: 07011602 | C133: 津吉 | D133: グエン ビック フーン | E133: 津吉町535-1コーポ津吉1-2 | F133: 2025/2/23～3/16親族結婚式出席のため帰国 2/20まで出勤 3/17～出勤
B134: 07012621 | C134: 津吉 | D134: グエン バァン ドゥ | E134: 松山市上野町774番地ビレッジハウス上野2-504 | F134: 2025/2/27最終出勤 2/28～4/3自身の結婚の為帰国 4/4再出勤日
A136: 再入寮・再入社 →退職へ変更 | B136: 07012606 | C136: 津吉 | D136: チャン クアン トゥアン→退職へ変更 | E136: 松山市上野町774番地ビレッジハウス上野2-508 | F136: 2024/12/21～2025/2/20一時退職 再度勤務25/02/21 家賃2か月・社会保険あれば1か月分を先に徴収→本人了承 急遽退職へ変更 4,131円2/25回収済
A138: 給料（資格手当） | B138: 07001610 | C138: 小栗 | D138: グエン ヒュー タイン ダット | E138: 松山市末広町5-14三和ﾏﾝｼｮﾝ末広201 | F138: 資格手当 5,000円 日本語能力検定N3合格 2024/12/01受験 2025/1/31確認
B139: 07001417 | C139: 小栗 | D139: レー ティ ダオ | E139: 和泉北1-20-28アトムスカイマンション402 | F139: 資格手当 5,000円 日本語能力検定N3合格 2024/12/01受験 2025/2/17確認
B140: 07011613 | C140: 津吉 | D140: ファム ティ チン | E140: 松山市上野町774番地ビレッジハウス上野2-503 | F140: 一時帰国費用37,150-控除 今回の控除により帰国費用は不要
...

Sheet 本社
A1: 本社
A3: =IFERROR(__xludf.DUMMYFUNCTION("query('管理表'!A:AP,""select * where (C = '本社' or C = '協同本社') and not(AH = '退職')"",1)"),"区") -> 区 | B3: =IFERROR(__xludf.DUMMYFUNCTION("""COMPUTED_VALUE"""),"No") -> No | C3: =IFERROR(__xludf.DUMMYFUNCTION("""COMPUTED_VALUE"""),"勤務地") -> 勤務地 | D3: =IFERROR(__xludf.DUMMYFUNCTION("""COMPUTED_VALUE"""),"国籍") -> 国籍 | E3: =IFERROR(__xludf.DUMMYFUNCTION("""COMPUTED_VALUE"""),"社員コード") -> 社員コード | F3: =IFERROR(__xludf.DUMMYFUNCTION("""COMPUTED_VALUE"""),"写真") -> 写真 | G3: =IFERROR(__xludf.DUMMYFUNCTION("""COMPUTED_VALUE"""),"フリガナ") -> フリガナ | H3: =IFERROR(__xludf.DUMMYFUNCTION("""COMPUTED_VALUE"""),"氏名") -> 氏名 | I3: =IFERROR(__xludf.DUMMYFUNCTION("""COMPUTED_VALUE"""),"呼名") -> 呼名 | J3: =IFERROR(__xludf.DUMMYFUNCTION("""COMPUTED_VALUE"""),"性別") -> 性別 | K3: =IFERROR(__xludf.DUMMYFUNCTION("""COMPUTED_VALUE"""),"生年月日") -> 生年月日 | L3: =IFERROR(__xludf.DUMMYFUNCTION("""COMPUTED_VALUE"""),"年齢") -> 年齢 | M3: =IFERROR(__xludf.DUMMYFUNCTION("""COMPUTED_VALUE"""),"配偶者") -> 配偶者 | N3: =IFERROR(__xludf.DUMMYFUNCTION("""COMPUTED_VALUE"""),"登録支援機関") -> 登録支援機関 | O3: =IFERROR(__xludf.DUMMYFUNCTION("""COMPUTED_VALUE"""),"入社日") -> 入社日 | P3: =IFERROR(__xludf.DUMMYFUNCTION("""COMPUTED_VALUE"""),"帰国予定") -> 帰国予定 | Q3: =IFERROR(__xludf.DUMMYFUNCTION("""COMPUTED_VALUE"""),"実習区分") -> 実習区分 | R3: =IFERROR(__xludf.DUMMYFUNCTION("""COMPUTED_VALUE"""),"住所") -> 住所 | S3: =IFERROR(__xludf.DUMMYFUNCTION("""COMPUTED_VALUE"""),"個・相部屋") -> 個・相部屋 | T3: =IFERROR(__xludf.DUMMYFUNCTION("""COMPUTED_VALUE"""),"家賃負担") -> 家賃負担 | U3: =IFERROR(__xludf.DUMMYFUNCTION("""COMPUTED_VALUE"""),"雇用条件書") -> 雇用条件書 | V3: =IFERROR(__xludf.DUMMYFUNCTION("""COMPUTED_VALUE"""),"カード期限") -> カード期限 | W3: =IFERROR(__xludf.DUMMYFUNCTION("""COMPUTED_VALUE"""),"在留カード番号") -> 在留カード番号 | X3: =IFERROR(__xludf.DUMMYFUNCTION("""COMPUTED_VALUE"""),"雇用保険番号") -> 雇用保険番号 | Y3: =IFERROR(__xludf.DUMMYFUNCTION("""COMPUTED_VALUE"""),"自転車渡日") -> 自転車渡日 | Z3: =IFERROR(__xludf.DUMMYFUNCTION("""COMPUTED_VALUE"""),"自転車No-防犯") -> 自転車No-防犯 | AA3: =IFERROR(__xludf.DUMMYFUNCTION("""COMPUTED_VALUE"""),"自転車回収日") -> 自転車回収日 | AB3: =IFERROR(__xludf.DUMMYFUNCTION("""COMPUTED_VALUE"""),"日本語検定") -> 日本語検定 | AC3: =IFERROR(__xludf.DUMMYFUNCTION("""COMPUTED_VALUE"""),"試験資格") -> 試験資格 | AD3: =IFERROR(__xludf.DUMMYFUNCTION("""COMPUTED_VALUE"""),"一時退職日") -> 一時退職日 | AE3: =IFERROR(__xludf.DUMMYFUNCTION("""COMPUTED_VALUE"""),"一時帰国From") -> 一時帰国From | AF3: =IFERROR(__xludf.DUMMYFUNCTION("""COMPUTED_VALUE"""),"一時帰国To") -> 一時帰国To | AG3: =IFERROR(__xludf.DUMMYFUNCTION("""COMPUTED_VALUE"""),"再入社") -> 再入社 | AH3: =IFERROR(__xludf.DUMMYFUNCTION("""COMPUTED_VALUE"""),"退職区分") -> 退職区分 | AI3: =IFERROR(__xludf.DUMMYFUNCTION("""COMPUTED_VALUE"""),"退職日") -> 退職日 | AJ3: =IFERROR(__xludf.DUMMYFUNCTION("""COMPUTED_VALUE"""),"帰国費用") -> 帰国費用 | AK3: =IFERROR(__xludf.DUMMYFUNCTION("""COMPUTED_VALUE"""),"部署長") -> 部署長 | AL3: =IFERROR(__xludf.DUMMYFUNCTION("""COMPUTED_VALUE"""),"特定1号 保険加入") -> 特定1号 保険加入 | AM3: =IFERROR(__xludf.DUMMYFUNCTION("""COMPUTED_VALUE"""),"特定1号 入国日") -> 特定1号 入国日 | AN3: =IFERROR(__xludf.DUMMYFUNCTION("""COMPUTED_VALUE"""),"特定1号保険期間") -> 特定1号保険期間 | AO3: =IFERROR(__xludf.DUMMYFUNCTION("""COMPUTED_VALUE"""),"給与口座") -> 給与口座 | AP3: =IFERROR(__xludf.DUMMYFUNCTION("""COMPUTED_VALUE"""),"備考") -> 備考
B4: =IFERROR(__xludf.DUMMYFUNCTION("""COMPUTED_VALUE"""),9) -> 9 | C4: =IFERROR(__xludf.DUMMYFUNCTION("""COMPUTED_VALUE"""),"本社") -> 本社 | D4: =IFERROR(__xludf.DUMMYFUNCTION("""COMPUTED_VALUE"""),"ベトナム") -> ベトナム | E4: =IFERROR(__xludf.DUMMYFUNCTION("""COMPUTED_VALUE"""),"07001611") -> 07001611 | F4: =IFERROR(__xludf.DUMMYFUNCTION("""COMPUTED_VALUE"""),"/appsheet/photograph/小栗_ミン_20240424.jpg") -> /appsheet/photograph/小栗_ミン_20240424.jpg | G4: =IFERROR(__xludf.DUMMYFUNCTION("""COMPUTED_VALUE"""),"ブイ ティ ミン") -> ブイ ティ ミン | H4: =IFERROR(__xludf.DUMMYFUNCTION("""COMPUTED_VALUE"""),"BUI THI MINH") -> BUI THI MINH | I4: =IFERROR(__xludf.DUMMYFUNCTION("""COMPUTED_VALUE"""),"ミン") -> ミン | J4: =IFERROR(__xludf.DUMMYFUNCTION("""COMPUTED_VALUE"""),"女") -> 女 | K4: =IFERROR(__xludf.DUMMYFUNCTION("""COMPUTED_VALUE"""),36245) -> 36245 | L4: =IFERROR(__xludf.DUMMYFUNCTION("""COMPUTED_VALUE"""),27) -> 27 | M4: =IFERROR(__xludf.DUMMYFUNCTION("""COMPUTED_VALUE"""),"夫婦") -> 夫婦 | N4: =IFERROR(__xludf.DUMMYFUNCTION("""COMPUTED_VALUE"""),"中四国") -> 中四国 | O4: =IFERROR(__xludf.DUMMYFUNCTION("""COMPUTED_VALUE"""),43435) -> 43435 | P4: =IFERROR(__xludf.DUMMYFUNCTION("""COMPUTED_VALUE"""),"2025/09") -> 2025/09 | Q4: =IFERROR(__xludf.DUMMYFUNCTION("""COMPUTED_VALUE"""),"特定技能１号") -> 特定技能１号 | R4: =IFERROR(__xludf.DUMMYFUNCTION("""COMPUTED_VALUE"""),"和泉北1-20-28アトムスカイマンション305") -> 和泉北1-20-28アトムスカイマンション305 | S4: =IFERROR(__xludf.DUMMYFUNCTION("""COMPUTED_VALUE"""),"夫婦") -> 夫婦 | T4: =IFERROR(__xludf.DUMMYFUNCTION("""COMPUTED_VALUE"""),20000) -> 20000 | U4: =IFERROR(__xludf.DUMMYFUNCTION("""COMPUTED_VALUE"""),45870) -> 45870 | V4: =IFERROR(__xludf.DUMMYFUNCTION("""COMPUTED_VALUE"""),46294) -> 46294 | W4: =IFERROR(__xludf.DUMMYFUNCTION("""COMPUTED_VALUE"""),"UH54552117PC") -> UH54552117PC | X4: =IFERROR(__xludf.DUMMYFUNCTION("""COMPUTED_VALUE"""),"5103-260929-6") -> 5103-260929-6 | Z4: =IFERROR(__xludf.DUMMYFUNCTION("""COMPUTED_VALUE"""),"返却済 宮内工場長の自転車を乗っている") -> 返却済 宮内工場長の自転車を乗っている | AB4: =IFERROR(__xludf.DUMMYFUNCTION("""COMPUTED_VALUE"""),"N4 2024/07/07") -> N4 2024/07/07 | AE4: =IFERROR(__xludf.DUMMYFUNCTION("""COMPUTED_VALUE"""),45271) -> 45271 | AF4: =IFERROR(__xludf.DUMMYFUNCTION("""COMPUTED_VALUE"""),45311) -> 45311 | AL4: =IFERROR(__xludf.DUMMYFUNCTION("""COMPUTED_VALUE"""),"〇") -> 〇 | AN4: =IFERROR(__xludf.DUMMYFUNCTION("""COMPUTED_VALUE"""),"2025/8/1～2029/9/30") -> 2025/8/1～2029/9/30 | AO4: =IFERROR(__xludf.DUMMYFUNCTION("""COMPUTED_VALUE"""),"伊予銀") -> 伊予銀 | AP4: =IFERROR(__xludf.DUMMYFUNCTION("""COMPUTED_VALUE"""),"※特定技能申請の為、ﾊﾟｽﾎﾟｰﾄと在留ｶｰﾄﾞは中四国預かり（6/13朴さんより） 2024.6.12～社員コード変わる済（特定活動になるため） 2024.6.12～9.12実習3号→特定活動 9/12～特定技能へ ※特定活動（6ヵ月）申請しその期間に特定技能へ変更予定。 2026/5/4出産予定日 一時帰国し出産予定。2026/3/24～6/29産休 6/30～2027/5/3育休") -> ※特定技能申請の為、ﾊﾟｽﾎﾟｰﾄと在留ｶｰﾄﾞは中四国預かり（6/13朴さんより） 2024.6.12～社員コード変わる済（特定活動になるため） 2024.6.12～9.12実習3号→特定活動 9/12～特定技能へ ※特定活動（6ヵ月）申請しその期間に特定技能へ変更予定。 2026/5/4出産予定日 一時帰国し出産予定。2026/3/24～6/29産休 6/30～2027/5/3育休
B5: =IFERROR(__xludf.DUMMYFUNCTION("""COMPUTED_VALUE"""),10) -> 10 | C5: =IFERROR(__xludf.DUMMYFUNCTION("""COMPUTED_VALUE"""),"本社") -> 本社 | D5: =IFERROR(__xludf.DUMMYFUNCTION("""COMPUTED_VALUE"""),"ベトナム") -> ベトナム | E5: =IFERROR(__xludf.DUMMYFUNCTION("""COMPUTED_VALUE"""),"07001613") -> 07001613 | F5: =IFERROR(__xludf.DUMMYFUNCTION("""COMPUTED_VALUE"""),"/appsheet/photograph/10.写真.032947.jpg") -> /appsheet/photograph/10.写真.032947.jpg | G5: =IFERROR(__xludf.DUMMYFUNCTION("""COMPUTED_VALUE"""),"グエン ティ ロアン") -> グエン ティ ロアン | H5: =IFERROR(__xludf.DUMMYFUNCTION("""COMPUTED_VALUE"""),"NGUYEN THI LOAN") -> NGUYEN THI LOAN | I5: =IFERROR(__xludf.DUMMYFUNCTION("""COMPUTED_VALUE"""),"ロアン") -> ロアン | J5: =IFERROR(__xludf.DUMMYFUNCTION("""COMPUTED_VALUE"""),"女") -> 女 | K5: =IFERROR(__xludf.DUMMYFUNCTION("""COMPUTED_VALUE"""),31701) -> 31701 | L5: =IFERROR(__xludf.DUMMYFUNCTION("""COMPUTED_VALUE"""),39) -> 39 | M5: =IFERROR(__xludf.DUMMYFUNCTION("""COMPUTED_VALUE"""),"有") -> 有 | N5: =IFERROR(__xludf.DUMMYFUNCTION("""COMPUTED_VALUE"""),"中四国") -> 中四国 | O5: =IFERROR(__xludf.DUMMYFUNCTION("""COMPUTED_VALUE"""),43435) -> 43435 | P5: =IFERROR(__xludf.DUMMYFUNCTION("""COMPUTED_VALUE"""),"2025/09") -> 2025/09 | Q5: =IFERROR(__xludf.DUMMYFUNCTION("""COMPUTED_VALUE"""),"特定技能１号") -> 特定技能１号 | R5: =IFERROR(__xludf.DUMMYFUNCTION("""COMPUTED_VALUE"""),"和泉北1-20-28アトムスカイマンション403") -> 和泉北1-20-28アトムスカイマンション403 | S5: =IFERROR(__xludf.DUMMYFUNCTION("""COMPUTED_VALUE"""),"個1") -> 個1 | T5: =IFERROR(__xludf.DUMMYFUNCTION("""COMPUTED_VALUE"""),20000) -> 20000 | U5: =IFERROR(__xludf.DUMMYFUNCTION("""COMPUTED_VALUE"""),45870) -> 45870 | V5: =IFERROR(__xludf.DUMMYFUNCTION("""COMPUTED_VALUE"""),46294) -> 46294 | W5: =IFERROR(__xludf.DUMMYFUNCTION("""COMPUTED_VALUE"""),"UH51964624PC") -> UH51964624PC | X5: =IFERROR(__xludf.DUMMYFUNCTION("""COMPUTED_VALUE"""),"5103-260926-8") -> 5103-260926-8 | Z5: =IFERROR(__xludf.DUMMYFUNCTION("""COMPUTED_VALUE"""),"1968-B-0091968 2024/08/27自転車変更 7912(1596)赤へ 2025/08/27変更 B-0246665-1008") -> 1968-B-0091968 2024/08/27自転車変更 7912(1596)赤へ 2025/08/27変更 B-0246665-1008 | AD5: =IFERROR(__xludf.DUMMYFUNCTION("""COMPUTED_VALUE"""),45317) -> 45317 | AG5: =IFERROR(__xludf.DUMMYFUNCTION("""COMPUTED_VALUE"""),45350) -> 45350 | AL5: =IFERROR(__xludf.DUMMYFUNCTION("""COMPUTED_VALUE"""),"〇") -> 〇 | AM5: =IFERROR(__xludf.DUMMYFUNCTION("""COMPUTED_VALUE"""),43403) -> 43403 | AN5: =IFERROR(__xludf.DUMMYFUNCTION("""COMPUTED_VALUE"""),"2025/8/1～2029/5/31") -> 2025/8/1～2029/5/31 | AO5: =IFERROR(__xludf.DUMMYFUNCTION("""COMPUTED_VALUE"""),"伊予銀 湊町支店") -> 伊予銀 湊町支店 | AP5: =IFERROR(__xludf.DUMMYFUNCTION("""COMPUTED_VALUE"""),"※特定技能申請の為、ﾊﾟｽﾎﾟｰﾄと在留ｶｰﾄﾞは中四国預かり（6/13朴さんより） 2024.6.12～社員コード変わる済（特定活動になるため） 2024.6.12～9/152実習3号→特定活動 9/12～特定技能へ ※特定活動（6ヵ月）申請しその期間に特定技能へ変更予定。 2022.7.18一時退職8/9～一時帰国 2024.1.26一時退職 2025/10/4 2～3年前から週に5日程下痢が続いているため、窪田クリニックを受診。便検査の結果、病原性大腸菌O-18が見つかり、ベロ毒素の検査結果は陰性。"&"（陽性であれば保健所に届け出が必要とのこと）。除菌のため、抗生物質の薬を5日服用し、5日後に再度便検査を病院でする予定。") -> ※特定技能申請の為、ﾊﾟｽﾎﾟｰﾄと在留ｶｰﾄﾞは中四国預かり（6/13朴さんより） 2024.6.12～社員コード変わる済（特定活動になるため） 2024.6.12～9/152実習3号→特定活動 9/12～特定技能へ ※特定活動（6ヵ月）申請しその期間に特定技能へ変更予定。 2022.7.18一時退職8/9～一時帰国 2024.1.26一時退職 2025/10/4 2～3年前から週に5日程下痢が続いているため、窪田クリニックを受診。便検査の結果、病原性大腸菌O-18が見つかり、ベロ毒素の検査結果は陰性。（陽性であれば保健所に届け出が必要とのこと）。除菌のため、抗生物質の薬を5日服用し、5日後に再度便検査を病院でする予定。
B6: =IFERROR(__xludf.DUMMYFUNCTION("""COMPUTED_VALUE"""),12) -> 12 | C6: =IFERROR(__xludf.DUMMYFUNCTION("""COMPUTED_VALUE"""),"本社") -> 本社 | D6: =IFERROR(__xludf.DUMMYFUNCTION("""COMPUTED_VALUE"""),"ベトナム") -> ベトナム | E6: =IFERROR(__xludf.DUMMYFUNCTION("""COMPUTED_VALUE"""),"07001614") -> 07001614 | F6: =IFERROR(__xludf.DUMMYFUNCTION("""COMPUTED_VALUE"""),"/appsheet/photograph/12.写真.224547.jpg") -> /appsheet/photograph/12.写真.224547.jpg | G6: =IFERROR(__xludf.DUMMYFUNCTION("""COMPUTED_VALUE"""),"ホアン ティ チャン") -> ホアン ティ チャン | H6: =IFERROR(__xludf.DUMMYFUNCTION("""COMPUTED_VALUE""")," HOANG THI TRANG") -> HOANG THI TRANG | I6: =IFERROR(__xludf.DUMMYFUNCTION("""COMPUTED_VALUE"""),"チャン") -> チャン | J6: =IFERROR(__xludf.DUMMYFUNCTION("""COMPUTED_VALUE"""),"女") -> 女 | K6: =IFERROR(__xludf.DUMMYFUNCTION("""COMPUTED_VALUE"""),34922) -> 34922 | L6: =IFERROR(__xludf.DUMMYFUNCTION("""COMPUTED_VALUE"""),30) -> 30 | N6: =IFERROR(__xludf.DUMMYFUNCTION("""COMPUTED_VALUE"""),"中四国") -> 中四国 | O6: =IFERROR(__xludf.DUMMYFUNCTION("""COMPUTED_VALUE"""),43627) -> 43627 | P6: =IFERROR(__xludf.DUMMYFUNCTION("""COMPUTED_VALUE"""),"2025/09") -> 2025/09 | Q6: =IFERROR(__xludf.DUMMYFUNCTION("""COMPUTED_VALUE"""),"特定技能１号") -> 特定技能１号 | R6: =IFERROR(__xludf.DUMMYFUNCTION("""COMPUTED_VALUE"""),"和泉北1-20-28アトムスカイマンション403") -> 和泉北1-20-28アトムスカイマンション403 | S6: =IFERROR(__xludf.DUMMYFUNCTION("""COMPUTED_VALUE"""),"個2") -> 個2 | T6: =IFERROR(__xludf.DUMMYFUNCTION("""COMPUTED_VALUE"""),20000) -> 20000 | U6: =IFERROR(__xludf.DUMMYFUNCTION("""COMPUTED_VALUE"""),45870) -> 45870 | V6: =IFERROR(__xludf.DUMMYFUNCTION("""COMPUTED_VALUE"""),46294) -> 46294 | W6: =IFERROR(__xludf.DUMMYFUNCTION("""COMPUTED_VALUE"""),"UH80838380PC") -> UH80838380PC | X6: =IFERROR(__xludf.DUMMYFUNCTION("""COMPUTED_VALUE"""),"5105-142112-5") -> 5105-142112-5 | Z6: =IFERROR(__xludf.DUMMYFUNCTION("""COMPUTED_VALUE"""),"2021/01購入 なし-B-0188562") -> 2021/01購入 なし-B-0188562 | AE6: =IFERROR(__xludf.DUMMYFUNCTION("""COMPUTED_VALUE"""),44760) -> 44760 | AF6: =IFERROR(__xludf.DUMMYFUNCTION("""COMPUTED_VALUE"""),44803) -> 44803 | AL6: =IFERROR(__xludf.DUMMYFUNCTION("""COMPUTED_VALUE"""),"〇") -> 〇 | AM6: =IFERROR(__xludf.DUMMYFUNCTION("""COMPUTED_VALUE"""),43594) -> 43594 | AN6: =IFERROR(__xludf.DUMMYFUNCTION("""COMPUTED_VALUE"""),"2025/8/1～2029/5/31") -> 2025/8/1～2029/5/31 | AO6: =IFERROR(__xludf.DUMMYFUNCTION("""COMPUTED_VALUE"""),"伊予銀") -> 伊予銀 | AP6: =IFERROR(__xludf.DUMMYFUNCTION("""COMPUTED_VALUE"""),"※特定技能申請の為、ﾊﾟｽﾎﾟｰﾄと在留ｶｰﾄﾞは中四国預かり（6/13朴さんより） 2024.6.12～9/12 実習3号→特定活動 9/12～特定技能へ ※特定活動（6ヵ月）申請しその期間に特定技能へ変更予定。 2024.6.12～（協同→中温へ転籍）") -> ※特定技能申請の為、ﾊﾟｽﾎﾟｰﾄと在留ｶｰﾄﾞは中四国預かり（6/13朴さんより） 2024.6.12～9/12 実習3号→特定活動 9/12～特定技能へ ※特定活動（6ヵ月）申請しその期間に特定技能へ変更予定。 2024.6.12～（協同→中温へ転籍）
B7: =IFERROR(__xludf.DUMMYFUNCTION("""COMPUTED_VALUE"""),29) -> 29 | C7: =IFERROR(__xludf.DUMMYFUNCTION("""COMPUTED_VALUE"""),"本社") -> 本社 | D7: =IFERROR(__xludf.DUMMYFUNCTION("""COMPUTED_VALUE"""),"ベトナム") -> ベトナム | E7: =IFERROR(__xludf.DUMMYFUNCTION("""COMPUTED_VALUE"""),"07001629") -> 07001629 | F7: =IFERROR(__xludf.DUMMYFUNCTION("""COMPUTED_VALUE"""),"/appsheet/photograph/IDPhoto_20240711_ヴィエット.jpg") -> /appsheet/photograph/IDPhoto_20240711_ヴィエット.jpg | G7: =IFERROR(__xludf.DUMMYFUNCTION("""COMPUTED_VALUE"""),"チャン ヴァン ヴィエット") -> チャン ヴァン ヴィエット | H7: =IFERROR(__xludf.DUMMYFUNCTION("""COMPUTED_VALUE"""),"TRAN VAN VIET") -> TRAN VAN VIET | I7: =IFERROR(__xludf.DUMMYFUNCTION("""COMPUTED_VALUE"""),"ヴィエット") -> ヴィエット | J7: =IFERROR(__xludf.DUMMYFUNCTION("""COMPUTED_VALUE"""),"男") -> 男 | K7: =IFERROR(__xludf.DUMMYFUNCTION("""COMPUTED_VALUE"""),32955) -> 32955 | L7: =IFERROR(__xludf.DUMMYFUNCTION("""COMPUTED_VALUE"""),36) -> 36 | N7: =IFERROR(__xludf.DUMMYFUNCTION("""COMPUTED_VALUE"""),"中四国") -> 中四国 | O7: =IFERROR(__xludf.DUMMYFUNCTION("""COMPUTED_VALUE"""),44119) -> 44119 | P7: =IFERROR(__xludf.DUMMYFUNCTION("""COMPUTED_VALUE"""),"2028/08") -> 2028/08 | Q7: =IFERROR(__xludf.DUMMYFUNCTION("""COMPUTED_VALUE"""),"特定技能１号") -> 特定技能１号 | R7: =IFERROR(__xludf.DUMMYFUNCTION("""COMPUTED_VALUE"""),"和泉北1-20-28アトムスカイマンション504") -> 和泉北1-20-28アトムスカイマンション504 | S7: =IFERROR(__xludf.DUMMYFUNCTION("""COMPUTED_VALUE"""),"相1") -> 相1 | T7: =IFERROR(__xludf.DUMMYFUNCTION("""COMPUTED_VALUE"""),20000) -> 20000 | V7: =IFERROR(__xludf.DUMMYFUNCTION("""COMPUTED_VALUE"""),46294) -> 46294 | W7: =IFERROR(__xludf.DUMMYFUNCTION("""COMPUTED_VALUE"""),"UH63950753PC") -> UH63950753PC | X7: =IFERROR(__xludf.DUMMYFUNCTION("""COMPUTED_VALUE"""),"5109-022666-1") -> 5109-022666-1 | Z7: =IFERROR(__xludf.DUMMYFUNCTION("""COMPUTED_VALUE"""),"2020/10購入 紛失17000002-B-0177519 新888-B-0143840-1653") -> 2020/10購入 紛失17000002-B-0177519 新888-B-0143840-1653 | AA7: =IFERROR(__xludf.DUMMYFUNCTION("""COMPUTED_VALUE"""),"5/30立花駅にて盗難 6/3市駅前交番届出") -> 5/30立花駅にて盗難 6/3市駅前交番届出 | AD7: =IFERROR(__xludf.DUMMYFUNCTION("""COMPUTED_VALUE"""),46015) -> 46015 | AE7: =IFERROR(__xludf.DUMMYFUNCTION("""COMPUTED_VALUE"""),46016) -> 46016 | AF7: =IFERROR(__xludf.DUMMYFUNCTION("""COMPUTED_VALUE"""),46055) -> 46055 | AG7: =IFERROR(__xludf.DUMMYFUNCTION("""COMPUTED_VALUE"""),46056) -> 46056 | AJ7: =IFERROR(__xludf.DUMMYFUNCTION("""COMPUTED_VALUE"""),"2025/12/25-2026/2/2 関西国際空港⇔ハノイ 115,800円") -> 2025/12/25-2026/2/2 関西国際空港⇔ハノイ 115,800円 | AL7: =IFERROR(__xludf.DUMMYFUNCTION("""COMPUTED_VALUE"""),"―") -> ― | AN7: =IFERROR(__xludf.DUMMYFUNCTION("""COMPUTED_VALUE"""),"自転車保険 2026/09/15") -> 自転車保険 2026/09/15 | AO7: =IFERROR(__xludf.DUMMYFUNCTION("""COMPUTED_VALUE"""),"伊予銀 三津浜支店") -> 伊予銀 三津浜支店 | AP7: =IFERROR(__xludf.DUMMYFUNCTION("""COMPUTED_VALUE"""),"特定技能1号期間更新中 24.7.11 6/3 10:01受理 市駅前交番にて 5/30自転車盗難の申出。鍵が故障により施錠しておらずとの申し出。6/3組合に5,000円徴収依頼 6/4￥5000支払済 2025/10/8伊予銀 三津浜支店 ワタナベさんより連絡あり。在留ｶｰﾄﾞ更新後のコピーの提出がまだ。10/17 2025/12/25～2026/02/02一時帰国希望（宮内工場長より） 2025/12/24一時退職 12/25～2026/2/2一時帰国 2026/2/3再入社 社員ｺｰﾄﾞ変更済") -> 特定技能1号期間更新中 24.7.11 6/3 10:01受理 市駅前交番にて 5/30自転車盗難の申出。鍵が故障により施錠しておらずとの申し出。6/3組合に5,000円徴収依頼 6/4￥5000支払済 2025/10/8伊予銀 三津浜支店 ワタナベさんより連絡あり。在留ｶｰﾄﾞ更新後のコピーの提出がまだ。10/17 2025/12/25～2026/02/02一時帰国希望（宮内工場長より） 2025/12/24一時退職 12/25～2026/2/2一時帰国 2026/2/3再入社 社員ｺｰﾄﾞ変更済
B8: =IFERROR(__xludf.DUMMYFUNCTION("""COMPUTED_VALUE"""),30) -> 30 | C8: =IFERROR(__xludf.DUMMYFUNCTION("""COMPUTED_VALUE"""),"本社") -> 本社 | D8: =IFERROR(__xludf.DUMMYFUNCTION("""COMPUTED_VALUE"""),"ベトナム") -> ベトナム | E8: =IFERROR(__xludf.DUMMYFUNCTION("""COMPUTED_VALUE"""),"07001610") -> 07001610 | F8: =IFERROR(__xludf.DUMMYFUNCTION("""COMPUTED_VALUE"""),"/appsheet/photograph/IDPhoto_20240711_ダット.jpg") -> /appsheet/photograph/IDPhoto_20240711_ダット.jpg | G8: =IFERROR(__xludf.DUMMYFUNCTION("""COMPUTED_VALUE"""),"グエン ヒュー タイン ダット") -> グエン ヒュー タイン ダット | H8: =IFERROR(__xludf.DUMMYFUNCTION("""COMPUTED_VALUE"""),"NGUYEN HUU THANH DAT") -> NGUYEN HUU THANH DAT | I8: =IFERROR(__xludf.DUMMYFUNCTION("""COMPUTED_VALUE"""),"ダット") -> ダット | J8: =IFERROR(__xludf.DUMMYFUNCTION("""COMPUTED_VALUE"""),"男") -> 男 | K8: =IFERROR(__xludf.DUMMYFUNCTION("""COMPUTED_VALUE"""),37255) -> 37255 | L8: =IFERROR(__xludf.DUMMYFUNCTION("""COMPUTED_VALUE"""),24) -> 24 | M8: =IFERROR(__xludf.DUMMYFUNCTION("""COMPUTED_VALUE"""),"夫婦") -> 夫婦 | N8: =IFERROR(__xludf.DUMMYFUNCTION("""COMPUTED_VALUE"""),"中四国") -> 中四国 | O8: =IFERROR(__xludf.DUMMYFUNCTION("""COMPUTED_VALUE"""),44119) -> 44119 | P8: =IFERROR(__xludf.DUMMYFUNCTION("""COMPUTED_VALUE"""),"2028/08") -> 2028/08 | Q8: =IFERROR(__xludf.DUMMYFUNCTION("""COMPUTED_VALUE"""),"特定技能１号") -> 特定技能１号 | R8: =IFERROR(__xludf.DUMMYFUNCTION("""COMPUTED_VALUE"""),"松山市末広町5-14三和ﾏﾝｼｮﾝ末広201") -> 松山市末広町5-14三和ﾏﾝｼｮﾝ末広201 | S8: =IFERROR(__xludf.DUMMYFUNCTION("""COMPUTED_VALUE"""),"夫婦") -> 夫婦 | T8: =IFERROR(__xludf.DUMMYFUNCTION("""COMPUTED_VALUE"""),21500) -> 21500 | U8: =IFERROR(__xludf.DUMMYFUNCTION("""COMPUTED_VALUE"""),46082) -> 46082 | V8: =IFERROR(__xludf.DUMMYFUNCTION("""COMPUTED_VALUE"""),46294) -> 46294 | W8: =IFERROR(__xludf.DUMMYFUNCTION("""COMPUTED_VALUE"""),"UH42724630PC") -> UH42724630PC | X8: =IFERROR(__xludf.DUMMYFUNCTION("""COMPUTED_VALUE"""),"5109-022610-8") -> 5109-022610-8 | Z8: =IFERROR(__xludf.DUMMYFUNCTION("""COMPUTED_VALUE"""),"2020/10購入 17000003 B-0177520") -> 2020/10購入 17000003 B-0177520 | AB8: =IFERROR(__xludf.DUMMYFUNCTION("""COMPUTED_VALUE"""),"N3 2024/12/01") -> N3 2024/12/01 | AD8: =IFERROR(__xludf.DUMMYFUNCTION("""COMPUTED_VALUE"""),45306) -> 45306 | AE8: =IFERROR(__xludf.DUMMYFUNCTION("""COMPUTED_VALUE"""),45306) -> 45306 | AF8: =IFERROR(__xludf.DUMMYFUNCTION("""COMPUTED_VALUE"""),45352) -> 45352 | AG8: =IFERROR(__xludf.DUMMYFUNCTION("""COMPUTED_VALUE"""),45355) -> 45355 | AL8: =IFERROR(__xludf.DUMMYFUNCTION("""COMPUTED_VALUE"""),"〇") -> 〇 | AM8: =IFERROR(__xludf.DUMMYFUNCTION("""COMPUTED_VALUE"""),45181) -> 45181 | AN8: =IFERROR(__xludf.DUMMYFUNCTION("""COMPUTED_VALUE"""),"2025/8/1～2028/8/31") -> 2025/8/1～2028/8/31 | AO8: =IFERROR(__xludf.DUMMYFUNCTION("""COMPUTED_VALUE"""),"伊予銀") -> 伊予銀 | AP8: =IFERROR(__xludf.DUMMYFUNCTION("""COMPUTED_VALUE"""),"特定技能1号期間更新中 24.7.11 2024.6.21～ｱﾄﾑ504→三和ﾏﾝｼｮﾝ末広201へ引越 6/26住所変更済（中四国で） 家賃￥21500/人。家具家電は会社負担 奥さんｱｲﾝと一緒に住む 2025/7/24一時帰国から戻ってから在留ｶｰﾄﾞ更新予定⇒済9/29 2026.1月 特定2号受験予定") -> 特定技能1号期間更新中 24.7.11 2024.6.21～ｱﾄﾑ504→三和ﾏﾝｼｮﾝ末広201へ引越 6/26住所変更済（中四国で） 家賃￥21500/人。家具家電は会社負担 奥さんｱｲﾝと一緒に住む 2025/7/24一時帰国から戻ってから在留ｶｰﾄﾞ更新予定⇒済9/29 2026.1月 特定2号受験予定
B9: =IFERROR(__xludf.DUMMYFUNCTION("""COMPUTED_VALUE"""),36) -> 36 | C9: =IFERROR(__xludf.DUMMYFUNCTION("""COMPUTED_VALUE"""),"本社") -> 本社 | D9: =IFERROR(__xludf.DUMMYFUNCTION("""COMPUTED_VALUE"""),"ベトナム") -> ベトナム | E9: =IFERROR(__xludf.DUMMYFUNCTION("""COMPUTED_VALUE"""),"07001617") -> 07001617 | F9: =IFERROR(__xludf.DUMMYFUNCTION("""COMPUTED_VALUE"""),"/appsheet/photograph/36.写真.225148.jpg") -> /appsheet/photograph/36.写真.225148.jpg | G9: =IFERROR(__xludf.DUMMYFUNCTION("""COMPUTED_VALUE"""),"グエン タイン ド―") -> グエン タイン ド― | H9: =IFERROR(__xludf.DUMMYFUNCTION("""COMPUTED_VALUE"""),"NGUYEN THANH DO") -> NGUYEN THANH DO | I9: =IFERROR(__xludf.DUMMYFUNCTION("""COMPUTED_VALUE"""),"ドー") -> ドー | J9: =IFERROR(__xludf.DUMMYFUNCTION("""COMPUTED_VALUE"""),"男") -> 男 | K9: =IFERROR(__xludf.DUMMYFUNCTION("""COMPUTED_VALUE"""),33529) -> 33529 | L9: =IFERROR(__xludf.DUMMYFUNCTION("""COMPUTED_VALUE"""),34) -> 34 | M9: =IFERROR(__xludf.DUMMYFUNCTION("""COMPUTED_VALUE"""),"有") -> 有 | N9: =IFERROR(__xludf.DUMMYFUNCTION("""COMPUTED_VALUE"""),"中四国") -> 中四国 | O9: =IFERROR(__xludf.DUMMYFUNCTION("""COMPUTED_VALUE"""),44221) -> 44221 | P9: =IFERROR(__xludf.DUMMYFUNCTION("""COMPUTED_VALUE"""),"2028/12") -> 2028/12 | Q9: =IFERROR(__xludf.DUMMYFUNCTION("""COMPUTED_VALUE"""),"特定技能１号") -> 特定技能１号 | R9: =IFERROR(__xludf.DUMMYFUNCTION("""COMPUTED_VALUE"""),"和泉北1-20-28アトムスカイマンション504") -> 和泉北1-20-28アトムスカイマンション504 | S9: =IFERROR(__xludf.DUMMYFUNCTION("""COMPUTED_VALUE"""),"相2") -> 相2 | T9: =IFERROR(__xludf.DUMMYFUNCTION("""COMPUTED_VALUE"""),20000) -> 20000 | U9: =IFERROR(__xludf.DUMMYFUNCTION("""COMPUTED_VALUE"""),45912) -> 45912 | V9: =IFERROR(__xludf.DUMMYFUNCTION("""COMPUTED_VALUE"""),46377) -> 46377 | W9: =IFERROR(__xludf.DUMMYFUNCTION("""COMPUTED_VALUE"""),"UH64477231PC") -> UH64477231PC | X9: =IFERROR(__xludf.DUMMYFUNCTION("""COMPUTED_VALUE"""),"5109-504178-2") -> 5109-504178-2 | Z9: =IFERROR(__xludf.DUMMYFUNCTION("""COMPUTED_VALUE"""),"2021/01購入 8561 B-0188561-1188") -> 2021/01購入 8561 B-0188561-1188 | AE9: =IFERROR(__xludf.DUMMYFUNCTION("""COMPUTED_VALUE"""),45677) -> 45677 | AF9: =IFERROR(__xludf.DUMMYFUNCTION("""COMPUTED_VALUE"""),45721) -> 45721 | AG9: =IFERROR(__xludf.DUMMYFUNCTION("""COMPUTED_VALUE"""),45723) -> 45723 | AJ9: =IFERROR(__xludf.DUMMYFUNCTION("""COMPUTED_VALUE"""),"関空⇔ハノイ 98,300-会社負担") -> 関空⇔ハノイ 98,300-会社負担 | AL9: =IFERROR(__xludf.DUMMYFUNCTION("""COMPUTED_VALUE"""),"―") -> ― | AN9: =IFERROR(__xludf.DUMMYFUNCTION("""COMPUTED_VALUE"""),"― 自転車保険加入済 2026/2/1～2027/2/1 1年間") -> ― 自転車保険加入済 2026/2/1～2027/2/1 1年間
B10: =IFERROR(__xludf.DUMMYFUNCTION("""COMPUTED_VALUE"""),131) -> 131 | C10: =IFERROR(__xludf.DUMMYFUNCTION("""COMPUTED_VALUE"""),"本社") -> 本社 | D10: =IFERROR(__xludf.DUMMYFUNCTION("""COMPUTED_VALUE"""),"ベトナム") -> ベトナム | E10: =IFERROR(__xludf.DUMMYFUNCTION("""COMPUTED_VALUE"""),"07001618") -> 07001618 | F10: =IFERROR(__xludf.DUMMYFUNCTION("""COMPUTED_VALUE"""),"/appsheet/photograph/131.写真.225308.jpg") -> /appsheet/photograph/131.写真.225308.jpg | G10: =IFERROR(__xludf.DUMMYFUNCTION("""COMPUTED_VALUE"""),"グエン タン ロン") -> グエン タン ロン | H10: =IFERROR(__xludf.DUMMYFUNCTION("""COMPUTED_VALUE"""),"NGUYEN THANG LONG") -> NGUYEN THANG LONG | I10: =IFERROR(__xludf.DUMMYFUNCTION("""COMPUTED_VALUE"""),"ロン") -> ロン | J10: =IFERROR(__xludf.DUMMYFUNCTION("""COMPUTED_VALUE"""),"男") -> 男 | K10: =IFERROR(__xludf.DUMMYFUNCTION("""COMPUTED_VALUE"""),36864) -> 36864 | L10: =IFERROR(__xludf.DUMMYFUNCTION("""COMPUTED_VALUE"""),25) -> 25 | M10: =IFERROR(__xludf.DUMMYFUNCTION("""COMPUTED_VALUE"""),"無") -> 無 | N10: =IFERROR(__xludf.DUMMYFUNCTION("""COMPUTED_VALUE"""),"中四国") -> 中四国 | O10: =IFERROR(__xludf.DUMMYFUNCTION("""COMPUTED_VALUE"""),44699) -> 44699 | P10: =IFERROR(__xludf.DUMMYFUNCTION("""COMPUTED_VALUE"""),"2030/04") -> 2030/04 | Q10: =IFERROR(__xludf.DUMMYFUNCTION("""COMPUTED_VALUE"""),"特定技能１号") -> 特定技能１号 | R10: =IFERROR(__xludf.DUMMYFUNCTION("""COMPUTED_VALUE"""),"和泉北1-20-28アトムスカイマンション404") -> 和泉北1-20-28アトムスカイマンション404 | S10: =IFERROR(__xludf.DUMMYFUNCTION("""COMPUTED_VALUE"""),"個1") -> 個1 | T10: =IFERROR(__xludf.DUMMYFUNCTION("""COMPUTED_VALUE"""),20000) -> 20000 | U10: =IFERROR(__xludf.DUMMYFUNCTION("""COMPUTED_VALUE"""),46082) -> 46082 | V10: =IFERROR(__xludf.DUMMYFUNCTION("""COMPUTED_VALUE"""),46171) -> 46171 | W10: =IFERROR(__xludf.DUMMYFUNCTION("""COMPUTED_VALUE"""),"UH94536849PA") -> UH94536849PA | Y10: =IFERROR(__xludf.DUMMYFUNCTION("""COMPUTED_VALUE"""),45978) -> 45978 | Z10: =IFERROR(__xludf.DUMMYFUNCTION("""COMPUTED_VALUE"""),"7909-202511盗難届済 B-0247909-1593鍵回収 代替B-0246656-1610 2026.4.3 代替自転車も盗難された") -> 7909-202511盗難届済 B-0247909-1593鍵回収 代替B-0246656-1610 2026.4.3 代替自転車も盗難された | AC10: =IFERROR(__xludf.DUMMYFUNCTION("""COMPUTED_VALUE"""),"缶詰巻締専門 2024/09/12") -> 缶詰巻締専門 2024/09/12 | AJ10: =IFERROR(__xludf.DUMMYFUNCTION("""COMPUTED_VALUE"""),"4/15広島→ハノイ 42,000-会社負担 実習終了帰国") -> 4/15広島→ハノイ 42,000-会社負担 実習終了帰国 | AL10: =IFERROR(__xludf.DUMMYFUNCTION("""COMPUTED_VALUE"""),"―") -> ― | AN10: =IFERROR(__xludf.DUMMYFUNCTION("""COMPUTED_VALUE"""),"―") -> ― | AP10: =IFERROR(__xludf.DUMMYFUNCTION("""COMPUTED_VALUE"""),"転職希望（大阪へ）× 中温残る 実習終了→特定技能申請中（2025.5） 2025.4.15～5.19一時帰国 2025.5.28～特定技能1号へ 社員ｺｰﾄﾞ変わる 2025/8/21～家賃20,000-") -> 転職希望（大阪へ）× 中温残る 実習終了→特定技能申請中（2025.5） 2025.4.15～5.19一時帰国 2025.5.28～特定技能1号へ 社員ｺｰﾄﾞ変わる 2025/8/21～家賃20,000-
B11: =IFERROR(__xludf.DUMMYFUNCTION("""COMPUTED_VALUE"""),132) -> 132 | C11: =IFERROR(__xludf.DUMMYFUNCTION("""COMPUTED_VALUE"""),"本社") -> 本社 | D11: =IFERROR(__xludf.DUMMYFUNCTION("""COMPUTED_VALUE"""),"ベトナム") -> ベトナム | E11: =IFERROR(__xludf.DUMMYFUNCTION("""COMPUTED_VALUE"""),"07001619") -> 07001619 | F11: =IFERROR(__xludf.DUMMYFUNCTION("""COMPUTED_VALUE"""),"/appsheet/photograph/132.写真.225249.jpg") -> /appsheet/photograph/132.写真.225249.jpg | G11: =IFERROR(__xludf.DUMMYFUNCTION("""COMPUTED_VALUE"""),"ダオ ヴァン ゴック") -> ダオ ヴァン ゴック | H11: =IFERROR(__xludf.DUMMYFUNCTION("""COMPUTED_VALUE"""),"DAO VAN NGOC") -> DAO VAN NGOC | I11: =IFERROR(__xludf.DUMMYFUNCTION("""COMPUTED_VALUE"""),"ゴック") -> ゴック | J11: =IFERROR(__xludf.DUMMYFUNCTION("""COMPUTED_VALUE"""),"男") -> 男 | K11: =IFERROR(__xludf.DUMMYFUNCTION("""COMPUTED_VALUE"""),36313) -> 36313 | L11: =IFERROR(__xludf.DUMMYFUNCTION("""COMPUTED_VALUE"""),26) -> 26 | M11: =IFERROR(__xludf.DUMMYFUNCTION("""COMPUTED_VALUE"""),"夫婦") -> 夫婦 | N11: =IFERROR(__xludf.DUMMYFUNCTION("""COMPUTED_VALUE"""),"中四国") -> 中四国 | O11: =IFERROR(__xludf.DUMMYFUNCTION("""COMPUTED_VALUE"""),44699) -> 44699 | P11: =IFERROR(__xludf.DUMMYFUNCTION("""COMPUTED_VALUE"""),"2030/04") -> 2030/04 | Q11: =IFERROR(__xludf.DUMMYFUNCTION("""COMPUTED_VALUE"""),"特定技能１号") -> 特定技能１号 | R11: =IFERROR(__xludf.DUMMYFUNCTION("""COMPUTED_VALUE"""),"和泉北1-20-28アトムスカイマンション406") -> 和泉北1-20-28アトムスカイマンション406 | S11: =IFERROR(__xludf.DUMMYFUNCTION("""COMPUTED_VALUE"""),"夫婦") -> 夫婦 | T11: =IFERROR(__xludf.DUMMYFUNCTION("""COMPUTED_VALUE"""),22500) -> 22500 | U11: =IFERROR(__xludf.DUMMYFUNCTION("""COMPUTED_VALUE"""),46047) -> 46047 | V11: =IFERROR(__xludf.DUMMYFUNCTION("""COMPUTED_VALUE"""),47223) -> 47223 | W11: =IFERROR(__xludf.DUMMYFUNCTION("""COMPUTED_VALUE"""),"LJ20876296PC") -> LJ20876296PC | Z11: =IFERROR(__xludf.DUMMYFUNCTION("""COMPUTED_VALUE"""),"7910 B-0247910-1610") -> 7910 B-0247910-1610 | AB11: =IFERROR(__xludf.DUMMYFUNCTION("""COMPUTED_VALUE"""),"N4 2024/12/01") -> N4 2024/12/01 | AC11: =IFERROR(__xludf.DUMMYFUNCTION("""COMPUTED_VALUE"""),"缶詰巻締専門 2024/09/12") -> 缶詰巻締専門 2024/09/12 | AE11: =IFERROR(__xludf.DUMMYFUNCTION("""COMPUTED_VALUE"""),45772) -> 45772 | AF11: =IFERROR(__xludf.DUMMYFUNCTION("""COMPUTED_VALUE"""),45818) -> 45818 | AL11: =IFERROR(__xludf.DUMMYFUNCTION("""COMPUTED_VALUE"""),"―") -> ― | AM11: =IFERROR(__xludf.DUMMYFUNCTION("""COMPUTED_VALUE"""),45762) -> 45762 | AN11: =IFERROR(__xludf.DUMMYFUNCTION("""COMPUTED_VALUE"""),"―") -> ― | AO11: =IFERROR(__xludf.DUMMYFUNCTION("""COMPUTED_VALUE"""),"ひめぎん 末広町支店") -> ひめぎん 末広町支店 | AP11: =IFERROR(__xludf.DUMMYFUNCTION("""COMPUTED_VALUE"""),"2025.4/25～6/10一時帰国、2025.6.11～出社 技能実習２号終了→特定技能１号 中温残る 実習終了後、一時帰国希望 時給1,050以上希望i出産帰国中のタオさんと２人で生活希望(アトムで) 今回の更新については、最低1,000円＋日本語検定2025/8/21～家賃20,000- 2026.1.21引越アトム404→アトム406へ 奥さんタオの入社に合わせて一緒に住む予定 家賃￥22500へ ゴックの妹が入寮したら、ゴックとタオの家賃を要相談") -> 2025.4/25～6/10一時帰国、2025.6.11～出社 技能実習２号終了→特定技能１号 中温残る 実習終了後、一時帰国希望 時給1,050以上希望i出産帰国中のタオさんと２人で生活希望(アトムで) 今回の更新については、最低1,000円＋日本語検定2025/8/21～家賃20,000- 2026.1.21引越アトム404→アトム406へ 奥さんタオの入社に合わせて一緒に住む予定 家賃￥22500へ ゴックの妹が入寮したら、ゴックとタオの家賃を要相談
B12: =IFERROR(__xludf.DUMMYFUNCTION("""COMPUTED_VALUE"""),133) -> 133 | C12: =IFERROR(__xludf.DUMMYFUNCTION("""COMPUTED_VALUE"""),"本社") -> 本社 | D12: =IFERROR(__xludf.DUMMYFUNCTION("""COMPUTED_VALUE"""),"ベトナム") -> ベトナム | E12: =IFERROR(__xludf.DUMMYFUNCTION("""COMPUTED_VALUE"""),"07001620") -> 07001620 | F12: =IFERROR(__xludf.DUMMYFUNCTION("""COMPUTED_VALUE"""),"/appsheet/photograph/133.写真.034935.jpg") -> /appsheet/photograph/133.写真.034935.jpg | G12: =IFERROR(__xludf.DUMMYFUNCTION("""COMPUTED_VALUE"""),"ルオン トゥアン リン") -> ルオン トゥアン リン | H12: =IFERROR(__xludf.DUMMYFUNCTION("""COMPUTED_VALUE"""),"LUONG TUAN LINH") -> LUONG TUAN LINH | I12: =IFERROR(__xludf.DUMMYFUNCTION("""COMPUTED_VALUE"""),"ルオン") -> ルオン | J12: =IFERROR(__xludf.DUMMYFUNCTION("""COMPUTED_VALUE"""),"男") -> 男 | K12: =IFERROR(__xludf.DUMMYFUNCTION("""COMPUTED_VALUE"""),34672) -> 34672 | L12: =IFERROR(__xludf.DUMMYFUNCTION("""COMPUTED_VALUE"""),31) -> 31 | M12: =IFERROR(__xludf.DUMMYFUNCTION("""COMPUTED_VALUE"""),"夫婦") -> 夫婦 | N12: =IFERROR(__xludf.DUMMYFUNCTION("""COMPUTED_VALUE"""),"中四国") -> 中四国 | O12: =IFERROR(__xludf.DUMMYFUNCTION("""COMPUTED_VALUE"""),44699) -> 44699 | P12: =IFERROR(__xludf.DUMMYFUNCTION("""COMPUTED_VALUE"""),"2030/04") -> 2030/04 | Q12: =IFERROR(__xludf.DUMMYFUNCTION("""COMPUTED_VALUE"""),"特定技能１号") -> 特定技能１号 | R12: =IFERROR(__xludf.DUMMYFUNCTION("""COMPUTED_VALUE"""),"和泉北1-20-28アトムスカイマンション506") -> 和泉北1-20-28アトムスカイマンション506 | S12: =IFERROR(__xludf.DUMMYFUNCTION("""COMPUTED_VALUE"""),"夫婦") -> 夫婦 | T12: =IFERROR(__xludf.DUMMYFUNCTION("""COMPUTED_VALUE"""),22500) -> 22500 | U12: =IFERROR(__xludf.DUMMYFUNCTION("""COMPUTED_VALUE"""),46047) -> 46047 | V12: =IFERROR(__xludf.DUMMYFUNCTION("""COMPUTED_VALUE"""),47223) -> 47223 | W12: =IFERROR(__xludf.DUMMYFUNCTION("""COMPUTED_VALUE"""),"LJ78088029PC") -> LJ78088029PC | Z12: =IFERROR(__xludf.DUMMYFUNCTION("""COMPUTED_VALUE"""),"7911 B-0247911-1115") -> 7911 B-0247911-1115 | AB12: =IFERROR(__xludf.DUMMYFUNCTION("""COMPUTED_VALUE"""),"N4 2024/07/07") -> N4 2024/07/07 | AC12: =IFERROR(__xludf.DUMMYFUNCTION("""COMPUTED_VALUE"""),"缶詰巻締専門 2024/09/12") -> 缶詰巻締専門 2024/09/12 | AE12: =IFERROR(__xludf.DUMMYFUNCTION("""COMPUTED_VALUE"""),45855) -> 45855 | AF12: =IFERROR(__xludf.DUMMYFUNCTION("""COMPUTED_VALUE"""),45886) -> 45886 | AL12: =IFERROR(__xludf.DUMMYFUNCTION("""COMPUTED_VALUE"""),"〇") -> 〇 | AM12: =IFERROR(__xludf.DUMMYFUNCTION("""COMPUTED_VALUE"""),45762) -> 45762 | AN12: =IFERROR(__xludf.DUMMYFUNCTION("""COMPUTED_VALUE"""),"2025/9/15-2030/4/14") -> 2025/9/15-2030/4/14 | AO12: =IFERROR(__xludf.DUMMYFUNCTION("""COMPUTED_VALUE"""),"ひめぎん 末広町支店") -> ひめぎん 末広町支店 | AP12: =IFERROR(__xludf.DUMMYFUNCTION("""COMPUTED_VALUE"""),"技能実習２号終了→特定技能１号 中温残る 実習終了後、一時帰国希望 残業増やしたい 時給1,060以上希望 １人部屋or１人暮希望 ゴックがいる間は2人でOK ハー ティ タイン アンと結婚 2025/8 一時帰国後、アンと一緒に住む予定（ｱﾄﾑ404→ｱﾄﾑ506へ）8/21～家賃￥22500") -> 技能実習２号終了→特定技能１号 中温残る 実習終了後、一時帰国希望 残業増やしたい 時給1,060以上希望 １人部屋or１人暮希望 ゴックがいる間は2人でOK ハー ティ タイン アンと結婚 2025/8 一時帰国後、アンと一緒に住む予定（ｱﾄﾑ404→ｱﾄﾑ506へ）8/21～家賃￥22500
B13: =IFERROR(__xludf.DUMMYFUNCTION("""COMPUTED_VALUE"""),137) -> 137 | C13: =IFERROR(__xludf.DUMMYFUNCTION("""COMPUTED_VALUE"""),"本社") -> 本社 | D13: =IFERROR(__xludf.DUMMYFUNCTION("""COMPUTED_VALUE"""),"ベトナム") -> ベトナム | E13: =IFERROR(__xludf.DUMMYFUNCTION("""COMPUTED_VALUE"""),"07001622") -> 07001622 | F13: =IFERROR(__xludf.DUMMYFUNCTION("""COMPUTED_VALUE"""),"/appsheet/photograph/137.写真.035239.jpg") -> /appsheet/photograph/137.写真.035239.jpg | G13: =IFERROR(__xludf.DUMMYFUNCTION("""COMPUTED_VALUE"""),"ハー ティ タイン アン") -> ハー ティ タイン アン | H13: =IFERROR(__xludf.DUMMYFUNCTION("""COMPUTED_VALUE"""),"HA THI THANH AN") -> HA THI THANH AN | I13: =IFERROR(__xludf.DUMMYFUNCTION("""COMPUTED_VALUE"""),"アン") -> アン | J13: =IFERROR(__xludf.DUMMYFUNCTION("""COMPUTED_VALUE"""),"女") -> 女 | K13: =IFERROR(__xludf.DUMMYFUNCTION("""COMPUTED_VALUE"""),36759) -> 36759 | L13: =IFERROR(__xludf.DUMMYFUNCTION("""COMPUTED_VALUE"""),25) -> 25 | M13: =IFERROR(__xludf.DUMMYFUNCTION("""COMPUTED_VALUE"""),"夫婦") -> 夫婦 | N13: =IFERROR(__xludf.DUMMYFUNCTION("""COMPUTED_VALUE"""),"中四国") -> 中四国 | O13: =IFERROR(__xludf.DUMMYFUNCTION("""COMPUTED_VALUE"""),44699) -> 44699 | P13: =IFERROR(__xludf.DUMMYFUNCTION("""COMPUTED_VALUE"""),"2030/04") -> 2030/04 | Q13: =IFERROR(__xludf.DUMMYFUNCTION("""COMPUTED_VALUE"""),"特定技能１号") -> 特定技能１号 | R13: =IFERROR(__xludf.DUMMYFUNCTION("""COMPUTED_VALUE"""),"和泉北1-20-28アトムスカイマンション506") -> 和泉北1-20-28アトムスカイマンション506 | S13: =IFERROR(__xludf.DUMMYFUNCTION("""COMPUTED_VALUE"""),"夫婦") -> 夫婦 | T13: =IFERROR(__xludf.DUMMYFUNCTION("""COMPUTED_VALUE"""),22500) -> 22500 | U13: =IFERROR(__xludf.DUMMYFUNCTION("""COMPUTED_VALUE"""),46047) -> 46047 | V13: =IFERROR(__xludf.DUMMYFUNCTION("""COMPUTED_VALUE"""),47223) -> 47223 | W13: =IFERROR(__xludf.DUMMYFUNCTION("""COMPUTED_VALUE"""),"LJ28117156PC") -> LJ28117156PC | Z13: =IFERROR(__xludf.DUMMYFUNCTION("""COMPUTED_VALUE"""),"7915 B-0247915-1075") -> 7915 B-0247915-1075 | AC13: =IFERROR(__xludf.DUMMYFUNCTION("""COMPUTED_VALUE"""),"缶詰巻締専門 2024/09/12") -> 缶詰巻締専門 2024/09/12 | AE13: =IFERROR(__xludf.DUMMYFUNCTION("""COMPUTED_VALUE"""),45855) -> 45855 | AF13: =IFERROR(__xludf.DUMMYFUNCTION("""COMPUTED_VALUE"""),45886) -> 45886 | AL13: =IFERROR(__xludf.DUMMYFUNCTION("""COMPUTED_VALUE"""),"〇") -> 〇 | AM13: =IFERROR(__xludf.DUMMYFUNCTION("""COMPUTED_VALUE"""),45762) -> 45762 | AN13: =IFERROR(__xludf.DUMMYFUNCTION("""COMPUTED_VALUE"""),"2025/9/15-2030/4/14") -> 2025/9/15-2030/4/14 | AO13: =IFERROR(__xludf.DUMMYFUNCTION("""COMPUTED_VALUE"""),"ひめぎん 末広町支店") -> ひめぎん 末広町支店 | AP13: =IFERROR(__xludf.DUMMYFUNCTION("""COMPUTED_VALUE"""),"技能実習２号終了→特定技能１号 中温残る 一時帰国予定なし １人部屋希望 ルオン トゥアン リンと結婚 2025/8 一時帰国後、ルオンと一緒に住む予定（ｱﾄﾑ402→ｱﾄﾑ506へ）8/21～家賃￥22500") -> 技能実習２号終了→特定技能１号 中温残る 一時帰国予定なし １人部屋希望 ルオン トゥアン リンと結婚 2025/8 一時帰国後、ルオンと一緒に住む予定（ｱﾄﾑ402→ｱﾄﾑ506へ）8/21～家賃￥22500
B14: =IFERROR(__xludf.DUMMYFUNCTION("""COMPUTED_VALUE"""),138) -> 138 | C14: =IFERROR(__xludf.DUMMYFUNCTION("""COMPUTED_VALUE"""),"本社") -> 本社 | D14: =IFERROR(__xludf.DUMMYFUNCTION("""COMPUTED_VALUE"""),"ベトナム") -> ベトナム | E14: =IFERROR(__xludf.DUMMYFUNCTION("""COMPUTED_VALUE"""),"07001623") -> 07001623 | F14: =IFERROR(__xludf.DUMMYFUNCTION("""COMPUTED_VALUE"""),"/appsheet/photograph/138.写真.224956.jpg") -> /appsheet/photograph/138.写真.224956.jpg | G14: =IFERROR(__xludf.DUMMYFUNCTION("""COMPUTED_VALUE"""),"レー ティ ダオ") -> レー ティ ダオ | H14: =IFERROR(__xludf.DUMMYFUNCTION("""COMPUTED_VALUE"""),"LE THI DAO") -> LE THI DAO | I14: =IFERROR(__xludf.DUMMYFUNCTION("""COMPUTED_VALUE"""),"ダオ") -> ダオ | J14: =IFERROR(__xludf.DUMMYFUNCTION("""COMPUTED_VALUE"""),"女") -> 女 | K14: =IFERROR(__xludf.DUMMYFUNCTION("""COMPUTED_VALUE"""),31894) -> 31894 | L14: =IFERROR(__xludf.DUMMYFUNCTION("""COMPUTED_VALUE"""),38) -> 38 | M14: =IFERROR(__xludf.DUMMYFUNCTION("""COMPUTED_VALUE"""),"有") -> 有 | N14: =IFERROR(__xludf.DUMMYFUNCTION("""COMPUTED_VALUE"""),"中四国") -> 中四国 | O14: =IFERROR(__xludf.DUMMYFUNCTION("""COMPUTED_VALUE"""),44699) -> 44699 | P14: =IFERROR(__xludf.DUMMYFUNCTION("""COMPUTED_VALUE"""),"2030/04") -> 2030/04 | Q14: =IFERROR(__xludf.DUMMYFUNCTION("""COMPUTED_VALUE"""),"特定技能１号") -> 特定技能１号 | R14: =IFERROR(__xludf.DUMMYFUNCTION("""COMPUTED_VALUE"""),"和泉北1-20-28アトムスカイマンション402") -> 和泉北1-20-28アトムスカイマンション402 | S14: =IFERROR(__xludf.DUMMYFUNCTION("""COMPUTED_VALUE"""),"個2") -> 個2 | T14: =IFERROR(__xludf.DUMMYFUNCTION("""COMPUTED_VALUE"""),20000) -> 20000 | U14: =IFERROR(__xludf.DUMMYFUNCTION("""COMPUTED_VALUE"""),46047) -> 46047 | V14: =IFERROR(__xludf.DUMMYFUNCTION("""COMPUTED_VALUE"""),47223) -> 47223 | W14: =IFERROR(__xludf.DUMMYFUNCTION("""COMPUTED_VALUE"""),"LJ48606238PC") -> LJ48606238PC | Z14: =IFERROR(__xludf.DUMMYFUNCTION("""COMPUTED_VALUE"""),"7916 B-0247916-1113") -> 7916 B-0247916-1113 | AB14: =IFERROR(__xludf.DUMMYFUNCTION("""COMPUTED_VALUE"""),"N3 2024/12/01") -> N3 2024/12/01 | AC14: =IFERROR(__xludf.DUMMYFUNCTION("""COMPUTED_VALUE"""),"缶詰巻締専門 2024/09/12") -> 缶詰巻締専門 2024/09/12 | AE14: =IFERROR(__xludf.DUMMYFUNCTION("""COMPUTED_VALUE"""),45846) -> 45846 | AF14: =IFERROR(__xludf.DUMMYFUNCTION("""COMPUTED_VALUE"""),45873) -> 45873 | AL14: =IFERROR(__xludf.DUMMYFUNCTION("""COMPUTED_VALUE"""),"〇") -> 〇 | AM14: =IFERROR(__xludf.DUMMYFUNCTION("""COMPUTED_VALUE"""),45762) -> 45762 | AN14: =IFERROR(__xludf.DUMMYFUNCTION("""COMPUTED_VALUE"""),"2025/9/15-2030/4/14") -> 2025/9/15-2030/4/14 | AO14: =IFERROR(__xludf.DUMMYFUNCTION("""COMPUTED_VALUE"""),"ひめぎん 末広町支店") -> ひめぎん 末広町支店 | AP14: =IFERROR(__xludf.DUMMYFUNCTION("""COMPUTED_VALUE"""),"技能実習２号終了→特定技能１号 中温残る 実習終了後、一時帰国希望 夫：今治で勤務 2025/8/21～家賃20,000-") -> 技能実習２号終了→特定技能１号 中温残る 実習終了後、一時帰国希望 夫：今治で勤務 2025/8/21～家賃20,000-
